{"dataRows":[{"taxon":{"displayName":"Egyptian Goose","commonName":"Egyptian Goose","sciName":"Alopochen aegyptiaca","speciesCode":"egygoo","category":"species","reportAsSpeciesCode":"egygoo","reportAsCategory":"species","showSpeciesPageLink":true},"values":[0.0,0.0,0.0,0.0,0.0,0.0,0.0,0.0,0.0,0.25,0.0,0.0,0.0,0.0,0.0,0.0,0.0,0.0,0.0,0.0,0.0,0.0,0.0,0.0,0.0,0.0,0.0,0.0,0.0,0.0,0.0,0.0,0.0,0.0,0.0,0.0,0.0,0.0,0.0,0.0,0.0,0.0,0.0,0.0,0.0,0.0,0.0,0.0],"prettyValues":["0%","0%","0%","0%","0%","0%","0%","0%","0%","25%","0%","0%","0%","0%","0%","0%","0%","0%","0%","0%","0%","0%","0%","0%","0%","0%","0%","0%","0%","0%","0%","0%","0%","0%","0%","0%","0%","0%","0%","0%","0%","0%","0%","0%","0%","0%","0%","0%"],"values_N":[0,0,0,0,0,0,0,0,0,4,0,0,0,0,0,0,0,0,0,0,0,0,0,0,0,0,0,0,1,0,0,0,0,0,0,0,0,0,0,0,0,0,0,0,0,0,0,0],"buckets":[-1,-1,-1,-1,-1,-1,-1,-1,-1,6,-1,-1,-1,-1,-1,-1,-1,-1,-1,-1,-1,-1,-1,-1,-1,-1,-1,-1,0,-1,-1,-1,-1,-1,-1,-1,-1,-1,-1,-1,-1,-1,-1,-1,-1,-1,-1,-1],"speciesCode":"egygoo","name":"Egyptian Goose"},{"taxon":{"displayName":"Speckled Pigeon","commonName":"Speckled Pigeon","sciName":"Columba guinea","speciesCode":"spepig1","category":"species","reportAsSpeciesCode":"spepig1","reportAsCategory":"species","showSpeciesPageLink":true},"values":[0.0,0.0,0.0,0.0,0.0,0.0,0.0,0.0,0.0,0.25,0.0,0.0,0.0,0.0,0.0,0.0,0.0,0.0,0.0,0.0,0.0,0.0,0.0,0.0,0.0,0.0,0.0,0.0,1.0,0.0,0.0,0.0,0.0,0.0,0.0,0.0,0.0,0.0,0.0,0.0,0.0,0.0,0.0,0.0,0.0,0.0,0.0,0.0],"prettyValues":["0%","0%","0%","0%","0%","0%","0%","0%","0%","25%","0%","0%","0%","0%","0%","0%","0%","0%","0%","0%","0%","0%","0%","0%","0%","0%","0%","0%","100%","0%","0%","0%","0%","0%","0%","0%","0%","0%","0%","0%","0%","0%","0%","0%","0%","0%","0%","0%"],"values_N":[0,0,0,0,0,0,0,0,0,4,0,0,0,0,0,0,0,0,0,0,0,0,0,0,0,0,0,0,1,0,0,0,0,0,0,0,0,0,0,0,0,0,0,0,0,0,0,0],"buckets":[-1,-1,-1,-1,-1,-1,-1,-1,-1,6,-1,-1,-1,-1,-1,-1,-1,-1,-1,-1,-1,-1,-1,-1,-1,-1,-1,-1,9,-1,-1,-1,-1,-1,-1,-1,-1,-1,-1,-1,-1,-1,-1,-1,-1,-1,-1,-1],"speciesCode":"spepig1","name":"Speckled Pigeon"},{"taxon":{"displayName":"Red-eyed Dove","commonName":"Red-eyed Dove","sciName":"Streptopelia semitorquata","speciesCode":"reedov1","category":"species","reportAsSpeciesCode":"reedov1","reportAsCategory":"species","showSpeciesPageLink":true},"values":[0.0,0.0,0.0,0.0,0.0,0.0,0.0,0.0,0.0,0.5,0.0,0.0,0.0,0.0,0.0,0.0,0.0,0.0,0.0,0.0,0.0,0.0,0.0,0.0,0.0,0.0,0.0,0.0,1.0,0.0,0.0,0.0,0.0,0.0,0.0,0.0,0.0,0.0,0.0,0.0,0.0,0.0,0.0,0.0,0.0,0.0,0.0,0.0],"prettyValues":["0%","0%","0%","0%","0%","0%","0%","0%","0%","50%","0%","0%","0%","0%","0%","0%","0%","0%","0%","0%","0%","0%","0%","0%","0%","0%","0%","0%","100%","0%","0%","0%","0%","0%","0%","0%","0%","0%","0%","0%","0%","0%","0%","0%","0%","0%","0%","0%"],"values_N":[0,0,0,0,0,0,0,0,0,4,0,0,0,0,0,0,0,0,0,0,0,0,0,0,0,0,0,0,1,0,0,0,0,0,0,0,0,0,0,0,0,0,0,0,0,0,0,0],"buckets":[-1,-1,-1,-1,-1,-1,-1,-1,-1,8,-1,-1,-1,-1,-1,-1,-1,-1,-1,-1,-1,-1,-1,-1,-1,-1,-1,-1,9,-1,-1,-1,-1,-1,-1,-1,-1,-1,-1,-1,-1,-1,-1,-1,-1,-1,-1,-1],"speciesCode":"reedov1","name":"Red-eyed Dove"},{"taxon":{"displayName":"Ring-necked Dove","commonName":"Ring-necked Dove","sciName":"Streptopelia capicola","speciesCode":"rindov","category":"species","reportAsSpeciesCode":"rindov","reportAsCategory":"species","showSpeciesPageLink":true},"values":[0.0,0.0,0.0,0.0,0.0,0.0,0.0,0.0,0.0,0.0,0.0,0.0,0.0,0.0,0.0,0.0,0.0,0.0,0.0,0.0,0.0,0.0,0.0,0.0,0.0,0.0,0.0,0.0,1.0,0.0,0.0,0.0,0.0,0.0,0.0,0.0,0.0,0.0,0.0,0.0,0.0,0.0,0.0,0.0,0.0,0.0,0.0,0.0],"prettyValues":["0%","0%","0%","0%","0%","0%","0%","0%","0%","0%","0%","0%","0%","0%","0%","0%","0%","0%","0%","0%","0%","0%","0%","0%","0%","0%","0%","0%","100%","0%","0%","0%","0%","0%","0%","0%","0%","0%","0%","0%","0%","0%","0%","0%","0%","0%","0%","0%"],"values_N":[0,0,0,0,0,0,0,0,0,4,0,0,0,0,0,0,0,0,0,0,0,0,0,0,0,0,0,0,1,0,0,0,0,0,0,0,0,0,0,0,0,0,0,0,0,0,0,0],"buckets":[-1,-1,-1,-1,-1,-1,-1,-1,-1,0,-1,-1,-1,-1,-1,-1,-1,-1,-1,-1,-1,-1,-1,-1,-1,-1,-1,-1,9,-1,-1,-1,-1,-1,-1,-1,-1,-1,-1,-1,-1,-1,-1,-1,-1,-1,-1,-1],"speciesCode":"rindov","name":"Ring-necked Dove"},{"taxon":{"displayName":"African Green-Pigeon","commonName":"African Green-Pigeon","sciName":"Treron calvus","speciesCode":"afrgrp1","category":"species","reportAsSpeciesCode":"afrgrp1","reportAsCategory":"species","showSpeciesPageLink":true},"values":[0.0,0.0,0.0,0.0,0.0,0.0,0.0,0.0,0.0,0.0,0.0,0.0,0.0,0.0,0.0,0.0,0.0,0.0,0.0,0.0,0.0,0.0,0.0,0.0,0.0,0.0,0.0,0.0,1.0,0.0,0.0,0.0,0.0,0.0,0.0,0.0,0.0,0.0,0.0,0.0,0.0,0.0,0.0,0.0,0.0,0.0,0.0,0.0],"prettyValues":["0%","0%","0%","0%","0%","0%","0%","0%","0%","0%","0%","0%","0%","0%","0%","0%","0%","0%","0%","0%","0%","0%","0%","0%","0%","0%","0%","0%","100%","0%","0%","0%","0%","0%","0%","0%","0%","0%","0%","0%","0%","0%","0%","0%","0%","0%","0%","0%"],"values_N":[0,0,0,0,0,0,0,0,0,4,0,0,0,0,0,0,0,0,0,0,0,0,0,0,0,0,0,0,1,0,0,0,0,0,0,0,0,0,0,0,0,0,0,0,0,0,0,0],"buckets":[-1,-1,-1,-1,-1,-1,-1,-1,-1,0,-1,-1,-1,-1,-1,-1,-1,-1,-1,-1,-1,-1,-1,-1,-1,-1,-1,-1,9,-1,-1,-1,-1,-1,-1,-1,-1,-1,-1,-1,-1,-1,-1,-1,-1,-1,-1,-1],"speciesCode":"afrgrp1","name":"African Green-Pigeon"},{"taxon":{"displayName":"Hartlaub's Turaco","commonName":"Hartlaub's Turaco","sciName":"Tauraco hartlaubi","speciesCode":"hartur1","category":"species","reportAsSpeciesCode":"hartur1","reportAsCategory":"species","showSpeciesPageLink":true},"values":[0.0,0.0,0.0,0.0,0.0,0.0,0.0,0.0,0.0,0.25,0.0,0.0,0.0,0.0,0.0,0.0,0.0,0.0,0.0,0.0,0.0,0.0,0.0,0.0,0.0,0.0,0.0,0.0,0.0,0.0,0.0,0.0,0.0,0.0,0.0,0.0,0.0,0.0,0.0,0.0,0.0,0.0,0.0,0.0,0.0,0.0,0.0,0.0],"prettyValues":["0%","0%","0%","0%","0%","0%","0%","0%","0%","25%","0%","0%","0%","0%","0%","0%","0%","0%","0%","0%","0%","0%","0%","0%","0%","0%","0%","0%","0%","0%","0%","0%","0%","0%","0%","0%","0%","0%","0%","0%","0%","0%","0%","0%","0%","0%","0%","0%"],"values_N":[0,0,0,0,0,0,0,0,0,4,0,0,0,0,0,0,0,0,0,0,0,0,0,0,0,0,0,0,1,0,0,0,0,0,0,0,0,0,0,0,0,0,0,0,0,0,0,0],"buckets":[-1,-1,-1,-1,-1,-1,-1,-1,-1,6,-1,-1,-1,-1,-1,-1,-1,-1,-1,-1,-1,-1,-1,-1,-1,-1,-1,-1,0,-1,-1,-1,-1,-1,-1,-1,-1,-1,-1,-1,-1,-1,-1,-1,-1,-1,-1,-1],"speciesCode":"hartur1","name":"Hartlaub's Turaco"},{"taxon":{"displayName":"Abyssinian Nightjar","commonName":"Abyssinian Nightjar","sciName":"Caprimulgus poliocephalus","speciesCode":"abynig1","category":"species","reportAsSpeciesCode":"abynig1","reportAsCategory":"species","showSpeciesPageLink":true},"values":[0.0,0.0,0.0,0.0,0.0,0.0,0.0,0.0,0.0,0.0,0.0,0.0,0.0,0.0,0.0,0.0,0.0,0.0,0.0,0.0,0.0,0.0,0.0,0.0,0.0,0.0,0.0,0.0,1.0,0.0,0.0,0.0,0.0,0.0,0.0,0.0,0.0,0.0,0.0,0.0,0.0,0.0,0.0,0.0,0.0,0.0,0.0,0.0],"prettyValues":["0%","0%","0%","0%","0%","0%","0%","0%","0%","0%","0%","0%","0%","0%","0%","0%","0%","0%","0%","0%","0%","0%","0%","0%","0%","0%","0%","0%","100%","0%","0%","0%","0%","0%","0%","0%","0%","0%","0%","0%","0%","0%","0%","0%","0%","0%","0%","0%"],"values_N":[0,0,0,0,0,0,0,0,0,4,0,0,0,0,0,0,0,0,0,0,0,0,0,0,0,0,0,0,1,0,0,0,0,0,0,0,0,0,0,0,0,0,0,0,0,0,0,0],"buckets":[-1,-1,-1,-1,-1,-1,-1,-1,-1,0,-1,-1,-1,-1,-1,-1,-1,-1,-1,-1,-1,-1,-1,-1,-1,-1,-1,-1,9,-1,-1,-1,-1,-1,-1,-1,-1,-1,-1,-1,-1,-1,-1,-1,-1,-1,-1,-1],"speciesCode":"abynig1","name":"Abyssinian Nightjar"},{"taxon":{"displayName":"Little Swift","commonName":"Little Swift","sciName":"Apus affinis","speciesCode":"litswi1","category":"species","reportAsSpeciesCode":"litswi1","reportAsCategory":"species","showSpeciesPageLink":true},"values":[0.0,0.0,0.0,0.0,0.0,0.0,0.0,0.0,0.0,0.5,0.0,0.0,0.0,0.0,0.0,0.0,0.0,0.0,0.0,0.0,0.0,0.0,0.0,0.0,0.0,0.0,0.0,0.0,1.0,0.0,0.0,0.0,0.0,0.0,0.0,0.0,0.0,0.0,0.0,0.0,0.0,0.0,0.0,0.0,0.0,0.0,0.0,0.0],"prettyValues":["0%","0%","0%","0%","0%","0%","0%","0%","0%","50%","0%","0%","0%","0%","0%","0%","0%","0%","0%","0%","0%","0%","0%","0%","0%","0%","0%","0%","100%","0%","0%","0%","0%","0%","0%","0%","0%","0%","0%","0%","0%","0%","0%","0%","0%","0%","0%","0%"],"values_N":[0,0,0,0,0,0,0,0,0,4,0,0,0,0,0,0,0,0,0,0,0,0,0,0,0,0,0,0,1,0,0,0,0,0,0,0,0,0,0,0,0,0,0,0,0,0,0,0],"buckets":[-1,-1,-1,-1,-1,-1,-1,-1,-1,8,-1,-1,-1,-1,-1,-1,-1,-1,-1,-1,-1,-1,-1,-1,-1,-1,-1,-1,9,-1,-1,-1,-1,-1,-1,-1,-1,-1,-1,-1,-1,-1,-1,-1,-1,-1,-1,-1],"speciesCode":"litswi1","name":"Little Swift"},{"taxon":{"displayName":"Hadada Ibis","commonName":"Hadada Ibis","sciName":"Bostrychia hagedash","speciesCode":"hadibi1","category":"species","reportAsSpeciesCode":"hadibi1","reportAsCategory":"species","showSpeciesPageLink":true},"values":[0.0,0.0,0.0,0.0,0.0,0.0,0.0,0.0,0.0,0.75,0.0,0.0,0.0,0.0,0.0,0.0,0.0,0.0,0.0,0.0,0.0,0.0,0.0,0.0,0.0,0.0,0.0,0.0,1.0,0.0,0.0,0.0,0.0,0.0,0.0,0.0,0.0,0.0,0.0,0.0,0.0,0.0,0.0,0.0,0.0,0.0,0.0,0.0],"prettyValues":["0%","0%","0%","0%","0%","0%","0%","0%","0%","75%","0%","0%","0%","0%","0%","0%","0%","0%","0%","0%","0%","0%","0%","0%","0%","0%","0%","0%","100%","0%","0%","0%","0%","0%","0%","0%","0%","0%","0%","0%","0%","0%","0%","0%","0%","0%","0%","0%"],"values_N":[0,0,0,0,0,0,0,0,0,4,0,0,0,0,0,0,0,0,0,0,0,0,0,0,0,0,0,0,1,0,0,0,0,0,0,0,0,0,0,0,0,0,0,0,0,0,0,0],"buckets":[-1,-1,-1,-1,-1,-1,-1,-1,-1,9,-1,-1,-1,-1,-1,-1,-1,-1,-1,-1,-1,-1,-1,-1,-1,-1,-1,-1,9,-1,-1,-1,-1,-1,-1,-1,-1,-1,-1,-1,-1,-1,-1,-1,-1,-1,-1,-1],"speciesCode":"hadibi1","name":"Hadada Ibis"},{"taxon":{"displayName":"Eurasian Marsh-Harrier","commonName":"Eurasian Marsh-Harrier","sciName":"Circus aeruginosus","speciesCode":"wemhar1","category":"species","reportAsSpeciesCode":"wemhar1","reportAsCategory":"species","showSpeciesPageLink":true},"values":[0.0,0.0,0.0,0.0,0.0,0.0,0.0,0.0,0.0,0.25,0.0,0.0,0.0,0.0,0.0,0.0,0.0,0.0,0.0,0.0,0.0,0.0,0.0,0.0,0.0,0.0,0.0,0.0,0.0,0.0,0.0,0.0,0.0,0.0,0.0,0.0,0.0,0.0,0.0,0.0,0.0,0.0,0.0,0.0,0.0,0.0,0.0,0.0],"prettyValues":["0%","0%","0%","0%","0%","0%","0%","0%","0%","25%","0%","0%","0%","0%","0%","0%","0%","0%","0%","0%","0%","0%","0%","0%","0%","0%","0%","0%","0%","0%","0%","0%","0%","0%","0%","0%","0%","0%","0%","0%","0%","0%","0%","0%","0%","0%","0%","0%"],"values_N":[0,0,0,0,0,0,0,0,0,4,0,0,0,0,0,0,0,0,0,0,0,0,0,0,0,0,0,0,1,0,0,0,0,0,0,0,0,0,0,0,0,0,0,0,0,0,0,0],"buckets":[-1,-1,-1,-1,-1,-1,-1,-1,-1,6,-1,-1,-1,-1,-1,-1,-1,-1,-1,-1,-1,-1,-1,-1,-1,-1,-1,-1,0,-1,-1,-1,-1,-1,-1,-1,-1,-1,-1,-1,-1,-1,-1,-1,-1,-1,-1,-1],"speciesCode":"wemhar1","name":"Eurasian Marsh-Harrier"},{"taxon":{"displayName":"Augur Buzzard","commonName":"Augur Buzzard","sciName":"Buteo augur","speciesCode":"augbuz1","category":"species","reportAsSpeciesCode":"augbuz1","reportAsCategory":"species","showSpeciesPageLink":true},"values":[0.0,0.0,0.0,0.0,0.0,0.0,0.0,0.0,0.0,0.75,0.0,0.0,0.0,0.0,0.0,0.0,0.0,0.0,0.0,0.0,0.0,0.0,0.0,0.0,0.0,0.0,0.0,0.0,1.0,0.0,0.0,0.0,0.0,0.0,0.0,0.0,0.0,0.0,0.0,0.0,0.0,0.0,0.0,0.0,0.0,0.0,0.0,0.0],"prettyValues":["0%","0%","0%","0%","0%","0%","0%","0%","0%","75%","0%","0%","0%","0%","0%","0%","0%","0%","0%","0%","0%","0%","0%","0%","0%","0%","0%","0%","100%","0%","0%","0%","0%","0%","0%","0%","0%","0%","0%","0%","0%","0%","0%","0%","0%","0%","0%","0%"],"values_N":[0,0,0,0,0,0,0,0,0,4,0,0,0,0,0,0,0,0,0,0,0,0,0,0,0,0,0,0,1,0,0,0,0,0,0,0,0,0,0,0,0,0,0,0,0,0,0,0],"buckets":[-1,-1,-1,-1,-1,-1,-1,-1,-1,9,-1,-1,-1,-1,-1,-1,-1,-1,-1,-1,-1,-1,-1,-1,-1,-1,-1,-1,9,-1,-1,-1,-1,-1,-1,-1,-1,-1,-1,-1,-1,-1,-1,-1,-1,-1,-1,-1],"speciesCode":"augbuz1","name":"Augur Buzzard"},{"taxon":{"displayName":"Speckled Mousebird","commonName":"Speckled Mousebird","sciName":"Colius striatus","speciesCode":"spemou2","category":"species","reportAsSpeciesCode":"spemou2","reportAsCategory":"species","showSpeciesPageLink":true},"values":[0.0,0.0,0.0,0.0,0.0,0.0,0.0,0.0,0.0,0.75,0.0,0.0,0.0,0.0,0.0,0.0,0.0,0.0,0.0,0.0,0.0,0.0,0.0,0.0,0.0,0.0,0.0,0.0,1.0,0.0,0.0,0.0,0.0,0.0,0.0,0.0,0.0,0.0,0.0,0.0,0.0,0.0,0.0,0.0,0.0,0.0,0.0,0.0],"prettyValues":["0%","0%","0%","0%","0%","0%","0%","0%","0%","75%","0%","0%","0%","0%","0%","0%","0%","0%","0%","0%","0%","0%","0%","0%","0%","0%","0%","0%","100%","0%","0%","0%","0%","0%","0%","0%","0%","0%","0%","0%","0%","0%","0%","0%","0%","0%","0%","0%"],"values_N":[0,0,0,0,0,0,0,0,0,4,0,0,0,0,0,0,0,0,0,0,0,0,0,0,0,0,0,0,1,0,0,0,0,0,0,0,0,0,0,0,0,0,0,0,0,0,0,0],"buckets":[-1,-1,-1,-1,-1,-1,-1,-1,-1,9,-1,-1,-1,-1,-1,-1,-1,-1,-1,-1,-1,-1,-1,-1,-1,-1,-1,-1,9,-1,-1,-1,-1,-1,-1,-1,-1,-1,-1,-1,-1,-1,-1,-1,-1,-1,-1,-1],"speciesCode":"spemou2","name":"Speckled Mousebird"},{"taxon":{"displayName":"Eurasian Hoopoe","commonName":"Eurasian Hoopoe","sciName":"Upupa epops","speciesCode":"hoopoe","category":"species","reportAsSpeciesCode":"hoopoe","reportAsCategory":"species","showSpeciesPageLink":true},"values":[0.0,0.0,0.0,0.0,0.0,0.0,0.0,0.0,0.0,0.25,0.0,0.0,0.0,0.0,0.0,0.0,0.0,0.0,0.0,0.0,0.0,0.0,0.0,0.0,0.0,0.0,0.0,0.0,1.0,0.0,0.0,0.0,0.0,0.0,0.0,0.0,0.0,0.0,0.0,0.0,0.0,0.0,0.0,0.0,0.0,0.0,0.0,0.0],"prettyValues":["0%","0%","0%","0%","0%","0%","0%","0%","0%","25%","0%","0%","0%","0%","0%","0%","0%","0%","0%","0%","0%","0%","0%","0%","0%","0%","0%","0%","100%","0%","0%","0%","0%","0%","0%","0%","0%","0%","0%","0%","0%","0%","0%","0%","0%","0%","0%","0%"],"values_N":[0,0,0,0,0,0,0,0,0,4,0,0,0,0,0,0,0,0,0,0,0,0,0,0,0,0,0,0,1,0,0,0,0,0,0,0,0,0,0,0,0,0,0,0,0,0,0,0],"buckets":[-1,-1,-1,-1,-1,-1,-1,-1,-1,6,-1,-1,-1,-1,-1,-1,-1,-1,-1,-1,-1,-1,-1,-1,-1,-1,-1,-1,9,-1,-1,-1,-1,-1,-1,-1,-1,-1,-1,-1,-1,-1,-1,-1,-1,-1,-1,-1],"speciesCode":"hoopoe","name":"Eurasian Hoopoe"},{"taxon":{"displayName":"Silvery-cheeked Hornbill","commonName":"Silvery-cheeked Hornbill","sciName":"Bycanistes brevis","speciesCode":"sichor1","category":"species","reportAsSpeciesCode":"sichor1","reportAsCategory":"species","showSpeciesPageLink":true},"values":[0.0,0.0,0.0,0.0,0.0,0.0,0.0,0.0,0.0,0.25,0.0,0.0,0.0,0.0,0.0,0.0,0.0,0.0,0.0,0.0,0.0,0.0,0.0,0.0,0.0,0.0,0.0,0.0,0.0,0.0,0.0,0.0,0.0,0.0,0.0,0.0,0.0,0.0,0.0,0.0,0.0,0.0,0.0,0.0,0.0,0.0,0.0,0.0],"prettyValues":["0%","0%","0%","0%","0%","0%","0%","0%","0%","25%","0%","0%","0%","0%","0%","0%","0%","0%","0%","0%","0%","0%","0%","0%","0%","0%","0%","0%","0%","0%","0%","0%","0%","0%","0%","0%","0%","0%","0%","0%","0%","0%","0%","0%","0%","0%","0%","0%"],"values_N":[0,0,0,0,0,0,0,0,0,4,0,0,0,0,0,0,0,0,0,0,0,0,0,0,0,0,0,0,1,0,0,0,0,0,0,0,0,0,0,0,0,0,0,0,0,0,0,0],"buckets":[-1,-1,-1,-1,-1,-1,-1,-1,-1,6,-1,-1,-1,-1,-1,-1,-1,-1,-1,-1,-1,-1,-1,-1,-1,-1,-1,-1,0,-1,-1,-1,-1,-1,-1,-1,-1,-1,-1,-1,-1,-1,-1,-1,-1,-1,-1,-1],"speciesCode":"sichor1","name":"Silvery-cheeked Hornbill"},{"taxon":{"displayName":"Nubian Woodpecker","commonName":"Nubian Woodpecker","sciName":"Campethera nubica","speciesCode":"nubwoo1","category":"species","reportAsSpeciesCode":"nubwoo1","reportAsCategory":"species","showSpeciesPageLink":true},"values":[0.0,0.0,0.0,0.0,0.0,0.0,0.0,0.0,0.0,0.25,0.0,0.0,0.0,0.0,0.0,0.0,0.0,0.0,0.0,0.0,0.0,0.0,0.0,0.0,0.0,0.0,0.0,0.0,1.0,0.0,0.0,0.0,0.0,0.0,0.0,0.0,0.0,0.0,0.0,0.0,0.0,0.0,0.0,0.0,0.0,0.0,0.0,0.0],"prettyValues":["0%","0%","0%","0%","0%","0%","0%","0%","0%","25%","0%","0%","0%","0%","0%","0%","0%","0%","0%","0%","0%","0%","0%","0%","0%","0%","0%","0%","100%","0%","0%","0%","0%","0%","0%","0%","0%","0%","0%","0%","0%","0%","0%","0%","0%","0%","0%","0%"],"values_N":[0,0,0,0,0,0,0,0,0,4,0,0,0,0,0,0,0,0,0,0,0,0,0,0,0,0,0,0,1,0,0,0,0,0,0,0,0,0,0,0,0,0,0,0,0,0,0,0],"buckets":[-1,-1,-1,-1,-1,-1,-1,-1,-1,6,-1,-1,-1,-1,-1,-1,-1,-1,-1,-1,-1,-1,-1,-1,-1,-1,-1,-1,9,-1,-1,-1,-1,-1,-1,-1,-1,-1,-1,-1,-1,-1,-1,-1,-1,-1,-1,-1],"speciesCode":"nubwoo1","name":"Nubian Woodpecker"},{"taxon":{"displayName":"Meyer's Parrot","commonName":"Meyer's Parrot","sciName":"Poicephalus meyeri","speciesCode":"meypar1","category":"species","reportAsSpeciesCode":"meypar1","reportAsCategory":"species","showSpeciesPageLink":true},"values":[0.0,0.0,0.0,0.0,0.0,0.0,0.0,0.0,0.0,0.75,0.0,0.0,0.0,0.0,0.0,0.0,0.0,0.0,0.0,0.0,0.0,0.0,0.0,0.0,0.0,0.0,0.0,0.0,1.0,0.0,0.0,0.0,0.0,0.0,0.0,0.0,0.0,0.0,0.0,0.0,0.0,0.0,0.0,0.0,0.0,0.0,0.0,0.0],"prettyValues":["0%","0%","0%","0%","0%","0%","0%","0%","0%","75%","0%","0%","0%","0%","0%","0%","0%","0%","0%","0%","0%","0%","0%","0%","0%","0%","0%","0%","100%","0%","0%","0%","0%","0%","0%","0%","0%","0%","0%","0%","0%","0%","0%","0%","0%","0%","0%","0%"],"values_N":[0,0,0,0,0,0,0,0,0,4,0,0,0,0,0,0,0,0,0,0,0,0,0,0,0,0,0,0,1,0,0,0,0,0,0,0,0,0,0,0,0,0,0,0,0,0,0,0],"buckets":[-1,-1,-1,-1,-1,-1,-1,-1,-1,9,-1,-1,-1,-1,-1,-1,-1,-1,-1,-1,-1,-1,-1,-1,-1,-1,-1,-1,9,-1,-1,-1,-1,-1,-1,-1,-1,-1,-1,-1,-1,-1,-1,-1,-1,-1,-1,-1],"speciesCode":"meypar1","name":"Meyer's Parrot"},{"taxon":{"displayName":"Chinspot Batis","commonName":"Chinspot Batis","sciName":"Batis molitor","speciesCode":"chibat1","category":"species","reportAsSpeciesCode":"chibat1","reportAsCategory":"species","showSpeciesPageLink":true},"values":[0.0,0.0,0.0,0.0,0.0,0.0,0.0,0.0,0.0,0.25,0.0,0.0,0.0,0.0,0.0,0.0,0.0,0.0,0.0,0.0,0.0,0.0,0.0,0.0,0.0,0.0,0.0,0.0,0.0,0.0,0.0,0.0,0.0,0.0,0.0,0.0,0.0,0.0,0.0,0.0,0.0,0.0,0.0,0.0,0.0,0.0,0.0,0.0],"prettyValues":["0%","0%","0%","0%","0%","0%","0%","0%","0%","25%","0%","0%","0%","0%","0%","0%","0%","0%","0%","0%","0%","0%","0%","0%","0%","0%","0%","0%","0%","0%","0%","0%","0%","0%","0%","0%","0%","0%","0%","0%","0%","0%","0%","0%","0%","0%","0%","0%"],"values_N":[0,0,0,0,0,0,0,0,0,4,0,0,0,0,0,0,0,0,0,0,0,0,0,0,0,0,0,0,1,0,0,0,0,0,0,0,0,0,0,0,0,0,0,0,0,0,0,0],"buckets":[-1,-1,-1,-1,-1,-1,-1,-1,-1,6,-1,-1,-1,-1,-1,-1,-1,-1,-1,-1,-1,-1,-1,-1,-1,-1,-1,-1,0,-1,-1,-1,-1,-1,-1,-1,-1,-1,-1,-1,-1,-1,-1,-1,-1,-1,-1,-1],"speciesCode":"chibat1","name":"Chinspot Batis"},{"taxon":{"displayName":"African Paradise-Flycatcher","commonName":"African Paradise-Flycatcher","sciName":"Terpsiphone viridis","speciesCode":"afpfly1","category":"species","reportAsSpeciesCode":"afpfly1","reportAsCategory":"species","showSpeciesPageLink":true},"values":[0.0,0.0,0.0,0.0,0.0,0.0,0.0,0.0,0.0,0.25,0.0,0.0,0.0,0.0,0.0,0.0,0.0,0.0,0.0,0.0,0.0,0.0,0.0,0.0,0.0,0.0,0.0,0.0,0.0,0.0,0.0,0.0,0.0,0.0,0.0,0.0,0.0,0.0,0.0,0.0,0.0,0.0,0.0,0.0,0.0,0.0,0.0,0.0],"prettyValues":["0%","0%","0%","0%","0%","0%","0%","0%","0%","25%","0%","0%","0%","0%","0%","0%","0%","0%","0%","0%","0%","0%","0%","0%","0%","0%","0%","0%","0%","0%","0%","0%","0%","0%","0%","0%","0%","0%","0%","0%","0%","0%","0%","0%","0%","0%","0%","0%"],"values_N":[0,0,0,0,0,0,0,0,0,4,0,0,0,0,0,0,0,0,0,0,0,0,0,0,0,0,0,0,1,0,0,0,0,0,0,0,0,0,0,0,0,0,0,0,0,0,0,0],"buckets":[-1,-1,-1,-1,-1,-1,-1,-1,-1,6,-1,-1,-1,-1,-1,-1,-1,-1,-1,-1,-1,-1,-1,-1,-1,-1,-1,-1,0,-1,-1,-1,-1,-1,-1,-1,-1,-1,-1,-1,-1,-1,-1,-1,-1,-1,-1,-1],"speciesCode":"afpfly1","name":"African Paradise-Flycatcher"},{"taxon":{"displayName":"Northern Fiscal","commonName":"Northern Fiscal","sciName":"Lanius humeralis","speciesCode":"norfis1","category":"species","reportAsSpeciesCode":"norfis1","reportAsCategory":"species","showSpeciesPageLink":true},"values":[0.0,0.0,0.0,0.0,0.0,0.0,0.0,0.0,0.0,1.0,0.0,0.0,0.0,0.0,0.0,0.0,0.0,0.0,0.0,0.0,0.0,0.0,0.0,0.0,0.0,0.0,0.0,0.0,1.0,0.0,0.0,0.0,0.0,0.0,0.0,0.0,0.0,0.0,0.0,0.0,0.0,0.0,0.0,0.0,0.0,0.0,0.0,0.0],"prettyValues":["0%","0%","0%","0%","0%","0%","0%","0%","0%","100%","0%","0%","0%","0%","0%","0%","0%","0%","0%","0%","0%","0%","0%","0%","0%","0%","0%","0%","100%","0%","0%","0%","0%","0%","0%","0%","0%","0%","0%","0%","0%","0%","0%","0%","0%","0%","0%","0%"],"values_N":[0,0,0,0,0,0,0,0,0,4,0,0,0,0,0,0,0,0,0,0,0,0,0,0,0,0,0,0,1,0,0,0,0,0,0,0,0,0,0,0,0,0,0,0,0,0,0,0],"buckets":[-1,-1,-1,-1,-1,-1,-1,-1,-1,9,-1,-1,-1,-1,-1,-1,-1,-1,-1,-1,-1,-1,-1,-1,-1,-1,-1,-1,9,-1,-1,-1,-1,-1,-1,-1,-1,-1,-1,-1,-1,-1,-1,-1,-1,-1,-1,-1],"speciesCode":"norfis1","name":"Northern Fiscal"},{"taxon":{"displayName":"Pied Crow","commonName":"Pied Crow","sciName":"Corvus albus","speciesCode":"piecro1","category":"species","reportAsSpeciesCode":"piecro1","reportAsCategory":"species","showSpeciesPageLink":true},"values":[0.0,0.0,0.0,0.0,0.0,0.0,0.0,0.0,0.0,1.0,0.0,0.0,0.0,0.0,0.0,0.0,0.0,0.0,0.0,0.0,0.0,0.0,0.0,0.0,0.0,0.0,0.0,0.0,1.0,0.0,0.0,0.0,0.0,0.0,0.0,0.0,0.0,0.0,0.0,0.0,0.0,0.0,0.0,0.0,0.0,0.0,0.0,0.0],"prettyValues":["0%","0%","0%","0%","0%","0%","0%","0%","0%","100%","0%","0%","0%","0%","0%","0%","0%","0%","0%","0%","0%","0%","0%","0%","0%","0%","0%","0%","100%","0%","0%","0%","0%","0%","0%","0%","0%","0%","0%","0%","0%","0%","0%","0%","0%","0%","0%","0%"],"values_N":[0,0,0,0,0,0,0,0,0,4,0,0,0,0,0,0,0,0,0,0,0,0,0,0,0,0,0,0,1,0,0,0,0,0,0,0,0,0,0,0,0,0,0,0,0,0,0,0],"buckets":[-1,-1,-1,-1,-1,-1,-1,-1,-1,9,-1,-1,-1,-1,-1,-1,-1,-1,-1,-1,-1,-1,-1,-1,-1,-1,-1,-1,9,-1,-1,-1,-1,-1,-1,-1,-1,-1,-1,-1,-1,-1,-1,-1,-1,-1,-1,-1],"speciesCode":"piecro1","name":"Pied Crow"},{"taxon":{"displayName":"Red-faced Crombec","commonName":"Red-faced Crombec","sciName":"Sylvietta whytii","speciesCode":"refcro1","category":"species","reportAsSpeciesCode":"refcro1","reportAsCategory":"species","showSpeciesPageLink":true},"values":[0.0,0.0,0.0,0.0,0.0,0.0,0.0,0.0,0.0,0.0,0.0,0.0,0.0,0.0,0.0,0.0,0.0,0.0,0.0,0.0,0.0,0.0,0.0,0.0,0.0,0.0,0.0,0.0,1.0,0.0,0.0,0.0,0.0,0.0,0.0,0.0,0.0,0.0,0.0,0.0,0.0,0.0,0.0,0.0,0.0,0.0,0.0,0.0],"prettyValues":["0%","0%","0%","0%","0%","0%","0%","0%","0%","0%","0%","0%","0%","0%","0%","0%","0%","0%","0%","0%","0%","0%","0%","0%","0%","0%","0%","0%","100%","0%","0%","0%","0%","0%","0%","0%","0%","0%","0%","0%","0%","0%","0%","0%","0%","0%","0%","0%"],"values_N":[0,0,0,0,0,0,0,0,0,4,0,0,0,0,0,0,0,0,0,0,0,0,0,0,0,0,0,0,1,0,0,0,0,0,0,0,0,0,0,0,0,0,0,0,0,0,0,0],"buckets":[-1,-1,-1,-1,-1,-1,-1,-1,-1,0,-1,-1,-1,-1,-1,-1,-1,-1,-1,-1,-1,-1,-1,-1,-1,-1,-1,-1,9,-1,-1,-1,-1,-1,-1,-1,-1,-1,-1,-1,-1,-1,-1,-1,-1,-1,-1,-1],"speciesCode":"refcro1","name":"Red-faced Crombec"},{"taxon":{"displayName":"Green-backed Camaroptera","commonName":"Green-backed Camaroptera","sciName":"Camaroptera brachyura","speciesCode":"grbcam1","category":"species","reportAsSpeciesCode":"grbcam1","reportAsCategory":"species","showSpeciesPageLink":true},"values":[0.0,0.0,0.0,0.0,0.0,0.0,0.0,0.0,0.0,0.0,0.0,0.0,0.0,0.0,0.0,0.0,0.0,0.0,0.0,0.0,0.0,0.0,0.0,0.0,0.0,0.0,0.0,0.0,1.0,0.0,0.0,0.0,0.0,0.0,0.0,0.0,0.0,0.0,0.0,0.0,0.0,0.0,0.0,0.0,0.0,0.0,0.0,0.0],"prettyValues":["0%","0%","0%","0%","0%","0%","0%","0%","0%","0%","0%","0%","0%","0%","0%","0%","0%","0%","0%","0%","0%","0%","0%","0%","0%","0%","0%","0%","100%","0%","0%","0%","0%","0%","0%","0%","0%","0%","0%","0%","0%","0%","0%","0%","0%","0%","0%","0%"],"values_N":[0,0,0,0,0,0,0,0,0,4,0,0,0,0,0,0,0,0,0,0,0,0,0,0,0,0,0,0,1,0,0,0,0,0,0,0,0,0,0,0,0,0,0,0,0,0,0,0],"buckets":[-1,-1,-1,-1,-1,-1,-1,-1,-1,0,-1,-1,-1,-1,-1,-1,-1,-1,-1,-1,-1,-1,-1,-1,-1,-1,-1,-1,9,-1,-1,-1,-1,-1,-1,-1,-1,-1,-1,-1,-1,-1,-1,-1,-1,-1,-1,-1],"speciesCode":"grbcam1","name":"Green-backed Camaroptera"},{"taxon":{"displayName":"Yellow-breasted Apalis","commonName":"Yellow-breasted Apalis","sciName":"Apalis flavida","speciesCode":"yebapa1","category":"species","reportAsSpeciesCode":"yebapa1","reportAsCategory":"species","showSpeciesPageLink":true},"values":[0.0,0.0,0.0,0.0,0.0,0.0,0.0,0.0,0.0,0.5,0.0,0.0,0.0,0.0,0.0,0.0,0.0,0.0,0.0,0.0,0.0,0.0,0.0,0.0,0.0,0.0,0.0,0.0,0.0,0.0,0.0,0.0,0.0,0.0,0.0,0.0,0.0,0.0,0.0,0.0,0.0,0.0,0.0,0.0,0.0,0.0,0.0,0.0],"prettyValues":["0%","0%","0%","0%","0%","0%","0%","0%","0%","50%","0%","0%","0%","0%","0%","0%","0%","0%","0%","0%","0%","0%","0%","0%","0%","0%","0%","0%","0%","0%","0%","0%","0%","0%","0%","0%","0%","0%","0%","0%","0%","0%","0%","0%","0%","0%","0%","0%"],"values_N":[0,0,0,0,0,0,0,0,0,4,0,0,0,0,0,0,0,0,0,0,0,0,0,0,0,0,0,0,1,0,0,0,0,0,0,0,0,0,0,0,0,0,0,0,0,0,0,0],"buckets":[-1,-1,-1,-1,-1,-1,-1,-1,-1,8,-1,-1,-1,-1,-1,-1,-1,-1,-1,-1,-1,-1,-1,-1,-1,-1,-1,-1,0,-1,-1,-1,-1,-1,-1,-1,-1,-1,-1,-1,-1,-1,-1,-1,-1,-1,-1,-1],"speciesCode":"yebapa1","name":"Yellow-breasted Apalis"},{"taxon":{"displayName":"Tawny-flanked Prinia","commonName":"Tawny-flanked Prinia","sciName":"Prinia subflava","speciesCode":"tafpri1","category":"species","reportAsSpeciesCode":"tafpri1","reportAsCategory":"species","showSpeciesPageLink":true},"values":[0.0,0.0,0.0,0.0,0.0,0.0,0.0,0.0,0.0,0.25,0.0,0.0,0.0,0.0,0.0,0.0,0.0,0.0,0.0,0.0,0.0,0.0,0.0,0.0,0.0,0.0,0.0,0.0,0.0,0.0,0.0,0.0,0.0,0.0,0.0,0.0,0.0,0.0,0.0,0.0,0.0,0.0,0.0,0.0,0.0,0.0,0.0,0.0],"prettyValues":["0%","0%","0%","0%","0%","0%","0%","0%","0%","25%","0%","0%","0%","0%","0%","0%","0%","0%","0%","0%","0%","0%","0%","0%","0%","0%","0%","0%","0%","0%","0%","0%","0%","0%","0%","0%","0%","0%","0%","0%","0%","0%","0%","0%","0%","0%","0%","0%"],"values_N":[0,0,0,0,0,0,0,0,0,4,0,0,0,0,0,0,0,0,0,0,0,0,0,0,0,0,0,0,1,0,0,0,0,0,0,0,0,0,0,0,0,0,0,0,0,0,0,0],"buckets":[-1,-1,-1,-1,-1,-1,-1,-1,-1,6,-1,-1,-1,-1,-1,-1,-1,-1,-1,-1,-1,-1,-1,-1,-1,-1,-1,-1,0,-1,-1,-1,-1,-1,-1,-1,-1,-1,-1,-1,-1,-1,-1,-1,-1,-1,-1,-1],"speciesCode":"tafpri1","name":"Tawny-flanked Prinia"},{"taxon":{"displayName":"Plain Martin","commonName":"Plain Martin","sciName":"Riparia paludicola","speciesCode":"plamar1","category":"species","reportAsSpeciesCode":"plamar1","reportAsCategory":"species","showSpeciesPageLink":true},"values":[0.0,0.0,0.0,0.0,0.0,0.0,0.0,0.0,0.0,0.25,0.0,0.0,0.0,0.0,0.0,0.0,0.0,0.0,0.0,0.0,0.0,0.0,0.0,0.0,0.0,0.0,0.0,0.0,0.0,0.0,0.0,0.0,0.0,0.0,0.0,0.0,0.0,0.0,0.0,0.0,0.0,0.0,0.0,0.0,0.0,0.0,0.0,0.0],"prettyValues":["0%","0%","0%","0%","0%","0%","0%","0%","0%","25%","0%","0%","0%","0%","0%","0%","0%","0%","0%","0%","0%","0%","0%","0%","0%","0%","0%","0%","0%","0%","0%","0%","0%","0%","0%","0%","0%","0%","0%","0%","0%","0%","0%","0%","0%","0%","0%","0%"],"values_N":[0,0,0,0,0,0,0,0,0,4,0,0,0,0,0,0,0,0,0,0,0,0,0,0,0,0,0,0,1,0,0,0,0,0,0,0,0,0,0,0,0,0,0,0,0,0,0,0],"buckets":[-1,-1,-1,-1,-1,-1,-1,-1,-1,6,-1,-1,-1,-1,-1,-1,-1,-1,-1,-1,-1,-1,-1,-1,-1,-1,-1,-1,0,-1,-1,-1,-1,-1,-1,-1,-1,-1,-1,-1,-1,-1,-1,-1,-1,-1,-1,-1],"speciesCode":"plamar1","name":"Plain Martin"},{"taxon":{"displayName":"Rock Martin","commonName":"Rock Martin","sciName":"Ptyonoprogne fuligula","speciesCode":"rocmar2","category":"species","reportAsSpeciesCode":"rocmar2","reportAsCategory":"species","showSpeciesPageLink":true},"values":[0.0,0.0,0.0,0.0,0.0,0.0,0.0,0.0,0.0,0.5,0.0,0.0,0.0,0.0,0.0,0.0,0.0,0.0,0.0,0.0,0.0,0.0,0.0,0.0,0.0,0.0,0.0,0.0,1.0,0.0,0.0,0.0,0.0,0.0,0.0,0.0,0.0,0.0,0.0,0.0,0.0,0.0,0.0,0.0,0.0,0.0,0.0,0.0],"prettyValues":["0%","0%","0%","0%","0%","0%","0%","0%","0%","50%","0%","0%","0%","0%","0%","0%","0%","0%","0%","0%","0%","0%","0%","0%","0%","0%","0%","0%","100%","0%","0%","0%","0%","0%","0%","0%","0%","0%","0%","0%","0%","0%","0%","0%","0%","0%","0%","0%"],"values_N":[0,0,0,0,0,0,0,0,0,4,0,0,0,0,0,0,0,0,0,0,0,0,0,0,0,0,0,0,1,0,0,0,0,0,0,0,0,0,0,0,0,0,0,0,0,0,0,0],"buckets":[-1,-1,-1,-1,-1,-1,-1,-1,-1,8,-1,-1,-1,-1,-1,-1,-1,-1,-1,-1,-1,-1,-1,-1,-1,-1,-1,-1,9,-1,-1,-1,-1,-1,-1,-1,-1,-1,-1,-1,-1,-1,-1,-1,-1,-1,-1,-1],"speciesCode":"rocmar2","name":"Rock Martin"},{"taxon":{"displayName":"Barn Swallow","commonName":"Barn Swallow","sciName":"Hirundo rustica","speciesCode":"barswa","category":"species","reportAsSpeciesCode":"barswa","reportAsCategory":"species","showSpeciesPageLink":true},"values":[0.0,0.0,0.0,0.0,0.0,0.0,0.0,0.0,0.0,0.5,0.0,0.0,0.0,0.0,0.0,0.0,0.0,0.0,0.0,0.0,0.0,0.0,0.0,0.0,0.0,0.0,0.0,0.0,0.0,0.0,0.0,0.0,0.0,0.0,0.0,0.0,0.0,0.0,0.0,0.0,0.0,0.0,0.0,0.0,0.0,0.0,0.0,0.0],"prettyValues":["0%","0%","0%","0%","0%","0%","0%","0%","0%","50%","0%","0%","0%","0%","0%","0%","0%","0%","0%","0%","0%","0%","0%","0%","0%","0%","0%","0%","0%","0%","0%","0%","0%","0%","0%","0%","0%","0%","0%","0%","0%","0%","0%","0%","0%","0%","0%","0%"],"values_N":[0,0,0,0,0,0,0,0,0,4,0,0,0,0,0,0,0,0,0,0,0,0,0,0,0,0,0,0,1,0,0,0,0,0,0,0,0,0,0,0,0,0,0,0,0,0,0,0],"buckets":[-1,-1,-1,-1,-1,-1,-1,-1,-1,8,-1,-1,-1,-1,-1,-1,-1,-1,-1,-1,-1,-1,-1,-1,-1,-1,-1,-1,0,-1,-1,-1,-1,-1,-1,-1,-1,-1,-1,-1,-1,-1,-1,-1,-1,-1,-1,-1],"speciesCode":"barswa","name":"Barn Swallow"},{"taxon":{"displayName":"Common House-Martin","commonName":"Common House-Martin","sciName":"Delichon urbicum","speciesCode":"cohmar1","category":"species","reportAsSpeciesCode":"cohmar1","reportAsCategory":"species","showSpeciesPageLink":true},"values":[0.0,0.0,0.0,0.0,0.0,0.0,0.0,0.0,0.0,0.25,0.0,0.0,0.0,0.0,0.0,0.0,0.0,0.0,0.0,0.0,0.0,0.0,0.0,0.0,0.0,0.0,0.0,0.0,0.0,0.0,0.0,0.0,0.0,0.0,0.0,0.0,0.0,0.0,0.0,0.0,0.0,0.0,0.0,0.0,0.0,0.0,0.0,0.0],"prettyValues":["0%","0%","0%","0%","0%","0%","0%","0%","0%","25%","0%","0%","0%","0%","0%","0%","0%","0%","0%","0%","0%","0%","0%","0%","0%","0%","0%","0%","0%","0%","0%","0%","0%","0%","0%","0%","0%","0%","0%","0%","0%","0%","0%","0%","0%","0%","0%","0%"],"values_N":[0,0,0,0,0,0,0,0,0,4,0,0,0,0,0,0,0,0,0,0,0,0,0,0,0,0,0,0,1,0,0,0,0,0,0,0,0,0,0,0,0,0,0,0,0,0,0,0],"buckets":[-1,-1,-1,-1,-1,-1,-1,-1,-1,6,-1,-1,-1,-1,-1,-1,-1,-1,-1,-1,-1,-1,-1,-1,-1,-1,-1,-1,0,-1,-1,-1,-1,-1,-1,-1,-1,-1,-1,-1,-1,-1,-1,-1,-1,-1,-1,-1],"speciesCode":"cohmar1","name":"Common House-Martin"},{"taxon":{"displayName":"Black Sawwing","commonName":"Black Sawwing","sciName":"Psalidoprocne pristoptera","speciesCode":"blksaw1","category":"species","reportAsSpeciesCode":"blksaw1","reportAsCategory":"species","showSpeciesPageLink":true},"values":[0.0,0.0,0.0,0.0,0.0,0.0,0.0,0.0,0.0,0.5,0.0,0.0,0.0,0.0,0.0,0.0,0.0,0.0,0.0,0.0,0.0,0.0,0.0,0.0,0.0,0.0,0.0,0.0,0.0,0.0,0.0,0.0,0.0,0.0,0.0,0.0,0.0,0.0,0.0,0.0,0.0,0.0,0.0,0.0,0.0,0.0,0.0,0.0],"prettyValues":["0%","0%","0%","0%","0%","0%","0%","0%","0%","50%","0%","0%","0%","0%","0%","0%","0%","0%","0%","0%","0%","0%","0%","0%","0%","0%","0%","0%","0%","0%","0%","0%","0%","0%","0%","0%","0%","0%","0%","0%","0%","0%","0%","0%","0%","0%","0%","0%"],"values_N":[0,0,0,0,0,0,0,0,0,4,0,0,0,0,0,0,0,0,0,0,0,0,0,0,0,0,0,0,1,0,0,0,0,0,0,0,0,0,0,0,0,0,0,0,0,0,0,0],"buckets":[-1,-1,-1,-1,-1,-1,-1,-1,-1,8,-1,-1,-1,-1,-1,-1,-1,-1,-1,-1,-1,-1,-1,-1,-1,-1,-1,-1,0,-1,-1,-1,-1,-1,-1,-1,-1,-1,-1,-1,-1,-1,-1,-1,-1,-1,-1,-1],"speciesCode":"blksaw1","name":"Black Sawwing"},{"taxon":{"displayName":"Common Bulbul","commonName":"Common Bulbul","sciName":"Pycnonotus barbatus","speciesCode":"combul2","category":"species","reportAsSpeciesCode":"combul2","reportAsCategory":"species","showSpeciesPageLink":true},"values":[0.0,0.0,0.0,0.0,0.0,0.0,0.0,0.0,0.0,0.25,0.0,0.0,0.0,0.0,0.0,0.0,0.0,0.0,0.0,0.0,0.0,0.0,0.0,0.0,0.0,0.0,0.0,0.0,1.0,0.0,0.0,0.0,0.0,0.0,0.0,0.0,0.0,0.0,0.0,0.0,0.0,0.0,0.0,0.0,0.0,0.0,0.0,0.0],"prettyValues":["0%","0%","0%","0%","0%","0%","0%","0%","0%","25%","0%","0%","0%","0%","0%","0%","0%","0%","0%","0%","0%","0%","0%","0%","0%","0%","0%","0%","100%","0%","0%","0%","0%","0%","0%","0%","0%","0%","0%","0%","0%","0%","0%","0%","0%","0%","0%","0%"],"values_N":[0,0,0,0,0,0,0,0,0,4,0,0,0,0,0,0,0,0,0,0,0,0,0,0,0,0,0,0,1,0,0,0,0,0,0,0,0,0,0,0,0,0,0,0,0,0,0,0],"buckets":[-1,-1,-1,-1,-1,-1,-1,-1,-1,6,-1,-1,-1,-1,-1,-1,-1,-1,-1,-1,-1,-1,-1,-1,-1,-1,-1,-1,9,-1,-1,-1,-1,-1,-1,-1,-1,-1,-1,-1,-1,-1,-1,-1,-1,-1,-1,-1],"speciesCode":"combul2","name":"Common Bulbul"},{"taxon":{"displayName":"Willow Warbler","commonName":"Willow Warbler","sciName":"Phylloscopus trochilus","speciesCode":"wlwwar","category":"species","reportAsSpeciesCode":"wlwwar","reportAsCategory":"species","showSpeciesPageLink":true},"values":[0.0,0.0,0.0,0.0,0.0,0.0,0.0,0.0,0.0,0.25,0.0,0.0,0.0,0.0,0.0,0.0,0.0,0.0,0.0,0.0,0.0,0.0,0.0,0.0,0.0,0.0,0.0,0.0,0.0,0.0,0.0,0.0,0.0,0.0,0.0,0.0,0.0,0.0,0.0,0.0,0.0,0.0,0.0,0.0,0.0,0.0,0.0,0.0],"prettyValues":["0%","0%","0%","0%","0%","0%","0%","0%","0%","25%","0%","0%","0%","0%","0%","0%","0%","0%","0%","0%","0%","0%","0%","0%","0%","0%","0%","0%","0%","0%","0%","0%","0%","0%","0%","0%","0%","0%","0%","0%","0%","0%","0%","0%","0%","0%","0%","0%"],"values_N":[0,0,0,0,0,0,0,0,0,4,0,0,0,0,0,0,0,0,0,0,0,0,0,0,0,0,0,0,1,0,0,0,0,0,0,0,0,0,0,0,0,0,0,0,0,0,0,0],"buckets":[-1,-1,-1,-1,-1,-1,-1,-1,-1,6,-1,-1,-1,-1,-1,-1,-1,-1,-1,-1,-1,-1,-1,-1,-1,-1,-1,-1,0,-1,-1,-1,-1,-1,-1,-1,-1,-1,-1,-1,-1,-1,-1,-1,-1,-1,-1,-1],"speciesCode":"wlwwar","name":"Willow Warbler"},{"taxon":{"displayName":"Brown Parisoma","commonName":"Brown Parisoma","sciName":"Sylvia lugens","speciesCode":"brnwar1","category":"species","reportAsSpeciesCode":"brnwar1","reportAsCategory":"species","showSpeciesPageLink":true},"values":[0.0,0.0,0.0,0.0,0.0,0.0,0.0,0.0,0.0,0.0,0.0,0.0,0.0,0.0,0.0,0.0,0.0,0.0,0.0,0.0,0.0,0.0,0.0,0.0,0.0,0.0,0.0,0.0,1.0,0.0,0.0,0.0,0.0,0.0,0.0,0.0,0.0,0.0,0.0,0.0,0.0,0.0,0.0,0.0,0.0,0.0,0.0,0.0],"prettyValues":["0%","0%","0%","0%","0%","0%","0%","0%","0%","0%","0%","0%","0%","0%","0%","0%","0%","0%","0%","0%","0%","0%","0%","0%","0%","0%","0%","0%","100%","0%","0%","0%","0%","0%","0%","0%","0%","0%","0%","0%","0%","0%","0%","0%","0%","0%","0%","0%"],"values_N":[0,0,0,0,0,0,0,0,0,4,0,0,0,0,0,0,0,0,0,0,0,0,0,0,0,0,0,0,1,0,0,0,0,0,0,0,0,0,0,0,0,0,0,0,0,0,0,0],"buckets":[-1,-1,-1,-1,-1,-1,-1,-1,-1,0,-1,-1,-1,-1,-1,-1,-1,-1,-1,-1,-1,-1,-1,-1,-1,-1,-1,-1,9,-1,-1,-1,-1,-1,-1,-1,-1,-1,-1,-1,-1,-1,-1,-1,-1,-1,-1,-1],"speciesCode":"brnwar1","name":"Brown Parisoma"},{"taxon":{"displayName":"Violet-backed Starling","commonName":"Violet-backed Starling","sciName":"Cinnyricinclus leucogaster","speciesCode":"vibsta2","category":"species","reportAsSpeciesCode":"vibsta2","reportAsCategory":"species","showSpeciesPageLink":true},"values":[0.0,0.0,0.0,0.0,0.0,0.0,0.0,0.0,0.0,0.25,0.0,0.0,0.0,0.0,0.0,0.0,0.0,0.0,0.0,0.0,0.0,0.0,0.0,0.0,0.0,0.0,0.0,0.0,0.0,0.0,0.0,0.0,0.0,0.0,0.0,0.0,0.0,0.0,0.0,0.0,0.0,0.0,0.0,0.0,0.0,0.0,0.0,0.0],"prettyValues":["0%","0%","0%","0%","0%","0%","0%","0%","0%","25%","0%","0%","0%","0%","0%","0%","0%","0%","0%","0%","0%","0%","0%","0%","0%","0%","0%","0%","0%","0%","0%","0%","0%","0%","0%","0%","0%","0%","0%","0%","0%","0%","0%","0%","0%","0%","0%","0%"],"values_N":[0,0,0,0,0,0,0,0,0,4,0,0,0,0,0,0,0,0,0,0,0,0,0,0,0,0,0,0,1,0,0,0,0,0,0,0,0,0,0,0,0,0,0,0,0,0,0,0],"buckets":[-1,-1,-1,-1,-1,-1,-1,-1,-1,6,-1,-1,-1,-1,-1,-1,-1,-1,-1,-1,-1,-1,-1,-1,-1,-1,-1,-1,0,-1,-1,-1,-1,-1,-1,-1,-1,-1,-1,-1,-1,-1,-1,-1,-1,-1,-1,-1],"speciesCode":"vibsta2","name":"Violet-backed Starling"},{"taxon":{"displayName":"Red-winged Starling","commonName":"Red-winged Starling","sciName":"Onychognathus morio","speciesCode":"rewsta1","category":"species","reportAsSpeciesCode":"rewsta1","reportAsCategory":"species","showSpeciesPageLink":true},"values":[0.0,0.0,0.0,0.0,0.0,0.0,0.0,0.0,0.0,0.5,0.0,0.0,0.0,0.0,0.0,0.0,0.0,0.0,0.0,0.0,0.0,0.0,0.0,0.0,0.0,0.0,0.0,0.0,0.0,0.0,0.0,0.0,0.0,0.0,0.0,0.0,0.0,0.0,0.0,0.0,0.0,0.0,0.0,0.0,0.0,0.0,0.0,0.0],"prettyValues":["0%","0%","0%","0%","0%","0%","0%","0%","0%","50%","0%","0%","0%","0%","0%","0%","0%","0%","0%","0%","0%","0%","0%","0%","0%","0%","0%","0%","0%","0%","0%","0%","0%","0%","0%","0%","0%","0%","0%","0%","0%","0%","0%","0%","0%","0%","0%","0%"],"values_N":[0,0,0,0,0,0,0,0,0,4,0,0,0,0,0,0,0,0,0,0,0,0,0,0,0,0,0,0,1,0,0,0,0,0,0,0,0,0,0,0,0,0,0,0,0,0,0,0],"buckets":[-1,-1,-1,-1,-1,-1,-1,-1,-1,8,-1,-1,-1,-1,-1,-1,-1,-1,-1,-1,-1,-1,-1,-1,-1,-1,-1,-1,0,-1,-1,-1,-1,-1,-1,-1,-1,-1,-1,-1,-1,-1,-1,-1,-1,-1,-1,-1],"speciesCode":"rewsta1","name":"Red-winged Starling"},{"taxon":{"displayName":"Superb Starling","commonName":"Superb Starling","sciName":"Lamprotornis superbus","speciesCode":"supsta1","category":"species","reportAsSpeciesCode":"supsta1","reportAsCategory":"species","showSpeciesPageLink":true},"values":[0.0,0.0,0.0,0.0,0.0,0.0,0.0,0.0,0.0,1.0,0.0,0.0,0.0,0.0,0.0,0.0,0.0,0.0,0.0,0.0,0.0,0.0,0.0,0.0,0.0,0.0,0.0,0.0,1.0,0.0,0.0,0.0,0.0,0.0,0.0,0.0,0.0,0.0,0.0,0.0,0.0,0.0,0.0,0.0,0.0,0.0,0.0,0.0],"prettyValues":["0%","0%","0%","0%","0%","0%","0%","0%","0%","100%","0%","0%","0%","0%","0%","0%","0%","0%","0%","0%","0%","0%","0%","0%","0%","0%","0%","0%","100%","0%","0%","0%","0%","0%","0%","0%","0%","0%","0%","0%","0%","0%","0%","0%","0%","0%","0%","0%"],"values_N":[0,0,0,0,0,0,0,0,0,4,0,0,0,0,0,0,0,0,0,0,0,0,0,0,0,0,0,0,1,0,0,0,0,0,0,0,0,0,0,0,0,0,0,0,0,0,0,0],"buckets":[-1,-1,-1,-1,-1,-1,-1,-1,-1,9,-1,-1,-1,-1,-1,-1,-1,-1,-1,-1,-1,-1,-1,-1,-1,-1,-1,-1,9,-1,-1,-1,-1,-1,-1,-1,-1,-1,-1,-1,-1,-1,-1,-1,-1,-1,-1,-1],"speciesCode":"supsta1","name":"Superb Starling"},{"taxon":{"displayName":"Greater Blue-eared Starling","commonName":"Greater Blue-eared Starling","sciName":"Lamprotornis chalybaeus","speciesCode":"gbesta1","category":"species","reportAsSpeciesCode":"gbesta1","reportAsCategory":"species","showSpeciesPageLink":true},"values":[0.0,0.0,0.0,0.0,0.0,0.0,0.0,0.0,0.0,1.0,0.0,0.0,0.0,0.0,0.0,0.0,0.0,0.0,0.0,0.0,0.0,0.0,0.0,0.0,0.0,0.0,0.0,0.0,1.0,0.0,0.0,0.0,0.0,0.0,0.0,0.0,0.0,0.0,0.0,0.0,0.0,0.0,0.0,0.0,0.0,0.0,0.0,0.0],"prettyValues":["0%","0%","0%","0%","0%","0%","0%","0%","0%","100%","0%","0%","0%","0%","0%","0%","0%","0%","0%","0%","0%","0%","0%","0%","0%","0%","0%","0%","100%","0%","0%","0%","0%","0%","0%","0%","0%","0%","0%","0%","0%","0%","0%","0%","0%","0%","0%","0%"],"values_N":[0,0,0,0,0,0,0,0,0,4,0,0,0,0,0,0,0,0,0,0,0,0,0,0,0,0,0,0,1,0,0,0,0,0,0,0,0,0,0,0,0,0,0,0,0,0,0,0],"buckets":[-1,-1,-1,-1,-1,-1,-1,-1,-1,9,-1,-1,-1,-1,-1,-1,-1,-1,-1,-1,-1,-1,-1,-1,-1,-1,-1,-1,9,-1,-1,-1,-1,-1,-1,-1,-1,-1,-1,-1,-1,-1,-1,-1,-1,-1,-1,-1],"speciesCode":"gbesta1","name":"Greater Blue-eared Starling"},{"taxon":{"displayName":"Abyssinian Thrush","commonName":"Abyssinian Thrush","sciName":"Turdus abyssinicus","speciesCode":"abythr1","category":"species","reportAsSpeciesCode":"abythr1","reportAsCategory":"species","showSpeciesPageLink":true},"values":[0.0,0.0,0.0,0.0,0.0,0.0,0.0,0.0,0.0,0.75,0.0,0.0,0.0,0.0,0.0,0.0,0.0,0.0,0.0,0.0,0.0,0.0,0.0,0.0,0.0,0.0,0.0,0.0,0.0,0.0,0.0,0.0,0.0,0.0,0.0,0.0,0.0,0.0,0.0,0.0,0.0,0.0,0.0,0.0,0.0,0.0,0.0,0.0],"prettyValues":["0%","0%","0%","0%","0%","0%","0%","0%","0%","75%","0%","0%","0%","0%","0%","0%","0%","0%","0%","0%","0%","0%","0%","0%","0%","0%","0%","0%","0%","0%","0%","0%","0%","0%","0%","0%","0%","0%","0%","0%","0%","0%","0%","0%","0%","0%","0%","0%"],"values_N":[0,0,0,0,0,0,0,0,0,4,0,0,0,0,0,0,0,0,0,0,0,0,0,0,0,0,0,0,1,0,0,0,0,0,0,0,0,0,0,0,0,0,0,0,0,0,0,0],"buckets":[-1,-1,-1,-1,-1,-1,-1,-1,-1,9,-1,-1,-1,-1,-1,-1,-1,-1,-1,-1,-1,-1,-1,-1,-1,-1,-1,-1,0,-1,-1,-1,-1,-1,-1,-1,-1,-1,-1,-1,-1,-1,-1,-1,-1,-1,-1,-1],"speciesCode":"abythr1","name":"Abyssinian Thrush"},{"taxon":{"displayName":"White-eyed Slaty-Flycatcher","commonName":"White-eyed Slaty-Flycatcher","sciName":"Melaenornis fischeri","speciesCode":"wheslf1","category":"species","reportAsSpeciesCode":"wheslf1","reportAsCategory":"species","showSpeciesPageLink":true},"values":[0.0,0.0,0.0,0.0,0.0,0.0,0.0,0.0,0.0,0.75,0.0,0.0,0.0,0.0,0.0,0.0,0.0,0.0,0.0,0.0,0.0,0.0,0.0,0.0,0.0,0.0,0.0,0.0,1.0,0.0,0.0,0.0,0.0,0.0,0.0,0.0,0.0,0.0,0.0,0.0,0.0,0.0,0.0,0.0,0.0,0.0,0.0,0.0],"prettyValues":["0%","0%","0%","0%","0%","0%","0%","0%","0%","75%","0%","0%","0%","0%","0%","0%","0%","0%","0%","0%","0%","0%","0%","0%","0%","0%","0%","0%","100%","0%","0%","0%","0%","0%","0%","0%","0%","0%","0%","0%","0%","0%","0%","0%","0%","0%","0%","0%"],"values_N":[0,0,0,0,0,0,0,0,0,4,0,0,0,0,0,0,0,0,0,0,0,0,0,0,0,0,0,0,1,0,0,0,0,0,0,0,0,0,0,0,0,0,0,0,0,0,0,0],"buckets":[-1,-1,-1,-1,-1,-1,-1,-1,-1,9,-1,-1,-1,-1,-1,-1,-1,-1,-1,-1,-1,-1,-1,-1,-1,-1,-1,-1,9,-1,-1,-1,-1,-1,-1,-1,-1,-1,-1,-1,-1,-1,-1,-1,-1,-1,-1,-1],"speciesCode":"wheslf1","name":"White-eyed Slaty-Flycatcher"},{"taxon":{"displayName":"Cape Robin-Chat","commonName":"Cape Robin-Chat","sciName":"Cossypha caffra","speciesCode":"carcha1","category":"species","reportAsSpeciesCode":"carcha1","reportAsCategory":"species","showSpeciesPageLink":true},"values":[0.0,0.0,0.0,0.0,0.0,0.0,0.0,0.0,0.0,0.25,0.0,0.0,0.0,0.0,0.0,0.0,0.0,0.0,0.0,0.0,0.0,0.0,0.0,0.0,0.0,0.0,0.0,0.0,1.0,0.0,0.0,0.0,0.0,0.0,0.0,0.0,0.0,0.0,0.0,0.0,0.0,0.0,0.0,0.0,0.0,0.0,0.0,0.0],"prettyValues":["0%","0%","0%","0%","0%","0%","0%","0%","0%","25%","0%","0%","0%","0%","0%","0%","0%","0%","0%","0%","0%","0%","0%","0%","0%","0%","0%","0%","100%","0%","0%","0%","0%","0%","0%","0%","0%","0%","0%","0%","0%","0%","0%","0%","0%","0%","0%","0%"],"values_N":[0,0,0,0,0,0,0,0,0,4,0,0,0,0,0,0,0,0,0,0,0,0,0,0,0,0,0,0,1,0,0,0,0,0,0,0,0,0,0,0,0,0,0,0,0,0,0,0],"buckets":[-1,-1,-1,-1,-1,-1,-1,-1,-1,6,-1,-1,-1,-1,-1,-1,-1,-1,-1,-1,-1,-1,-1,-1,-1,-1,-1,-1,9,-1,-1,-1,-1,-1,-1,-1,-1,-1,-1,-1,-1,-1,-1,-1,-1,-1,-1,-1],"speciesCode":"carcha1","name":"Cape Robin-Chat"},{"taxon":{"displayName":"White-browed Robin-Chat","commonName":"White-browed Robin-Chat","sciName":"Cossypha heuglini","speciesCode":"wbrcha2","category":"species","reportAsSpeciesCode":"wbrcha2","reportAsCategory":"species","showSpeciesPageLink":true},"values":[0.0,0.0,0.0,0.0,0.0,0.0,0.0,0.0,0.0,0.0,0.0,0.0,0.0,0.0,0.0,0.0,0.0,0.0,0.0,0.0,0.0,0.0,0.0,0.0,0.0,0.0,0.0,0.0,1.0,0.0,0.0,0.0,0.0,0.0,0.0,0.0,0.0,0.0,0.0,0.0,0.0,0.0,0.0,0.0,0.0,0.0,0.0,0.0],"prettyValues":["0%","0%","0%","0%","0%","0%","0%","0%","0%","0%","0%","0%","0%","0%","0%","0%","0%","0%","0%","0%","0%","0%","0%","0%","0%","0%","0%","0%","100%","0%","0%","0%","0%","0%","0%","0%","0%","0%","0%","0%","0%","0%","0%","0%","0%","0%","0%","0%"],"values_N":[0,0,0,0,0,0,0,0,0,4,0,0,0,0,0,0,0,0,0,0,0,0,0,0,0,0,0,0,1,0,0,0,0,0,0,0,0,0,0,0,0,0,0,0,0,0,0,0],"buckets":[-1,-1,-1,-1,-1,-1,-1,-1,-1,0,-1,-1,-1,-1,-1,-1,-1,-1,-1,-1,-1,-1,-1,-1,-1,-1,-1,-1,9,-1,-1,-1,-1,-1,-1,-1,-1,-1,-1,-1,-1,-1,-1,-1,-1,-1,-1,-1],"speciesCode":"wbrcha2","name":"White-browed Robin-Chat"},{"taxon":{"displayName":"Amethyst Sunbird","commonName":"Amethyst Sunbird","sciName":"Chalcomitra amethystina","speciesCode":"amesun2","category":"species","reportAsSpeciesCode":"amesun2","reportAsCategory":"species","showSpeciesPageLink":true},"values":[0.0,0.0,0.0,0.0,0.0,0.0,0.0,0.0,0.0,0.0,0.0,0.0,0.0,0.0,0.0,0.0,0.0,0.0,0.0,0.0,0.0,0.0,0.0,0.0,0.0,0.0,0.0,0.0,1.0,0.0,0.0,0.0,0.0,0.0,0.0,0.0,0.0,0.0,0.0,0.0,0.0,0.0,0.0,0.0,0.0,0.0,0.0,0.0],"prettyValues":["0%","0%","0%","0%","0%","0%","0%","0%","0%","0%","0%","0%","0%","0%","0%","0%","0%","0%","0%","0%","0%","0%","0%","0%","0%","0%","0%","0%","100%","0%","0%","0%","0%","0%","0%","0%","0%","0%","0%","0%","0%","0%","0%","0%","0%","0%","0%","0%"],"values_N":[0,0,0,0,0,0,0,0,0,4,0,0,0,0,0,0,0,0,0,0,0,0,0,0,0,0,0,0,1,0,0,0,0,0,0,0,0,0,0,0,0,0,0,0,0,0,0,0],"buckets":[-1,-1,-1,-1,-1,-1,-1,-1,-1,0,-1,-1,-1,-1,-1,-1,-1,-1,-1,-1,-1,-1,-1,-1,-1,-1,-1,-1,9,-1,-1,-1,-1,-1,-1,-1,-1,-1,-1,-1,-1,-1,-1,-1,-1,-1,-1,-1],"speciesCode":"amesun2","name":"Amethyst Sunbird"},{"taxon":{"displayName":"Bronze Sunbird","commonName":"Bronze Sunbird","sciName":"Nectarinia kilimensis","speciesCode":"brosun1","category":"species","reportAsSpeciesCode":"brosun1","reportAsCategory":"species","showSpeciesPageLink":true},"values":[0.0,0.0,0.0,0.0,0.0,0.0,0.0,0.0,0.0,0.0,0.0,0.0,0.0,0.0,0.0,0.0,0.0,0.0,0.0,0.0,0.0,0.0,0.0,0.0,0.0,0.0,0.0,0.0,1.0,0.0,0.0,0.0,0.0,0.0,0.0,0.0,0.0,0.0,0.0,0.0,0.0,0.0,0.0,0.0,0.0,0.0,0.0,0.0],"prettyValues":["0%","0%","0%","0%","0%","0%","0%","0%","0%","0%","0%","0%","0%","0%","0%","0%","0%","0%","0%","0%","0%","0%","0%","0%","0%","0%","0%","0%","100%","0%","0%","0%","0%","0%","0%","0%","0%","0%","0%","0%","0%","0%","0%","0%","0%","0%","0%","0%"],"values_N":[0,0,0,0,0,0,0,0,0,4,0,0,0,0,0,0,0,0,0,0,0,0,0,0,0,0,0,0,1,0,0,0,0,0,0,0,0,0,0,0,0,0,0,0,0,0,0,0],"buckets":[-1,-1,-1,-1,-1,-1,-1,-1,-1,0,-1,-1,-1,-1,-1,-1,-1,-1,-1,-1,-1,-1,-1,-1,-1,-1,-1,-1,9,-1,-1,-1,-1,-1,-1,-1,-1,-1,-1,-1,-1,-1,-1,-1,-1,-1,-1,-1],"speciesCode":"brosun1","name":"Bronze Sunbird"},{"taxon":{"displayName":"Variable Sunbird","commonName":"Variable Sunbird","sciName":"Cinnyris venustus","speciesCode":"varsun2","category":"species","reportAsSpeciesCode":"varsun2","reportAsCategory":"species","showSpeciesPageLink":true},"values":[0.0,0.0,0.0,0.0,0.0,0.0,0.0,0.0,0.0,0.5,0.0,0.0,0.0,0.0,0.0,0.0,0.0,0.0,0.0,0.0,0.0,0.0,0.0,0.0,0.0,0.0,0.0,0.0,0.0,0.0,0.0,0.0,0.0,0.0,0.0,0.0,0.0,0.0,0.0,0.0,0.0,0.0,0.0,0.0,0.0,0.0,0.0,0.0],"prettyValues":["0%","0%","0%","0%","0%","0%","0%","0%","0%","50%","0%","0%","0%","0%","0%","0%","0%","0%","0%","0%","0%","0%","0%","0%","0%","0%","0%","0%","0%","0%","0%","0%","0%","0%","0%","0%","0%","0%","0%","0%","0%","0%","0%","0%","0%","0%","0%","0%"],"values_N":[0,0,0,0,0,0,0,0,0,4,0,0,0,0,0,0,0,0,0,0,0,0,0,0,0,0,0,0,1,0,0,0,0,0,0,0,0,0,0,0,0,0,0,0,0,0,0,0],"buckets":[-1,-1,-1,-1,-1,-1,-1,-1,-1,8,-1,-1,-1,-1,-1,-1,-1,-1,-1,-1,-1,-1,-1,-1,-1,-1,-1,-1,0,-1,-1,-1,-1,-1,-1,-1,-1,-1,-1,-1,-1,-1,-1,-1,-1,-1,-1,-1],"speciesCode":"varsun2","name":"Variable Sunbird"},{"taxon":{"displayName":"Red-headed Weaver","commonName":"Red-headed Weaver","sciName":"Anaplectes rubriceps","speciesCode":"rehwea1","category":"species","reportAsSpeciesCode":"rehwea1","reportAsCategory":"species","showSpeciesPageLink":true},"values":[0.0,0.0,0.0,0.0,0.0,0.0,0.0,0.0,0.0,0.25,0.0,0.0,0.0,0.0,0.0,0.0,0.0,0.0,0.0,0.0,0.0,0.0,0.0,0.0,0.0,0.0,0.0,0.0,0.0,0.0,0.0,0.0,0.0,0.0,0.0,0.0,0.0,0.0,0.0,0.0,0.0,0.0,0.0,0.0,0.0,0.0,0.0,0.0],"prettyValues":["0%","0%","0%","0%","0%","0%","0%","0%","0%","25%","0%","0%","0%","0%","0%","0%","0%","0%","0%","0%","0%","0%","0%","0%","0%","0%","0%","0%","0%","0%","0%","0%","0%","0%","0%","0%","0%","0%","0%","0%","0%","0%","0%","0%","0%","0%","0%","0%"],"values_N":[0,0,0,0,0,0,0,0,0,4,0,0,0,0,0,0,0,0,0,0,0,0,0,0,0,0,0,0,1,0,0,0,0,0,0,0,0,0,0,0,0,0,0,0,0,0,0,0],"buckets":[-1,-1,-1,-1,-1,-1,-1,-1,-1,6,-1,-1,-1,-1,-1,-1,-1,-1,-1,-1,-1,-1,-1,-1,-1,-1,-1,-1,0,-1,-1,-1,-1,-1,-1,-1,-1,-1,-1,-1,-1,-1,-1,-1,-1,-1,-1,-1],"speciesCode":"rehwea1","name":"Red-headed Weaver"},{"taxon":{"displayName":"Baglafecht Weaver","commonName":"Baglafecht Weaver","sciName":"Ploceus baglafecht","speciesCode":"bagwea1","category":"species","reportAsSpeciesCode":"bagwea1","reportAsCategory":"species","showSpeciesPageLink":true},"values":[0.0,0.0,0.0,0.0,0.0,0.0,0.0,0.0,0.0,1.0,0.0,0.0,0.0,0.0,0.0,0.0,0.0,0.0,0.0,0.0,0.0,0.0,0.0,0.0,0.0,0.0,0.0,0.0,1.0,0.0,0.0,0.0,0.0,0.0,0.0,0.0,0.0,0.0,0.0,0.0,0.0,0.0,0.0,0.0,0.0,0.0,0.0,0.0],"prettyValues":["0%","0%","0%","0%","0%","0%","0%","0%","0%","100%","0%","0%","0%","0%","0%","0%","0%","0%","0%","0%","0%","0%","0%","0%","0%","0%","0%","0%","100%","0%","0%","0%","0%","0%","0%","0%","0%","0%","0%","0%","0%","0%","0%","0%","0%","0%","0%","0%"],"values_N":[0,0,0,0,0,0,0,0,0,4,0,0,0,0,0,0,0,0,0,0,0,0,0,0,0,0,0,0,1,0,0,0,0,0,0,0,0,0,0,0,0,0,0,0,0,0,0,0],"buckets":[-1,-1,-1,-1,-1,-1,-1,-1,-1,9,-1,-1,-1,-1,-1,-1,-1,-1,-1,-1,-1,-1,-1,-1,-1,-1,-1,-1,9,-1,-1,-1,-1,-1,-1,-1,-1,-1,-1,-1,-1,-1,-1,-1,-1,-1,-1,-1],"speciesCode":"bagwea1","name":"Baglafecht Weaver"},{"taxon":{"displayName":"Speke's Weaver","commonName":"Speke's Weaver","sciName":"Ploceus spekei","speciesCode":"spewea2","category":"species","reportAsSpeciesCode":"spewea2","reportAsCategory":"species","showSpeciesPageLink":true},"values":[0.0,0.0,0.0,0.0,0.0,0.0,0.0,0.0,0.0,0.5,0.0,0.0,0.0,0.0,0.0,0.0,0.0,0.0,0.0,0.0,0.0,0.0,0.0,0.0,0.0,0.0,0.0,0.0,0.0,0.0,0.0,0.0,0.0,0.0,0.0,0.0,0.0,0.0,0.0,0.0,0.0,0.0,0.0,0.0,0.0,0.0,0.0,0.0],"prettyValues":["0%","0%","0%","0%","0%","0%","0%","0%","0%","50%","0%","0%","0%","0%","0%","0%","0%","0%","0%","0%","0%","0%","0%","0%","0%","0%","0%","0%","0%","0%","0%","0%","0%","0%","0%","0%","0%","0%","0%","0%","0%","0%","0%","0%","0%","0%","0%","0%"],"values_N":[0,0,0,0,0,0,0,0,0,4,0,0,0,0,0,0,0,0,0,0,0,0,0,0,0,0,0,0,1,0,0,0,0,0,0,0,0,0,0,0,0,0,0,0,0,0,0,0],"buckets":[-1,-1,-1,-1,-1,-1,-1,-1,-1,8,-1,-1,-1,-1,-1,-1,-1,-1,-1,-1,-1,-1,-1,-1,-1,-1,-1,-1,0,-1,-1,-1,-1,-1,-1,-1,-1,-1,-1,-1,-1,-1,-1,-1,-1,-1,-1,-1],"speciesCode":"spewea2","name":"Speke's Weaver"},{"taxon":{"displayName":"Common Waxbill","commonName":"Common Waxbill","sciName":"Estrilda astrild","speciesCode":"comwax","category":"species","reportAsSpeciesCode":"comwax","reportAsCategory":"species","showSpeciesPageLink":true},"values":[0.0,0.0,0.0,0.0,0.0,0.0,0.0,0.0,0.0,0.0,0.0,0.0,0.0,0.0,0.0,0.0,0.0,0.0,0.0,0.0,0.0,0.0,0.0,0.0,0.0,0.0,0.0,0.0,1.0,0.0,0.0,0.0,0.0,0.0,0.0,0.0,0.0,0.0,0.0,0.0,0.0,0.0,0.0,0.0,0.0,0.0,0.0,0.0],"prettyValues":["0%","0%","0%","0%","0%","0%","0%","0%","0%","0%","0%","0%","0%","0%","0%","0%","0%","0%","0%","0%","0%","0%","0%","0%","0%","0%","0%","0%","100%","0%","0%","0%","0%","0%","0%","0%","0%","0%","0%","0%","0%","0%","0%","0%","0%","0%","0%","0%"],"values_N":[0,0,0,0,0,0,0,0,0,4,0,0,0,0,0,0,0,0,0,0,0,0,0,0,0,0,0,0,1,0,0,0,0,0,0,0,0,0,0,0,0,0,0,0,0,0,0,0],"buckets":[-1,-1,-1,-1,-1,-1,-1,-1,-1,0,-1,-1,-1,-1,-1,-1,-1,-1,-1,-1,-1,-1,-1,-1,-1,-1,-1,-1,9,-1,-1,-1,-1,-1,-1,-1,-1,-1,-1,-1,-1,-1,-1,-1,-1,-1,-1,-1],"speciesCode":"comwax","name":"Common Waxbill"},{"taxon":{"displayName":"Red-cheeked Cordonbleu","commonName":"Red-cheeked Cordonbleu","sciName":"Uraeginthus bengalus","speciesCode":"reccor","category":"species","reportAsSpeciesCode":"reccor","reportAsCategory":"species","showSpeciesPageLink":true},"values":[0.0,0.0,0.0,0.0,0.0,0.0,0.0,0.0,0.0,0.25,0.0,0.0,0.0,0.0,0.0,0.0,0.0,0.0,0.0,0.0,0.0,0.0,0.0,0.0,0.0,0.0,0.0,0.0,0.0,0.0,0.0,0.0,0.0,0.0,0.0,0.0,0.0,0.0,0.0,0.0,0.0,0.0,0.0,0.0,0.0,0.0,0.0,0.0],"prettyValues":["0%","0%","0%","0%","0%","0%","0%","0%","0%","25%","0%","0%","0%","0%","0%","0%","0%","0%","0%","0%","0%","0%","0%","0%","0%","0%","0%","0%","0%","0%","0%","0%","0%","0%","0%","0%","0%","0%","0%","0%","0%","0%","0%","0%","0%","0%","0%","0%"],"values_N":[0,0,0,0,0,0,0,0,0,4,0,0,0,0,0,0,0,0,0,0,0,0,0,0,0,0,0,0,1,0,0,0,0,0,0,0,0,0,0,0,0,0,0,0,0,0,0,0],"buckets":[-1,-1,-1,-1,-1,-1,-1,-1,-1,6,-1,-1,-1,-1,-1,-1,-1,-1,-1,-1,-1,-1,-1,-1,-1,-1,-1,-1,0,-1,-1,-1,-1,-1,-1,-1,-1,-1,-1,-1,-1,-1,-1,-1,-1,-1,-1,-1],"speciesCode":"reccor","name":"Red-cheeked Cordonbleu"},{"taxon":{"displayName":"Red-billed Firefinch","commonName":"Red-billed Firefinch","sciName":"Lagonosticta senegala","speciesCode":"rebfir2","category":"species","reportAsSpeciesCode":"rebfir2","reportAsCategory":"species","showSpeciesPageLink":true},"values":[0.0,0.0,0.0,0.0,0.0,0.0,0.0,0.0,0.0,0.25,0.0,0.0,0.0,0.0,0.0,0.0,0.0,0.0,0.0,0.0,0.0,0.0,0.0,0.0,0.0,0.0,0.0,0.0,0.0,0.0,0.0,0.0,0.0,0.0,0.0,0.0,0.0,0.0,0.0,0.0,0.0,0.0,0.0,0.0,0.0,0.0,0.0,0.0],"prettyValues":["0%","0%","0%","0%","0%","0%","0%","0%","0%","25%","0%","0%","0%","0%","0%","0%","0%","0%","0%","0%","0%","0%","0%","0%","0%","0%","0%","0%","0%","0%","0%","0%","0%","0%","0%","0%","0%","0%","0%","0%","0%","0%","0%","0%","0%","0%","0%","0%"],"values_N":[0,0,0,0,0,0,0,0,0,4,0,0,0,0,0,0,0,0,0,0,0,0,0,0,0,0,0,0,1,0,0,0,0,0,0,0,0,0,0,0,0,0,0,0,0,0,0,0],"buckets":[-1,-1,-1,-1,-1,-1,-1,-1,-1,6,-1,-1,-1,-1,-1,-1,-1,-1,-1,-1,-1,-1,-1,-1,-1,-1,-1,-1,0,-1,-1,-1,-1,-1,-1,-1,-1,-1,-1,-1,-1,-1,-1,-1,-1,-1,-1,-1],"speciesCode":"rebfir2","name":"Red-billed Firefinch"},{"taxon":{"displayName":"Bronze Mannikin","commonName":"Bronze Mannikin","sciName":"Spermestes cucullata","speciesCode":"broman1","category":"species","reportAsSpeciesCode":"broman1","reportAsCategory":"species","showSpeciesPageLink":true},"values":[0.0,0.0,0.0,0.0,0.0,0.0,0.0,0.0,0.0,0.0,0.0,0.0,0.0,0.0,0.0,0.0,0.0,0.0,0.0,0.0,0.0,0.0,0.0,0.0,0.0,0.0,0.0,0.0,1.0,0.0,0.0,0.0,0.0,0.0,0.0,0.0,0.0,0.0,0.0,0.0,0.0,0.0,0.0,0.0,0.0,0.0,0.0,0.0],"prettyValues":["0%","0%","0%","0%","0%","0%","0%","0%","0%","0%","0%","0%","0%","0%","0%","0%","0%","0%","0%","0%","0%","0%","0%","0%","0%","0%","0%","0%","100%","0%","0%","0%","0%","0%","0%","0%","0%","0%","0%","0%","0%","0%","0%","0%","0%","0%","0%","0%"],"values_N":[0,0,0,0,0,0,0,0,0,4,0,0,0,0,0,0,0,0,0,0,0,0,0,0,0,0,0,0,1,0,0,0,0,0,0,0,0,0,0,0,0,0,0,0,0,0,0,0],"buckets":[-1,-1,-1,-1,-1,-1,-1,-1,-1,0,-1,-1,-1,-1,-1,-1,-1,-1,-1,-1,-1,-1,-1,-1,-1,-1,-1,-1,9,-1,-1,-1,-1,-1,-1,-1,-1,-1,-1,-1,-1,-1,-1,-1,-1,-1,-1,-1],"speciesCode":"broman1","name":"Bronze Mannikin"},{"taxon":{"displayName":"Kenya Rufous Sparrow","commonName":"Kenya Rufous Sparrow","sciName":"Passer rufocinctus","speciesCode":"kerspa2","category":"species","reportAsSpeciesCode":"kerspa2","reportAsCategory":"species","showSpeciesPageLink":true},"values":[0.0,0.0,0.0,0.0,0.0,0.0,0.0,0.0,0.0,0.5,0.0,0.0,0.0,0.0,0.0,0.0,0.0,0.0,0.0,0.0,0.0,0.0,0.0,0.0,0.0,0.0,0.0,0.0,0.0,0.0,0.0,0.0,0.0,0.0,0.0,0.0,0.0,0.0,0.0,0.0,0.0,0.0,0.0,0.0,0.0,0.0,0.0,0.0],"prettyValues":["0%","0%","0%","0%","0%","0%","0%","0%","0%","50%","0%","0%","0%","0%","0%","0%","0%","0%","0%","0%","0%","0%","0%","0%","0%","0%","0%","0%","0%","0%","0%","0%","0%","0%","0%","0%","0%","0%","0%","0%","0%","0%","0%","0%","0%","0%","0%","0%"],"values_N":[0,0,0,0,0,0,0,0,0,4,0,0,0,0,0,0,0,0,0,0,0,0,0,0,0,0,0,0,1,0,0,0,0,0,0,0,0,0,0,0,0,0,0,0,0,0,0,0],"buckets":[-1,-1,-1,-1,-1,-1,-1,-1,-1,8,-1,-1,-1,-1,-1,-1,-1,-1,-1,-1,-1,-1,-1,-1,-1,-1,-1,-1,0,-1,-1,-1,-1,-1,-1,-1,-1,-1,-1,-1,-1,-1,-1,-1,-1,-1,-1,-1],"speciesCode":"kerspa2","name":"Kenya Rufous Sparrow"},{"taxon":{"displayName":"African Pipit","commonName":"African Pipit","sciName":"Anthus cinnamomeus","speciesCode":"afrpip1","category":"species","reportAsSpeciesCode":"afrpip1","reportAsCategory":"species","showSpeciesPageLink":true},"values":[0.0,0.0,0.0,0.0,0.0,0.0,0.0,0.0,0.0,0.25,0.0,0.0,0.0,0.0,0.0,0.0,0.0,0.0,0.0,0.0,0.0,0.0,0.0,0.0,0.0,0.0,0.0,0.0,0.0,0.0,0.0,0.0,0.0,0.0,0.0,0.0,0.0,0.0,0.0,0.0,0.0,0.0,0.0,0.0,0.0,0.0,0.0,0.0],"prettyValues":["0%","0%","0%","0%","0%","0%","0%","0%","0%","25%","0%","0%","0%","0%","0%","0%","0%","0%","0%","0%","0%","0%","0%","0%","0%","0%","0%","0%","0%","0%","0%","0%","0%","0%","0%","0%","0%","0%","0%","0%","0%","0%","0%","0%","0%","0%","0%","0%"],"values_N":[0,0,0,0,0,0,0,0,0,4,0,0,0,0,0,0,0,0,0,0,0,0,0,0,0,0,0,0,1,0,0,0,0,0,0,0,0,0,0,0,0,0,0,0,0,0,0,0],"buckets":[-1,-1,-1,-1,-1,-1,-1,-1,-1,6,-1,-1,-1,-1,-1,-1,-1,-1,-1,-1,-1,-1,-1,-1,-1,-1,-1,-1,0,-1,-1,-1,-1,-1,-1,-1,-1,-1,-1,-1,-1,-1,-1,-1,-1,-1,-1,-1],"speciesCode":"afrpip1","name":"African Pipit"},{"taxon":{"displayName":"Streaky Seedeater","commonName":"Streaky Seedeater","sciName":"Crithagra striolata","speciesCode":"strsee1","category":"species","reportAsSpeciesCode":"strsee1","reportAsCategory":"species","showSpeciesPageLink":true},"values":[0.0,0.0,0.0,0.0,0.0,0.0,0.0,0.0,0.0,0.75,0.0,0.0,0.0,0.0,0.0,0.0,0.0,0.0,0.0,0.0,0.0,0.0,0.0,0.0,0.0,0.0,0.0,0.0,0.0,0.0,0.0,0.0,0.0,0.0,0.0,0.0,0.0,0.0,0.0,0.0,0.0,0.0,0.0,0.0,0.0,0.0,0.0,0.0],"prettyValues":["0%","0%","0%","0%","0%","0%","0%","0%","0%","75%","0%","0%","0%","0%","0%","0%","0%","0%","0%","0%","0%","0%","0%","0%","0%","0%","0%","0%","0%","0%","0%","0%","0%","0%","0%","0%","0%","0%","0%","0%","0%","0%","0%","0%","0%","0%","0%","0%"],"values_N":[0,0,0,0,0,0,0,0,0,4,0,0,0,0,0,0,0,0,0,0,0,0,0,0,0,0,0,0,1,0,0,0,0,0,0,0,0,0,0,0,0,0,0,0,0,0,0,0],"buckets":[-1,-1,-1,-1,-1,-1,-1,-1,-1,9,-1,-1,-1,-1,-1,-1,-1,-1,-1,-1,-1,-1,-1,-1,-1,-1,-1,-1,0,-1,-1,-1,-1,-1,-1,-1,-1,-1,-1,-1,-1,-1,-1,-1,-1,-1,-1,-1],"speciesCode":"strsee1","name":"Streaky Seedeater"}],"numSpecies":53,"numTaxa":53}