{"dataRows":[{"taxon":{"displayName":"Speckled Pigeon","commonName":"Speckled Pigeon","sciName":"Columba guinea","speciesCode":"spepig1","category":"species","reportAsSpeciesCode":"spepig1","reportAsCategory":"species","showSpeciesPageLink":true},"values":[0.0,0.0,0.0,0.0,0.0,0.0,0.0,0.0,0.0,0.0,0.0,0.0,0.0,0.0,0.0,0.0,0.0,0.0,0.0,0.0,0.0,0.0,0.0,0.0,0.0,0.0,0.0,0.0,0.0,0.0,0.0,0.0,0.0,0.0,0.0,0.0,1.0,0.0,0.0,0.0,0.0,0.0,0.0,0.0,0.0,0.0,0.0,0.0],"prettyValues":["0%","0%","0%","0%","0%","0%","0%","0%","0%","0%","0%","0%","0%","0%","0%","0%","0%","0%","0%","0%","0%","0%","0%","0%","0%","0%","0%","0%","0%","0%","0%","0%","0%","0%","0%","0%","100%","0%","0%","0%","0%","0%","0%","0%","0%","0%","0%","0%"],"values_N":[0,0,0,0,0,0,0,0,0,0,0,0,0,0,0,0,0,0,0,0,0,0,0,0,0,0,0,0,0,0,0,0,0,0,0,0,1,0,0,0,0,0,0,0,0,0,0,0],"buckets":[-1,-1,-1,-1,-1,-1,-1,-1,-1,-1,-1,-1,-1,-1,-1,-1,-1,-1,-1,-1,-1,-1,-1,-1,-1,-1,-1,-1,-1,-1,-1,-1,-1,-1,-1,-1,9,-1,-1,-1,-1,-1,-1,-1,-1,-1,-1,-1],"speciesCode":"spepig1","name":"Speckled Pigeon"},{"taxon":{"displayName":"Rameron Pigeon","commonName":"Rameron Pigeon","sciName":"Columba arquatrix","speciesCode":"rampig1","category":"species","reportAsSpeciesCode":"rampig1","reportAsCategory":"species","showSpeciesPageLink":true},"values":[0.0,0.0,0.0,0.0,0.0,0.0,0.0,0.0,0.0,0.0,0.0,0.0,0.0,0.0,0.0,0.0,0.0,0.0,0.0,0.0,0.0,0.0,0.0,0.0,0.0,0.0,0.0,0.0,0.0,0.0,0.0,0.0,0.0,0.0,0.0,0.0,1.0,0.0,0.0,0.0,0.0,0.0,0.0,0.0,0.0,0.0,0.0,0.0],"prettyValues":["0%","0%","0%","0%","0%","0%","0%","0%","0%","0%","0%","0%","0%","0%","0%","0%","0%","0%","0%","0%","0%","0%","0%","0%","0%","0%","0%","0%","0%","0%","0%","0%","0%","0%","0%","0%","100%","0%","0%","0%","0%","0%","0%","0%","0%","0%","0%","0%"],"values_N":[0,0,0,0,0,0,0,0,0,0,0,0,0,0,0,0,0,0,0,0,0,0,0,0,0,0,0,0,0,0,0,0,0,0,0,0,1,0,0,0,0,0,0,0,0,0,0,0],"buckets":[-1,-1,-1,-1,-1,-1,-1,-1,-1,-1,-1,-1,-1,-1,-1,-1,-1,-1,-1,-1,-1,-1,-1,-1,-1,-1,-1,-1,-1,-1,-1,-1,-1,-1,-1,-1,9,-1,-1,-1,-1,-1,-1,-1,-1,-1,-1,-1],"speciesCode":"rampig1","name":"Rameron Pigeon"},{"taxon":{"displayName":"Tambourine Dove","commonName":"Tambourine Dove","sciName":"Turtur tympanistria","speciesCode":"tamdov1","category":"species","reportAsSpeciesCode":"tamdov1","reportAsCategory":"species","showSpeciesPageLink":true},"values":[0.0,0.0,0.0,0.0,0.0,0.0,0.0,0.0,0.0,0.0,0.0,0.0,0.0,0.0,0.0,0.0,0.0,0.0,0.0,0.0,0.0,0.0,0.0,0.0,0.0,0.0,0.0,0.0,0.0,0.0,0.0,0.0,0.0,0.0,0.0,0.0,1.0,0.0,0.0,0.0,0.0,0.0,0.0,0.0,0.0,0.0,0.0,0.0],"prettyValues":["0%","0%","0%","0%","0%","0%","0%","0%","0%","0%","0%","0%","0%","0%","0%","0%","0%","0%","0%","0%","0%","0%","0%","0%","0%","0%","0%","0%","0%","0%","0%","0%","0%","0%","0%","0%","100%","0%","0%","0%","0%","0%","0%","0%","0%","0%","0%","0%"],"values_N":[0,0,0,0,0,0,0,0,0,0,0,0,0,0,0,0,0,0,0,0,0,0,0,0,0,0,0,0,0,0,0,0,0,0,0,0,1,0,0,0,0,0,0,0,0,0,0,0],"buckets":[-1,-1,-1,-1,-1,-1,-1,-1,-1,-1,-1,-1,-1,-1,-1,-1,-1,-1,-1,-1,-1,-1,-1,-1,-1,-1,-1,-1,-1,-1,-1,-1,-1,-1,-1,-1,9,-1,-1,-1,-1,-1,-1,-1,-1,-1,-1,-1],"speciesCode":"tamdov1","name":"Tambourine Dove"},{"taxon":{"displayName":"Hartlaub's Turaco","commonName":"Hartlaub's Turaco","sciName":"Tauraco hartlaubi","speciesCode":"hartur1","category":"species","reportAsSpeciesCode":"hartur1","reportAsCategory":"species","showSpeciesPageLink":true},"values":[0.0,0.0,0.0,0.0,0.0,0.0,0.0,0.0,0.0,0.0,0.0,0.0,0.0,0.0,0.0,0.0,0.0,0.0,0.0,0.0,0.0,0.0,0.0,0.0,0.0,0.0,0.0,0.0,0.0,0.0,0.0,0.0,0.0,0.0,0.0,0.0,1.0,0.0,0.0,0.0,0.0,0.0,0.0,0.0,0.0,0.0,0.0,0.0],"prettyValues":["0%","0%","0%","0%","0%","0%","0%","0%","0%","0%","0%","0%","0%","0%","0%","0%","0%","0%","0%","0%","0%","0%","0%","0%","0%","0%","0%","0%","0%","0%","0%","0%","0%","0%","0%","0%","100%","0%","0%","0%","0%","0%","0%","0%","0%","0%","0%","0%"],"values_N":[0,0,0,0,0,0,0,0,0,0,0,0,0,0,0,0,0,0,0,0,0,0,0,0,0,0,0,0,0,0,0,0,0,0,0,0,1,0,0,0,0,0,0,0,0,0,0,0],"buckets":[-1,-1,-1,-1,-1,-1,-1,-1,-1,-1,-1,-1,-1,-1,-1,-1,-1,-1,-1,-1,-1,-1,-1,-1,-1,-1,-1,-1,-1,-1,-1,-1,-1,-1,-1,-1,9,-1,-1,-1,-1,-1,-1,-1,-1,-1,-1,-1],"speciesCode":"hartur1","name":"Hartlaub's Turaco"},{"taxon":{"displayName":"Ross's Turaco","commonName":"Ross's Turaco","sciName":"Musophaga rossae","speciesCode":"rostur1","category":"species","reportAsSpeciesCode":"rostur1","reportAsCategory":"species","showSpeciesPageLink":true},"values":[0.0,0.0,0.0,0.0,0.0,0.0,0.0,0.0,0.0,0.0,0.0,0.0,0.0,0.0,0.0,0.0,0.0,0.0,0.0,0.0,0.0,0.0,0.0,0.0,0.0,0.0,0.0,0.0,0.0,0.0,0.0,0.0,0.0,0.0,0.0,0.0,1.0,0.0,0.0,0.0,0.0,0.0,0.0,0.0,0.0,0.0,0.0,0.0],"prettyValues":["0%","0%","0%","0%","0%","0%","0%","0%","0%","0%","0%","0%","0%","0%","0%","0%","0%","0%","0%","0%","0%","0%","0%","0%","0%","0%","0%","0%","0%","0%","0%","0%","0%","0%","0%","0%","100%","0%","0%","0%","0%","0%","0%","0%","0%","0%","0%","0%"],"values_N":[0,0,0,0,0,0,0,0,0,0,0,0,0,0,0,0,0,0,0,0,0,0,0,0,0,0,0,0,0,0,0,0,0,0,0,0,1,0,0,0,0,0,0,0,0,0,0,0],"buckets":[-1,-1,-1,-1,-1,-1,-1,-1,-1,-1,-1,-1,-1,-1,-1,-1,-1,-1,-1,-1,-1,-1,-1,-1,-1,-1,-1,-1,-1,-1,-1,-1,-1,-1,-1,-1,9,-1,-1,-1,-1,-1,-1,-1,-1,-1,-1,-1],"speciesCode":"rostur1","name":"Ross's Turaco"},{"taxon":{"displayName":"Scarce Swift","commonName":"Scarce Swift","sciName":"Schoutedenapus myoptilus","speciesCode":"scaswi1","category":"species","reportAsSpeciesCode":"scaswi1","reportAsCategory":"species","showSpeciesPageLink":true},"values":[0.0,0.0,0.0,0.0,0.0,0.0,0.0,0.0,0.0,0.0,0.0,0.0,0.0,0.0,0.0,0.0,0.0,0.0,0.0,0.0,0.0,0.0,0.0,0.0,0.0,0.0,0.0,0.0,0.0,0.0,0.0,0.0,0.0,0.0,0.0,0.0,1.0,0.0,0.0,0.0,0.0,0.0,0.0,0.0,0.0,0.0,0.0,0.0],"prettyValues":["0%","0%","0%","0%","0%","0%","0%","0%","0%","0%","0%","0%","0%","0%","0%","0%","0%","0%","0%","0%","0%","0%","0%","0%","0%","0%","0%","0%","0%","0%","0%","0%","0%","0%","0%","0%","100%","0%","0%","0%","0%","0%","0%","0%","0%","0%","0%","0%"],"values_N":[0,0,0,0,0,0,0,0,0,0,0,0,0,0,0,0,0,0,0,0,0,0,0,0,0,0,0,0,0,0,0,0,0,0,0,0,1,0,0,0,0,0,0,0,0,0,0,0],"buckets":[-1,-1,-1,-1,-1,-1,-1,-1,-1,-1,-1,-1,-1,-1,-1,-1,-1,-1,-1,-1,-1,-1,-1,-1,-1,-1,-1,-1,-1,-1,-1,-1,-1,-1,-1,-1,9,-1,-1,-1,-1,-1,-1,-1,-1,-1,-1,-1],"speciesCode":"scaswi1","name":"Scarce Swift"},{"taxon":{"displayName":"Little Swift","commonName":"Little Swift","sciName":"Apus affinis","speciesCode":"litswi1","category":"species","reportAsSpeciesCode":"litswi1","reportAsCategory":"species","showSpeciesPageLink":true},"values":[0.0,0.0,0.0,0.0,0.0,0.0,0.0,0.0,0.0,0.0,0.0,0.0,0.0,0.0,0.0,0.0,0.0,0.0,0.0,0.0,0.0,0.0,0.0,0.0,0.0,0.0,0.0,0.0,0.0,0.0,0.0,0.0,0.0,0.0,0.0,0.0,1.0,0.0,0.0,0.0,0.0,0.0,0.0,0.0,0.0,0.0,0.0,0.0],"prettyValues":["0%","0%","0%","0%","0%","0%","0%","0%","0%","0%","0%","0%","0%","0%","0%","0%","0%","0%","0%","0%","0%","0%","0%","0%","0%","0%","0%","0%","0%","0%","0%","0%","0%","0%","0%","0%","100%","0%","0%","0%","0%","0%","0%","0%","0%","0%","0%","0%"],"values_N":[0,0,0,0,0,0,0,0,0,0,0,0,0,0,0,0,0,0,0,0,0,0,0,0,0,0,0,0,0,0,0,0,0,0,0,0,1,0,0,0,0,0,0,0,0,0,0,0],"buckets":[-1,-1,-1,-1,-1,-1,-1,-1,-1,-1,-1,-1,-1,-1,-1,-1,-1,-1,-1,-1,-1,-1,-1,-1,-1,-1,-1,-1,-1,-1,-1,-1,-1,-1,-1,-1,9,-1,-1,-1,-1,-1,-1,-1,-1,-1,-1,-1],"speciesCode":"litswi1","name":"Little Swift"},{"taxon":{"displayName":"White-rumped Swift","commonName":"White-rumped Swift","sciName":"Apus caffer","speciesCode":"whrswi1","category":"species","reportAsSpeciesCode":"whrswi1","reportAsCategory":"species","showSpeciesPageLink":true},"values":[0.0,0.0,0.0,0.0,0.0,0.0,0.0,0.0,0.0,0.0,0.0,0.0,0.0,0.0,0.0,0.0,0.0,0.0,0.0,0.0,0.0,0.0,0.0,0.0,0.0,0.0,0.0,0.0,0.0,0.0,0.0,0.0,0.0,0.0,0.0,0.0,1.0,0.0,0.0,0.0,0.0,0.0,0.0,0.0,0.0,0.0,0.0,0.0],"prettyValues":["0%","0%","0%","0%","0%","0%","0%","0%","0%","0%","0%","0%","0%","0%","0%","0%","0%","0%","0%","0%","0%","0%","0%","0%","0%","0%","0%","0%","0%","0%","0%","0%","0%","0%","0%","0%","100%","0%","0%","0%","0%","0%","0%","0%","0%","0%","0%","0%"],"values_N":[0,0,0,0,0,0,0,0,0,0,0,0,0,0,0,0,0,0,0,0,0,0,0,0,0,0,0,0,0,0,0,0,0,0,0,0,1,0,0,0,0,0,0,0,0,0,0,0],"buckets":[-1,-1,-1,-1,-1,-1,-1,-1,-1,-1,-1,-1,-1,-1,-1,-1,-1,-1,-1,-1,-1,-1,-1,-1,-1,-1,-1,-1,-1,-1,-1,-1,-1,-1,-1,-1,9,-1,-1,-1,-1,-1,-1,-1,-1,-1,-1,-1],"speciesCode":"whrswi1","name":"White-rumped Swift"},{"taxon":{"displayName":"Hadada Ibis","commonName":"Hadada Ibis","sciName":"Bostrychia hagedash","speciesCode":"hadibi1","category":"species","reportAsSpeciesCode":"hadibi1","reportAsCategory":"species","showSpeciesPageLink":true},"values":[0.0,0.0,0.0,0.0,0.0,0.0,0.0,0.0,0.0,0.0,0.0,0.0,0.0,0.0,0.0,0.0,0.0,0.0,0.0,0.0,0.0,0.0,0.0,0.0,0.0,0.0,0.0,0.0,0.0,0.0,0.0,0.0,0.0,0.0,0.0,0.0,1.0,0.0,0.0,0.0,0.0,0.0,0.0,0.0,0.0,0.0,0.0,0.0],"prettyValues":["0%","0%","0%","0%","0%","0%","0%","0%","0%","0%","0%","0%","0%","0%","0%","0%","0%","0%","0%","0%","0%","0%","0%","0%","0%","0%","0%","0%","0%","0%","0%","0%","0%","0%","0%","0%","100%","0%","0%","0%","0%","0%","0%","0%","0%","0%","0%","0%"],"values_N":[0,0,0,0,0,0,0,0,0,0,0,0,0,0,0,0,0,0,0,0,0,0,0,0,0,0,0,0,0,0,0,0,0,0,0,0,1,0,0,0,0,0,0,0,0,0,0,0],"buckets":[-1,-1,-1,-1,-1,-1,-1,-1,-1,-1,-1,-1,-1,-1,-1,-1,-1,-1,-1,-1,-1,-1,-1,-1,-1,-1,-1,-1,-1,-1,-1,-1,-1,-1,-1,-1,9,-1,-1,-1,-1,-1,-1,-1,-1,-1,-1,-1],"speciesCode":"hadibi1","name":"Hadada Ibis"},{"taxon":{"displayName":"Long-crested Eagle","commonName":"Long-crested Eagle","sciName":"Lophaetus occipitalis","speciesCode":"loceag1","category":"species","reportAsSpeciesCode":"loceag1","reportAsCategory":"species","showSpeciesPageLink":true},"values":[0.0,0.0,0.0,0.0,0.0,0.0,0.0,0.0,0.0,0.0,0.0,0.0,0.0,0.0,0.0,0.0,0.0,0.0,0.0,0.0,0.0,0.0,0.0,0.0,0.0,0.0,0.0,0.0,0.0,0.0,0.0,0.0,0.0,0.0,0.0,0.0,1.0,0.0,0.0,0.0,0.0,0.0,0.0,0.0,0.0,0.0,0.0,0.0],"prettyValues":["0%","0%","0%","0%","0%","0%","0%","0%","0%","0%","0%","0%","0%","0%","0%","0%","0%","0%","0%","0%","0%","0%","0%","0%","0%","0%","0%","0%","0%","0%","0%","0%","0%","0%","0%","0%","100%","0%","0%","0%","0%","0%","0%","0%","0%","0%","0%","0%"],"values_N":[0,0,0,0,0,0,0,0,0,0,0,0,0,0,0,0,0,0,0,0,0,0,0,0,0,0,0,0,0,0,0,0,0,0,0,0,1,0,0,0,0,0,0,0,0,0,0,0],"buckets":[-1,-1,-1,-1,-1,-1,-1,-1,-1,-1,-1,-1,-1,-1,-1,-1,-1,-1,-1,-1,-1,-1,-1,-1,-1,-1,-1,-1,-1,-1,-1,-1,-1,-1,-1,-1,9,-1,-1,-1,-1,-1,-1,-1,-1,-1,-1,-1],"speciesCode":"loceag1","name":"Long-crested Eagle"},{"taxon":{"displayName":"Dark Chanting-Goshawk","commonName":"Dark Chanting-Goshawk","sciName":"Melierax metabates","speciesCode":"dacgos1","category":"species","reportAsSpeciesCode":"dacgos1","reportAsCategory":"species","showSpeciesPageLink":true},"values":[0.0,0.0,0.0,0.0,0.0,0.0,0.0,0.0,0.0,0.0,0.0,0.0,0.0,0.0,0.0,0.0,0.0,0.0,0.0,0.0,0.0,0.0,0.0,0.0,0.0,0.0,0.0,0.0,0.0,0.0,0.0,0.0,0.0,0.0,0.0,0.0,1.0,0.0,0.0,0.0,0.0,0.0,0.0,0.0,0.0,0.0,0.0,0.0],"prettyValues":["0%","0%","0%","0%","0%","0%","0%","0%","0%","0%","0%","0%","0%","0%","0%","0%","0%","0%","0%","0%","0%","0%","0%","0%","0%","0%","0%","0%","0%","0%","0%","0%","0%","0%","0%","0%","100%","0%","0%","0%","0%","0%","0%","0%","0%","0%","0%","0%"],"values_N":[0,0,0,0,0,0,0,0,0,0,0,0,0,0,0,0,0,0,0,0,0,0,0,0,0,0,0,0,0,0,0,0,0,0,0,0,1,0,0,0,0,0,0,0,0,0,0,0],"buckets":[-1,-1,-1,-1,-1,-1,-1,-1,-1,-1,-1,-1,-1,-1,-1,-1,-1,-1,-1,-1,-1,-1,-1,-1,-1,-1,-1,-1,-1,-1,-1,-1,-1,-1,-1,-1,9,-1,-1,-1,-1,-1,-1,-1,-1,-1,-1,-1],"speciesCode":"dacgos1","name":"Dark Chanting-Goshawk"},{"taxon":{"displayName":"Black Kite","commonName":"Black Kite","sciName":"Milvus migrans","speciesCode":"blakit1","category":"species","reportAsSpeciesCode":"blakit1","reportAsCategory":"species","showSpeciesPageLink":true},"values":[0.0,0.0,0.0,0.0,0.0,0.0,0.0,0.0,0.0,0.0,0.0,0.0,0.0,0.0,0.0,0.0,0.0,0.0,0.0,0.0,0.0,0.0,0.0,0.0,0.0,0.0,0.0,0.0,0.0,0.0,0.0,0.0,0.0,0.0,0.0,0.0,1.0,0.0,0.0,0.0,0.0,0.0,0.0,0.0,0.0,0.0,0.0,0.0],"prettyValues":["0%","0%","0%","0%","0%","0%","0%","0%","0%","0%","0%","0%","0%","0%","0%","0%","0%","0%","0%","0%","0%","0%","0%","0%","0%","0%","0%","0%","0%","0%","0%","0%","0%","0%","0%","0%","100%","0%","0%","0%","0%","0%","0%","0%","0%","0%","0%","0%"],"values_N":[0,0,0,0,0,0,0,0,0,0,0,0,0,0,0,0,0,0,0,0,0,0,0,0,0,0,0,0,0,0,0,0,0,0,0,0,1,0,0,0,0,0,0,0,0,0,0,0],"buckets":[-1,-1,-1,-1,-1,-1,-1,-1,-1,-1,-1,-1,-1,-1,-1,-1,-1,-1,-1,-1,-1,-1,-1,-1,-1,-1,-1,-1,-1,-1,-1,-1,-1,-1,-1,-1,9,-1,-1,-1,-1,-1,-1,-1,-1,-1,-1,-1],"speciesCode":"blakit1","name":"Black Kite"},{"taxon":{"displayName":"Augur Buzzard","commonName":"Augur Buzzard","sciName":"Buteo augur","speciesCode":"augbuz1","category":"species","reportAsSpeciesCode":"augbuz1","reportAsCategory":"species","showSpeciesPageLink":true},"values":[0.0,0.0,0.0,0.0,0.0,0.0,0.0,0.0,0.0,0.0,0.0,0.0,0.0,0.0,0.0,0.0,0.0,0.0,0.0,0.0,0.0,0.0,0.0,0.0,0.0,0.0,0.0,0.0,0.0,0.0,0.0,0.0,0.0,0.0,0.0,0.0,1.0,0.0,0.0,0.0,0.0,0.0,0.0,0.0,0.0,0.0,0.0,0.0],"prettyValues":["0%","0%","0%","0%","0%","0%","0%","0%","0%","0%","0%","0%","0%","0%","0%","0%","0%","0%","0%","0%","0%","0%","0%","0%","0%","0%","0%","0%","0%","0%","0%","0%","0%","0%","0%","0%","100%","0%","0%","0%","0%","0%","0%","0%","0%","0%","0%","0%"],"values_N":[0,0,0,0,0,0,0,0,0,0,0,0,0,0,0,0,0,0,0,0,0,0,0,0,0,0,0,0,0,0,0,0,0,0,0,0,1,0,0,0,0,0,0,0,0,0,0,0],"buckets":[-1,-1,-1,-1,-1,-1,-1,-1,-1,-1,-1,-1,-1,-1,-1,-1,-1,-1,-1,-1,-1,-1,-1,-1,-1,-1,-1,-1,-1,-1,-1,-1,-1,-1,-1,-1,9,-1,-1,-1,-1,-1,-1,-1,-1,-1,-1,-1],"speciesCode":"augbuz1","name":"Augur Buzzard"},{"taxon":{"displayName":"Speckled Mousebird","commonName":"Speckled Mousebird","sciName":"Colius striatus","speciesCode":"spemou2","category":"species","reportAsSpeciesCode":"spemou2","reportAsCategory":"species","showSpeciesPageLink":true},"values":[0.0,0.0,0.0,0.0,0.0,0.0,0.0,0.0,0.0,0.0,0.0,0.0,0.0,0.0,0.0,0.0,0.0,0.0,0.0,0.0,0.0,0.0,0.0,0.0,0.0,0.0,0.0,0.0,0.0,0.0,0.0,0.0,0.0,0.0,0.0,0.0,1.0,0.0,0.0,0.0,0.0,0.0,0.0,0.0,0.0,0.0,0.0,0.0],"prettyValues":["0%","0%","0%","0%","0%","0%","0%","0%","0%","0%","0%","0%","0%","0%","0%","0%","0%","0%","0%","0%","0%","0%","0%","0%","0%","0%","0%","0%","0%","0%","0%","0%","0%","0%","0%","0%","100%","0%","0%","0%","0%","0%","0%","0%","0%","0%","0%","0%"],"values_N":[0,0,0,0,0,0,0,0,0,0,0,0,0,0,0,0,0,0,0,0,0,0,0,0,0,0,0,0,0,0,0,0,0,0,0,0,1,0,0,0,0,0,0,0,0,0,0,0],"buckets":[-1,-1,-1,-1,-1,-1,-1,-1,-1,-1,-1,-1,-1,-1,-1,-1,-1,-1,-1,-1,-1,-1,-1,-1,-1,-1,-1,-1,-1,-1,-1,-1,-1,-1,-1,-1,9,-1,-1,-1,-1,-1,-1,-1,-1,-1,-1,-1],"speciesCode":"spemou2","name":"Speckled Mousebird"},{"taxon":{"displayName":"Black-and-white-casqued Hornbill","commonName":"Black-and-white-casqued Hornbill","sciName":"Bycanistes subcylindricus","speciesCode":"bawhor2","category":"species","reportAsSpeciesCode":"bawhor2","reportAsCategory":"species","showSpeciesPageLink":true},"values":[0.0,0.0,0.0,0.0,0.0,0.0,0.0,0.0,0.0,0.0,0.0,0.0,0.0,0.0,0.0,0.0,0.0,0.0,0.0,0.0,0.0,0.0,0.0,0.0,0.0,0.0,0.0,0.0,0.0,0.0,0.0,0.0,0.0,0.0,0.0,0.0,1.0,0.0,0.0,0.0,0.0,0.0,0.0,0.0,0.0,0.0,0.0,0.0],"prettyValues":["0%","0%","0%","0%","0%","0%","0%","0%","0%","0%","0%","0%","0%","0%","0%","0%","0%","0%","0%","0%","0%","0%","0%","0%","0%","0%","0%","0%","0%","0%","0%","0%","0%","0%","0%","0%","100%","0%","0%","0%","0%","0%","0%","0%","0%","0%","0%","0%"],"values_N":[0,0,0,0,0,0,0,0,0,0,0,0,0,0,0,0,0,0,0,0,0,0,0,0,0,0,0,0,0,0,0,0,0,0,0,0,1,0,0,0,0,0,0,0,0,0,0,0],"buckets":[-1,-1,-1,-1,-1,-1,-1,-1,-1,-1,-1,-1,-1,-1,-1,-1,-1,-1,-1,-1,-1,-1,-1,-1,-1,-1,-1,-1,-1,-1,-1,-1,-1,-1,-1,-1,9,-1,-1,-1,-1,-1,-1,-1,-1,-1,-1,-1],"speciesCode":"bawhor2","name":"Black-and-white-casqued Hornbill"},{"taxon":{"displayName":"Cinnamon-chested Bee-eater","commonName":"Cinnamon-chested Bee-eater","sciName":"Merops oreobates","speciesCode":"ccbeat1","category":"species","reportAsSpeciesCode":"ccbeat1","reportAsCategory":"species","showSpeciesPageLink":true},"values":[0.0,0.0,0.0,0.0,0.0,0.0,0.0,0.0,0.0,0.0,0.0,0.0,0.0,0.0,0.0,0.0,0.0,0.0,0.0,0.0,0.0,0.0,0.0,0.0,0.0,0.0,0.0,0.0,0.0,0.0,0.0,0.0,0.0,0.0,0.0,0.0,1.0,0.0,0.0,0.0,0.0,0.0,0.0,0.0,0.0,0.0,0.0,0.0],"prettyValues":["0%","0%","0%","0%","0%","0%","0%","0%","0%","0%","0%","0%","0%","0%","0%","0%","0%","0%","0%","0%","0%","0%","0%","0%","0%","0%","0%","0%","0%","0%","0%","0%","0%","0%","0%","0%","100%","0%","0%","0%","0%","0%","0%","0%","0%","0%","0%","0%"],"values_N":[0,0,0,0,0,0,0,0,0,0,0,0,0,0,0,0,0,0,0,0,0,0,0,0,0,0,0,0,0,0,0,0,0,0,0,0,1,0,0,0,0,0,0,0,0,0,0,0],"buckets":[-1,-1,-1,-1,-1,-1,-1,-1,-1,-1,-1,-1,-1,-1,-1,-1,-1,-1,-1,-1,-1,-1,-1,-1,-1,-1,-1,-1,-1,-1,-1,-1,-1,-1,-1,-1,9,-1,-1,-1,-1,-1,-1,-1,-1,-1,-1,-1],"speciesCode":"ccbeat1","name":"Cinnamon-chested Bee-eater"},{"taxon":{"displayName":"European Bee-eater","commonName":"European Bee-eater","sciName":"Merops apiaster","speciesCode":"eubeat1","category":"species","reportAsSpeciesCode":"eubeat1","reportAsCategory":"species","showSpeciesPageLink":true},"values":[0.0,0.0,0.0,0.0,0.0,0.0,0.0,0.0,0.0,0.0,0.0,0.0,0.0,0.0,0.0,0.0,0.0,0.0,0.0,0.0,0.0,0.0,0.0,0.0,0.0,0.0,0.0,0.0,0.0,0.0,0.0,0.0,0.0,0.0,0.0,0.0,1.0,0.0,0.0,0.0,0.0,0.0,0.0,0.0,0.0,0.0,0.0,0.0],"prettyValues":["0%","0%","0%","0%","0%","0%","0%","0%","0%","0%","0%","0%","0%","0%","0%","0%","0%","0%","0%","0%","0%","0%","0%","0%","0%","0%","0%","0%","0%","0%","0%","0%","0%","0%","0%","0%","100%","0%","0%","0%","0%","0%","0%","0%","0%","0%","0%","0%"],"values_N":[0,0,0,0,0,0,0,0,0,0,0,0,0,0,0,0,0,0,0,0,0,0,0,0,0,0,0,0,0,0,0,0,0,0,0,0,1,0,0,0,0,0,0,0,0,0,0,0],"buckets":[-1,-1,-1,-1,-1,-1,-1,-1,-1,-1,-1,-1,-1,-1,-1,-1,-1,-1,-1,-1,-1,-1,-1,-1,-1,-1,-1,-1,-1,-1,-1,-1,-1,-1,-1,-1,9,-1,-1,-1,-1,-1,-1,-1,-1,-1,-1,-1],"speciesCode":"eubeat1","name":"European Bee-eater"},{"taxon":{"displayName":"Yellow-rumped Tinkerbird","commonName":"Yellow-rumped Tinkerbird","sciName":"Pogoniulus bilineatus","speciesCode":"yertin1","category":"species","reportAsSpeciesCode":"yertin1","reportAsCategory":"species","showSpeciesPageLink":true},"values":[0.0,0.0,0.0,0.0,0.0,0.0,0.0,0.0,0.0,0.0,0.0,0.0,0.0,0.0,0.0,0.0,0.0,0.0,0.0,0.0,0.0,0.0,0.0,0.0,0.0,0.0,0.0,0.0,0.0,0.0,0.0,0.0,0.0,0.0,0.0,0.0,1.0,0.0,0.0,0.0,0.0,0.0,0.0,0.0,0.0,0.0,0.0,0.0],"prettyValues":["0%","0%","0%","0%","0%","0%","0%","0%","0%","0%","0%","0%","0%","0%","0%","0%","0%","0%","0%","0%","0%","0%","0%","0%","0%","0%","0%","0%","0%","0%","0%","0%","0%","0%","0%","0%","100%","0%","0%","0%","0%","0%","0%","0%","0%","0%","0%","0%"],"values_N":[0,0,0,0,0,0,0,0,0,0,0,0,0,0,0,0,0,0,0,0,0,0,0,0,0,0,0,0,0,0,0,0,0,0,0,0,1,0,0,0,0,0,0,0,0,0,0,0],"buckets":[-1,-1,-1,-1,-1,-1,-1,-1,-1,-1,-1,-1,-1,-1,-1,-1,-1,-1,-1,-1,-1,-1,-1,-1,-1,-1,-1,-1,-1,-1,-1,-1,-1,-1,-1,-1,9,-1,-1,-1,-1,-1,-1,-1,-1,-1,-1,-1],"speciesCode":"yertin1","name":"Yellow-rumped Tinkerbird"},{"taxon":{"displayName":"Lesser Honeyguide","commonName":"Lesser Honeyguide","sciName":"Indicator minor","speciesCode":"leshon1","category":"species","reportAsSpeciesCode":"leshon1","reportAsCategory":"species","showSpeciesPageLink":true},"values":[0.0,0.0,0.0,0.0,0.0,0.0,0.0,0.0,0.0,0.0,0.0,0.0,0.0,0.0,0.0,0.0,0.0,0.0,0.0,0.0,0.0,0.0,0.0,0.0,0.0,0.0,0.0,0.0,0.0,0.0,0.0,0.0,0.0,0.0,0.0,0.0,1.0,0.0,0.0,0.0,0.0,0.0,0.0,0.0,0.0,0.0,0.0,0.0],"prettyValues":["0%","0%","0%","0%","0%","0%","0%","0%","0%","0%","0%","0%","0%","0%","0%","0%","0%","0%","0%","0%","0%","0%","0%","0%","0%","0%","0%","0%","0%","0%","0%","0%","0%","0%","0%","0%","100%","0%","0%","0%","0%","0%","0%","0%","0%","0%","0%","0%"],"values_N":[0,0,0,0,0,0,0,0,0,0,0,0,0,0,0,0,0,0,0,0,0,0,0,0,0,0,0,0,0,0,0,0,0,0,0,0,1,0,0,0,0,0,0,0,0,0,0,0],"buckets":[-1,-1,-1,-1,-1,-1,-1,-1,-1,-1,-1,-1,-1,-1,-1,-1,-1,-1,-1,-1,-1,-1,-1,-1,-1,-1,-1,-1,-1,-1,-1,-1,-1,-1,-1,-1,9,-1,-1,-1,-1,-1,-1,-1,-1,-1,-1,-1],"speciesCode":"leshon1","name":"Lesser Honeyguide"},{"taxon":{"displayName":"Rufous-necked Wryneck","commonName":"Rufous-necked Wryneck","sciName":"Jynx ruficollis","speciesCode":"runwry1","category":"species","reportAsSpeciesCode":"runwry1","reportAsCategory":"species","showSpeciesPageLink":true},"values":[0.0,0.0,0.0,0.0,0.0,0.0,0.0,0.0,0.0,0.0,0.0,0.0,0.0,0.0,0.0,0.0,0.0,0.0,0.0,0.0,0.0,0.0,0.0,0.0,0.0,0.0,0.0,0.0,0.0,0.0,0.0,0.0,0.0,0.0,0.0,0.0,1.0,0.0,0.0,0.0,0.0,0.0,0.0,0.0,0.0,0.0,0.0,0.0],"prettyValues":["0%","0%","0%","0%","0%","0%","0%","0%","0%","0%","0%","0%","0%","0%","0%","0%","0%","0%","0%","0%","0%","0%","0%","0%","0%","0%","0%","0%","0%","0%","0%","0%","0%","0%","0%","0%","100%","0%","0%","0%","0%","0%","0%","0%","0%","0%","0%","0%"],"values_N":[0,0,0,0,0,0,0,0,0,0,0,0,0,0,0,0,0,0,0,0,0,0,0,0,0,0,0,0,0,0,0,0,0,0,0,0,1,0,0,0,0,0,0,0,0,0,0,0],"buckets":[-1,-1,-1,-1,-1,-1,-1,-1,-1,-1,-1,-1,-1,-1,-1,-1,-1,-1,-1,-1,-1,-1,-1,-1,-1,-1,-1,-1,-1,-1,-1,-1,-1,-1,-1,-1,9,-1,-1,-1,-1,-1,-1,-1,-1,-1,-1,-1],"speciesCode":"runwry1","name":"Rufous-necked Wryneck"},{"taxon":{"displayName":"Cardinal Woodpecker","commonName":"Cardinal Woodpecker","sciName":"Chloropicus fuscescens","speciesCode":"carwoo1","category":"species","reportAsSpeciesCode":"carwoo1","reportAsCategory":"species","showSpeciesPageLink":true},"values":[0.0,0.0,0.0,0.0,0.0,0.0,0.0,0.0,0.0,0.0,0.0,0.0,0.0,0.0,0.0,0.0,0.0,0.0,0.0,0.0,0.0,0.0,0.0,0.0,0.0,0.0,0.0,0.0,0.0,0.0,0.0,0.0,0.0,0.0,0.0,0.0,1.0,0.0,0.0,0.0,0.0,0.0,0.0,0.0,0.0,0.0,0.0,0.0],"prettyValues":["0%","0%","0%","0%","0%","0%","0%","0%","0%","0%","0%","0%","0%","0%","0%","0%","0%","0%","0%","0%","0%","0%","0%","0%","0%","0%","0%","0%","0%","0%","0%","0%","0%","0%","0%","0%","100%","0%","0%","0%","0%","0%","0%","0%","0%","0%","0%","0%"],"values_N":[0,0,0,0,0,0,0,0,0,0,0,0,0,0,0,0,0,0,0,0,0,0,0,0,0,0,0,0,0,0,0,0,0,0,0,0,1,0,0,0,0,0,0,0,0,0,0,0],"buckets":[-1,-1,-1,-1,-1,-1,-1,-1,-1,-1,-1,-1,-1,-1,-1,-1,-1,-1,-1,-1,-1,-1,-1,-1,-1,-1,-1,-1,-1,-1,-1,-1,-1,-1,-1,-1,9,-1,-1,-1,-1,-1,-1,-1,-1,-1,-1,-1],"speciesCode":"carwoo1","name":"Cardinal Woodpecker"},{"taxon":{"displayName":"African Hobby","commonName":"African Hobby","sciName":"Falco cuvierii","speciesCode":"afrhob1","category":"species","reportAsSpeciesCode":"afrhob1","reportAsCategory":"species","showSpeciesPageLink":true},"values":[0.0,0.0,0.0,0.0,0.0,0.0,0.0,0.0,0.0,0.0,0.0,0.0,0.0,0.0,0.0,0.0,0.0,0.0,0.0,0.0,0.0,0.0,0.0,0.0,0.0,0.0,0.0,0.0,0.0,0.0,0.0,0.0,0.0,0.0,0.0,0.0,1.0,0.0,0.0,0.0,0.0,0.0,0.0,0.0,0.0,0.0,0.0,0.0],"prettyValues":["0%","0%","0%","0%","0%","0%","0%","0%","0%","0%","0%","0%","0%","0%","0%","0%","0%","0%","0%","0%","0%","0%","0%","0%","0%","0%","0%","0%","0%","0%","0%","0%","0%","0%","0%","0%","100%","0%","0%","0%","0%","0%","0%","0%","0%","0%","0%","0%"],"values_N":[0,0,0,0,0,0,0,0,0,0,0,0,0,0,0,0,0,0,0,0,0,0,0,0,0,0,0,0,0,0,0,0,0,0,0,0,1,0,0,0,0,0,0,0,0,0,0,0],"buckets":[-1,-1,-1,-1,-1,-1,-1,-1,-1,-1,-1,-1,-1,-1,-1,-1,-1,-1,-1,-1,-1,-1,-1,-1,-1,-1,-1,-1,-1,-1,-1,-1,-1,-1,-1,-1,9,-1,-1,-1,-1,-1,-1,-1,-1,-1,-1,-1],"speciesCode":"afrhob1","name":"African Hobby"},{"taxon":{"displayName":"Gray Cuckooshrike","commonName":"Gray Cuckooshrike","sciName":"Coracina caesia","speciesCode":"grycus1","category":"species","reportAsSpeciesCode":"grycus1","reportAsCategory":"species","showSpeciesPageLink":true},"values":[0.0,0.0,0.0,0.0,0.0,0.0,0.0,0.0,0.0,0.0,0.0,0.0,0.0,0.0,0.0,0.0,0.0,0.0,0.0,0.0,0.0,0.0,0.0,0.0,0.0,0.0,0.0,0.0,0.0,0.0,0.0,0.0,0.0,0.0,0.0,0.0,1.0,0.0,0.0,0.0,0.0,0.0,0.0,0.0,0.0,0.0,0.0,0.0],"prettyValues":["0%","0%","0%","0%","0%","0%","0%","0%","0%","0%","0%","0%","0%","0%","0%","0%","0%","0%","0%","0%","0%","0%","0%","0%","0%","0%","0%","0%","0%","0%","0%","0%","0%","0%","0%","0%","100%","0%","0%","0%","0%","0%","0%","0%","0%","0%","0%","0%"],"values_N":[0,0,0,0,0,0,0,0,0,0,0,0,0,0,0,0,0,0,0,0,0,0,0,0,0,0,0,0,0,0,0,0,0,0,0,0,1,0,0,0,0,0,0,0,0,0,0,0],"buckets":[-1,-1,-1,-1,-1,-1,-1,-1,-1,-1,-1,-1,-1,-1,-1,-1,-1,-1,-1,-1,-1,-1,-1,-1,-1,-1,-1,-1,-1,-1,-1,-1,-1,-1,-1,-1,9,-1,-1,-1,-1,-1,-1,-1,-1,-1,-1,-1],"speciesCode":"grycus1","name":"Gray Cuckooshrike"},{"taxon":{"displayName":"Black-tailed Oriole","commonName":"Black-tailed Oriole","sciName":"Oriolus percivali","speciesCode":"bltori1","category":"species","reportAsSpeciesCode":"bltori1","reportAsCategory":"species","showSpeciesPageLink":true},"values":[0.0,0.0,0.0,0.0,0.0,0.0,0.0,0.0,0.0,0.0,0.0,0.0,0.0,0.0,0.0,0.0,0.0,0.0,0.0,0.0,0.0,0.0,0.0,0.0,0.0,0.0,0.0,0.0,0.0,0.0,0.0,0.0,0.0,0.0,0.0,0.0,1.0,0.0,0.0,0.0,0.0,0.0,0.0,0.0,0.0,0.0,0.0,0.0],"prettyValues":["0%","0%","0%","0%","0%","0%","0%","0%","0%","0%","0%","0%","0%","0%","0%","0%","0%","0%","0%","0%","0%","0%","0%","0%","0%","0%","0%","0%","0%","0%","0%","0%","0%","0%","0%","0%","100%","0%","0%","0%","0%","0%","0%","0%","0%","0%","0%","0%"],"values_N":[0,0,0,0,0,0,0,0,0,0,0,0,0,0,0,0,0,0,0,0,0,0,0,0,0,0,0,0,0,0,0,0,0,0,0,0,1,0,0,0,0,0,0,0,0,0,0,0],"buckets":[-1,-1,-1,-1,-1,-1,-1,-1,-1,-1,-1,-1,-1,-1,-1,-1,-1,-1,-1,-1,-1,-1,-1,-1,-1,-1,-1,-1,-1,-1,-1,-1,-1,-1,-1,-1,9,-1,-1,-1,-1,-1,-1,-1,-1,-1,-1,-1],"speciesCode":"bltori1","name":"Black-tailed Oriole"},{"taxon":{"displayName":"Black-throated Wattle-eye","commonName":"Black-throated Wattle-eye","sciName":"Platysteira peltata","speciesCode":"btweye1","category":"species","reportAsSpeciesCode":"btweye1","reportAsCategory":"species","showSpeciesPageLink":true},"values":[0.0,0.0,0.0,0.0,0.0,0.0,0.0,0.0,0.0,0.0,0.0,0.0,0.0,0.0,0.0,0.0,0.0,0.0,0.0,0.0,0.0,0.0,0.0,0.0,0.0,0.0,0.0,0.0,0.0,0.0,0.0,0.0,0.0,0.0,0.0,0.0,1.0,0.0,0.0,0.0,0.0,0.0,0.0,0.0,0.0,0.0,0.0,0.0],"prettyValues":["0%","0%","0%","0%","0%","0%","0%","0%","0%","0%","0%","0%","0%","0%","0%","0%","0%","0%","0%","0%","0%","0%","0%","0%","0%","0%","0%","0%","0%","0%","0%","0%","0%","0%","0%","0%","100%","0%","0%","0%","0%","0%","0%","0%","0%","0%","0%","0%"],"values_N":[0,0,0,0,0,0,0,0,0,0,0,0,0,0,0,0,0,0,0,0,0,0,0,0,0,0,0,0,0,0,0,0,0,0,0,0,1,0,0,0,0,0,0,0,0,0,0,0],"buckets":[-1,-1,-1,-1,-1,-1,-1,-1,-1,-1,-1,-1,-1,-1,-1,-1,-1,-1,-1,-1,-1,-1,-1,-1,-1,-1,-1,-1,-1,-1,-1,-1,-1,-1,-1,-1,9,-1,-1,-1,-1,-1,-1,-1,-1,-1,-1,-1],"speciesCode":"btweye1","name":"Black-throated Wattle-eye"},{"taxon":{"displayName":"Chinspot Batis","commonName":"Chinspot Batis","sciName":"Batis molitor","speciesCode":"chibat1","category":"species","reportAsSpeciesCode":"chibat1","reportAsCategory":"species","showSpeciesPageLink":true},"values":[0.0,0.0,0.0,0.0,0.0,0.0,0.0,0.0,0.0,0.0,0.0,0.0,0.0,0.0,0.0,0.0,0.0,0.0,0.0,0.0,0.0,0.0,0.0,0.0,0.0,0.0,0.0,0.0,0.0,0.0,0.0,0.0,0.0,0.0,0.0,0.0,1.0,0.0,0.0,0.0,0.0,0.0,0.0,0.0,0.0,0.0,0.0,0.0],"prettyValues":["0%","0%","0%","0%","0%","0%","0%","0%","0%","0%","0%","0%","0%","0%","0%","0%","0%","0%","0%","0%","0%","0%","0%","0%","0%","0%","0%","0%","0%","0%","0%","0%","0%","0%","0%","0%","100%","0%","0%","0%","0%","0%","0%","0%","0%","0%","0%","0%"],"values_N":[0,0,0,0,0,0,0,0,0,0,0,0,0,0,0,0,0,0,0,0,0,0,0,0,0,0,0,0,0,0,0,0,0,0,0,0,1,0,0,0,0,0,0,0,0,0,0,0],"buckets":[-1,-1,-1,-1,-1,-1,-1,-1,-1,-1,-1,-1,-1,-1,-1,-1,-1,-1,-1,-1,-1,-1,-1,-1,-1,-1,-1,-1,-1,-1,-1,-1,-1,-1,-1,-1,9,-1,-1,-1,-1,-1,-1,-1,-1,-1,-1,-1],"speciesCode":"chibat1","name":"Chinspot Batis"},{"taxon":{"displayName":"Tropical Boubou","commonName":"Tropical Boubou","sciName":"Laniarius major","speciesCode":"trobou1","category":"species","reportAsSpeciesCode":"trobou1","reportAsCategory":"species","showSpeciesPageLink":true},"values":[0.0,0.0,0.0,0.0,0.0,0.0,0.0,0.0,0.0,0.0,0.0,0.0,0.0,0.0,0.0,0.0,0.0,0.0,0.0,0.0,0.0,0.0,0.0,0.0,0.0,0.0,0.0,0.0,0.0,0.0,0.0,0.0,0.0,0.0,0.0,0.0,1.0,0.0,0.0,0.0,0.0,0.0,0.0,0.0,0.0,0.0,0.0,0.0],"prettyValues":["0%","0%","0%","0%","0%","0%","0%","0%","0%","0%","0%","0%","0%","0%","0%","0%","0%","0%","0%","0%","0%","0%","0%","0%","0%","0%","0%","0%","0%","0%","0%","0%","0%","0%","0%","0%","100%","0%","0%","0%","0%","0%","0%","0%","0%","0%","0%","0%"],"values_N":[0,0,0,0,0,0,0,0,0,0,0,0,0,0,0,0,0,0,0,0,0,0,0,0,0,0,0,0,0,0,0,0,0,0,0,0,1,0,0,0,0,0,0,0,0,0,0,0],"buckets":[-1,-1,-1,-1,-1,-1,-1,-1,-1,-1,-1,-1,-1,-1,-1,-1,-1,-1,-1,-1,-1,-1,-1,-1,-1,-1,-1,-1,-1,-1,-1,-1,-1,-1,-1,-1,9,-1,-1,-1,-1,-1,-1,-1,-1,-1,-1,-1],"speciesCode":"trobou1","name":"Tropical Boubou"},{"taxon":{"displayName":"Northern Fiscal","commonName":"Northern Fiscal","sciName":"Lanius humeralis","speciesCode":"norfis1","category":"species","reportAsSpeciesCode":"norfis1","reportAsCategory":"species","showSpeciesPageLink":true},"values":[0.0,0.0,0.0,0.0,0.0,0.0,0.0,0.0,0.0,0.0,0.0,0.0,0.0,0.0,0.0,0.0,0.0,0.0,0.0,0.0,0.0,0.0,0.0,0.0,0.0,0.0,0.0,0.0,0.0,0.0,0.0,0.0,0.0,0.0,0.0,0.0,1.0,0.0,0.0,0.0,0.0,0.0,0.0,0.0,0.0,0.0,0.0,0.0],"prettyValues":["0%","0%","0%","0%","0%","0%","0%","0%","0%","0%","0%","0%","0%","0%","0%","0%","0%","0%","0%","0%","0%","0%","0%","0%","0%","0%","0%","0%","0%","0%","0%","0%","0%","0%","0%","0%","100%","0%","0%","0%","0%","0%","0%","0%","0%","0%","0%","0%"],"values_N":[0,0,0,0,0,0,0,0,0,0,0,0,0,0,0,0,0,0,0,0,0,0,0,0,0,0,0,0,0,0,0,0,0,0,0,0,1,0,0,0,0,0,0,0,0,0,0,0],"buckets":[-1,-1,-1,-1,-1,-1,-1,-1,-1,-1,-1,-1,-1,-1,-1,-1,-1,-1,-1,-1,-1,-1,-1,-1,-1,-1,-1,-1,-1,-1,-1,-1,-1,-1,-1,-1,9,-1,-1,-1,-1,-1,-1,-1,-1,-1,-1,-1],"speciesCode":"norfis1","name":"Northern Fiscal"},{"taxon":{"displayName":"Pied Crow","commonName":"Pied Crow","sciName":"Corvus albus","speciesCode":"piecro1","category":"species","reportAsSpeciesCode":"piecro1","reportAsCategory":"species","showSpeciesPageLink":true},"values":[0.0,0.0,0.0,0.0,0.0,0.0,0.0,0.0,0.0,0.0,0.0,0.0,0.0,0.0,0.0,0.0,0.0,0.0,0.0,0.0,0.0,0.0,0.0,0.0,0.0,0.0,0.0,0.0,0.0,0.0,0.0,0.0,0.0,0.0,0.0,0.0,1.0,0.0,0.0,0.0,0.0,0.0,0.0,0.0,0.0,0.0,0.0,0.0],"prettyValues":["0%","0%","0%","0%","0%","0%","0%","0%","0%","0%","0%","0%","0%","0%","0%","0%","0%","0%","0%","0%","0%","0%","0%","0%","0%","0%","0%","0%","0%","0%","0%","0%","0%","0%","0%","0%","100%","0%","0%","0%","0%","0%","0%","0%","0%","0%","0%","0%"],"values_N":[0,0,0,0,0,0,0,0,0,0,0,0,0,0,0,0,0,0,0,0,0,0,0,0,0,0,0,0,0,0,0,0,0,0,0,0,1,0,0,0,0,0,0,0,0,0,0,0],"buckets":[-1,-1,-1,-1,-1,-1,-1,-1,-1,-1,-1,-1,-1,-1,-1,-1,-1,-1,-1,-1,-1,-1,-1,-1,-1,-1,-1,-1,-1,-1,-1,-1,-1,-1,-1,-1,9,-1,-1,-1,-1,-1,-1,-1,-1,-1,-1,-1],"speciesCode":"piecro1","name":"Pied Crow"},{"taxon":{"displayName":"Fan-tailed Raven","commonName":"Fan-tailed Raven","sciName":"Corvus rhipidurus","speciesCode":"fatrav1","category":"species","reportAsSpeciesCode":"fatrav1","reportAsCategory":"species","showSpeciesPageLink":true},"values":[0.0,0.0,0.0,0.0,0.0,0.0,0.0,0.0,0.0,0.0,0.0,0.0,0.0,0.0,0.0,0.0,0.0,0.0,0.0,0.0,0.0,0.0,0.0,0.0,0.0,0.0,0.0,0.0,0.0,0.0,0.0,0.0,0.0,0.0,0.0,0.0,1.0,0.0,0.0,0.0,0.0,0.0,0.0,0.0,0.0,0.0,0.0,0.0],"prettyValues":["0%","0%","0%","0%","0%","0%","0%","0%","0%","0%","0%","0%","0%","0%","0%","0%","0%","0%","0%","0%","0%","0%","0%","0%","0%","0%","0%","0%","0%","0%","0%","0%","0%","0%","0%","0%","100%","0%","0%","0%","0%","0%","0%","0%","0%","0%","0%","0%"],"values_N":[0,0,0,0,0,0,0,0,0,0,0,0,0,0,0,0,0,0,0,0,0,0,0,0,0,0,0,0,0,0,0,0,0,0,0,0,1,0,0,0,0,0,0,0,0,0,0,0],"buckets":[-1,-1,-1,-1,-1,-1,-1,-1,-1,-1,-1,-1,-1,-1,-1,-1,-1,-1,-1,-1,-1,-1,-1,-1,-1,-1,-1,-1,-1,-1,-1,-1,-1,-1,-1,-1,9,-1,-1,-1,-1,-1,-1,-1,-1,-1,-1,-1],"speciesCode":"fatrav1","name":"Fan-tailed Raven"},{"taxon":{"displayName":"African Blue Flycatcher","commonName":"African Blue Flycatcher","sciName":"Elminia longicauda","speciesCode":"afbfly1","category":"species","reportAsSpeciesCode":"afbfly1","reportAsCategory":"species","showSpeciesPageLink":true},"values":[0.0,0.0,0.0,0.0,0.0,0.0,0.0,0.0,0.0,0.0,0.0,0.0,0.0,0.0,0.0,0.0,0.0,0.0,0.0,0.0,0.0,0.0,0.0,0.0,0.0,0.0,0.0,0.0,0.0,0.0,0.0,0.0,0.0,0.0,0.0,0.0,1.0,0.0,0.0,0.0,0.0,0.0,0.0,0.0,0.0,0.0,0.0,0.0],"prettyValues":["0%","0%","0%","0%","0%","0%","0%","0%","0%","0%","0%","0%","0%","0%","0%","0%","0%","0%","0%","0%","0%","0%","0%","0%","0%","0%","0%","0%","0%","0%","0%","0%","0%","0%","0%","0%","100%","0%","0%","0%","0%","0%","0%","0%","0%","0%","0%","0%"],"values_N":[0,0,0,0,0,0,0,0,0,0,0,0,0,0,0,0,0,0,0,0,0,0,0,0,0,0,0,0,0,0,0,0,0,0,0,0,1,0,0,0,0,0,0,0,0,0,0,0],"buckets":[-1,-1,-1,-1,-1,-1,-1,-1,-1,-1,-1,-1,-1,-1,-1,-1,-1,-1,-1,-1,-1,-1,-1,-1,-1,-1,-1,-1,-1,-1,-1,-1,-1,-1,-1,-1,9,-1,-1,-1,-1,-1,-1,-1,-1,-1,-1,-1],"speciesCode":"afbfly1","name":"African Blue Flycatcher"},{"taxon":{"displayName":"White-bellied Tit","commonName":"White-bellied Tit","sciName":"Melaniparus albiventris","speciesCode":"whbtit5","category":"species","reportAsSpeciesCode":"whbtit5","reportAsCategory":"species","showSpeciesPageLink":true},"values":[0.0,0.0,0.0,0.0,0.0,0.0,0.0,0.0,0.0,0.0,0.0,0.0,0.0,0.0,0.0,0.0,0.0,0.0,0.0,0.0,0.0,0.0,0.0,0.0,0.0,0.0,0.0,0.0,0.0,0.0,0.0,0.0,0.0,0.0,0.0,0.0,1.0,0.0,0.0,0.0,0.0,0.0,0.0,0.0,0.0,0.0,0.0,0.0],"prettyValues":["0%","0%","0%","0%","0%","0%","0%","0%","0%","0%","0%","0%","0%","0%","0%","0%","0%","0%","0%","0%","0%","0%","0%","0%","0%","0%","0%","0%","0%","0%","0%","0%","0%","0%","0%","0%","100%","0%","0%","0%","0%","0%","0%","0%","0%","0%","0%","0%"],"values_N":[0,0,0,0,0,0,0,0,0,0,0,0,0,0,0,0,0,0,0,0,0,0,0,0,0,0,0,0,0,0,0,0,0,0,0,0,1,0,0,0,0,0,0,0,0,0,0,0],"buckets":[-1,-1,-1,-1,-1,-1,-1,-1,-1,-1,-1,-1,-1,-1,-1,-1,-1,-1,-1,-1,-1,-1,-1,-1,-1,-1,-1,-1,-1,-1,-1,-1,-1,-1,-1,-1,9,-1,-1,-1,-1,-1,-1,-1,-1,-1,-1,-1],"speciesCode":"whbtit5","name":"White-bellied Tit"},{"taxon":{"displayName":"Black-collared Apalis","commonName":"Black-collared Apalis","sciName":"Oreolais pulcher","speciesCode":"blcapa2","category":"species","reportAsSpeciesCode":"blcapa2","reportAsCategory":"species","showSpeciesPageLink":true},"values":[0.0,0.0,0.0,0.0,0.0,0.0,0.0,0.0,0.0,0.0,0.0,0.0,0.0,0.0,0.0,0.0,0.0,0.0,0.0,0.0,0.0,0.0,0.0,0.0,0.0,0.0,0.0,0.0,0.0,0.0,0.0,0.0,0.0,0.0,0.0,0.0,1.0,0.0,0.0,0.0,0.0,0.0,0.0,0.0,0.0,0.0,0.0,0.0],"prettyValues":["0%","0%","0%","0%","0%","0%","0%","0%","0%","0%","0%","0%","0%","0%","0%","0%","0%","0%","0%","0%","0%","0%","0%","0%","0%","0%","0%","0%","0%","0%","0%","0%","0%","0%","0%","0%","100%","0%","0%","0%","0%","0%","0%","0%","0%","0%","0%","0%"],"values_N":[0,0,0,0,0,0,0,0,0,0,0,0,0,0,0,0,0,0,0,0,0,0,0,0,0,0,0,0,0,0,0,0,0,0,0,0,1,0,0,0,0,0,0,0,0,0,0,0],"buckets":[-1,-1,-1,-1,-1,-1,-1,-1,-1,-1,-1,-1,-1,-1,-1,-1,-1,-1,-1,-1,-1,-1,-1,-1,-1,-1,-1,-1,-1,-1,-1,-1,-1,-1,-1,-1,9,-1,-1,-1,-1,-1,-1,-1,-1,-1,-1,-1],"speciesCode":"blcapa2","name":"Black-collared Apalis"},{"taxon":{"displayName":"Black-throated Apalis","commonName":"Black-throated Apalis","sciName":"Apalis jacksoni","speciesCode":"bltapa1","category":"species","reportAsSpeciesCode":"bltapa1","reportAsCategory":"species","showSpeciesPageLink":true},"values":[0.0,0.0,0.0,0.0,0.0,0.0,0.0,0.0,0.0,0.0,0.0,0.0,0.0,0.0,0.0,0.0,0.0,0.0,0.0,0.0,0.0,0.0,0.0,0.0,0.0,0.0,0.0,0.0,0.0,0.0,0.0,0.0,0.0,0.0,0.0,0.0,1.0,0.0,0.0,0.0,0.0,0.0,0.0,0.0,0.0,0.0,0.0,0.0],"prettyValues":["0%","0%","0%","0%","0%","0%","0%","0%","0%","0%","0%","0%","0%","0%","0%","0%","0%","0%","0%","0%","0%","0%","0%","0%","0%","0%","0%","0%","0%","0%","0%","0%","0%","0%","0%","0%","100%","0%","0%","0%","0%","0%","0%","0%","0%","0%","0%","0%"],"values_N":[0,0,0,0,0,0,0,0,0,0,0,0,0,0,0,0,0,0,0,0,0,0,0,0,0,0,0,0,0,0,0,0,0,0,0,0,1,0,0,0,0,0,0,0,0,0,0,0],"buckets":[-1,-1,-1,-1,-1,-1,-1,-1,-1,-1,-1,-1,-1,-1,-1,-1,-1,-1,-1,-1,-1,-1,-1,-1,-1,-1,-1,-1,-1,-1,-1,-1,-1,-1,-1,-1,9,-1,-1,-1,-1,-1,-1,-1,-1,-1,-1,-1],"speciesCode":"bltapa1","name":"Black-throated Apalis"},{"taxon":{"displayName":"Chestnut-throated Apalis","commonName":"Chestnut-throated Apalis","sciName":"Apalis porphyrolaema","speciesCode":"chtapa3","category":"species","reportAsSpeciesCode":"chtapa3","reportAsCategory":"species","showSpeciesPageLink":true},"values":[0.0,0.0,0.0,0.0,0.0,0.0,0.0,0.0,0.0,0.0,0.0,0.0,0.0,0.0,0.0,0.0,0.0,0.0,0.0,0.0,0.0,0.0,0.0,0.0,0.0,0.0,0.0,0.0,0.0,0.0,0.0,0.0,0.0,0.0,0.0,0.0,1.0,0.0,0.0,0.0,0.0,0.0,0.0,0.0,0.0,0.0,0.0,0.0],"prettyValues":["0%","0%","0%","0%","0%","0%","0%","0%","0%","0%","0%","0%","0%","0%","0%","0%","0%","0%","0%","0%","0%","0%","0%","0%","0%","0%","0%","0%","0%","0%","0%","0%","0%","0%","0%","0%","100%","0%","0%","0%","0%","0%","0%","0%","0%","0%","0%","0%"],"values_N":[0,0,0,0,0,0,0,0,0,0,0,0,0,0,0,0,0,0,0,0,0,0,0,0,0,0,0,0,0,0,0,0,0,0,0,0,1,0,0,0,0,0,0,0,0,0,0,0],"buckets":[-1,-1,-1,-1,-1,-1,-1,-1,-1,-1,-1,-1,-1,-1,-1,-1,-1,-1,-1,-1,-1,-1,-1,-1,-1,-1,-1,-1,-1,-1,-1,-1,-1,-1,-1,-1,9,-1,-1,-1,-1,-1,-1,-1,-1,-1,-1,-1],"speciesCode":"chtapa3","name":"Chestnut-throated Apalis"},{"taxon":{"displayName":"Gray Apalis","commonName":"Gray Apalis","sciName":"Apalis cinerea","speciesCode":"gryapa1","category":"species","reportAsSpeciesCode":"gryapa1","reportAsCategory":"species","showSpeciesPageLink":true},"values":[0.0,0.0,0.0,0.0,0.0,0.0,0.0,0.0,0.0,0.0,0.0,0.0,0.0,0.0,0.0,0.0,0.0,0.0,0.0,0.0,0.0,0.0,0.0,0.0,0.0,0.0,0.0,0.0,0.0,0.0,0.0,0.0,0.0,0.0,0.0,0.0,1.0,0.0,0.0,0.0,0.0,0.0,0.0,0.0,0.0,0.0,0.0,0.0],"prettyValues":["0%","0%","0%","0%","0%","0%","0%","0%","0%","0%","0%","0%","0%","0%","0%","0%","0%","0%","0%","0%","0%","0%","0%","0%","0%","0%","0%","0%","0%","0%","0%","0%","0%","0%","0%","0%","100%","0%","0%","0%","0%","0%","0%","0%","0%","0%","0%","0%"],"values_N":[0,0,0,0,0,0,0,0,0,0,0,0,0,0,0,0,0,0,0,0,0,0,0,0,0,0,0,0,0,0,0,0,0,0,0,0,1,0,0,0,0,0,0,0,0,0,0,0],"buckets":[-1,-1,-1,-1,-1,-1,-1,-1,-1,-1,-1,-1,-1,-1,-1,-1,-1,-1,-1,-1,-1,-1,-1,-1,-1,-1,-1,-1,-1,-1,-1,-1,-1,-1,-1,-1,9,-1,-1,-1,-1,-1,-1,-1,-1,-1,-1,-1],"speciesCode":"gryapa1","name":"Gray Apalis"},{"taxon":{"displayName":"Tawny-flanked Prinia","commonName":"Tawny-flanked Prinia","sciName":"Prinia subflava","speciesCode":"tafpri1","category":"species","reportAsSpeciesCode":"tafpri1","reportAsCategory":"species","showSpeciesPageLink":true},"values":[0.0,0.0,0.0,0.0,0.0,0.0,0.0,0.0,0.0,0.0,0.0,0.0,0.0,0.0,0.0,0.0,0.0,0.0,0.0,0.0,0.0,0.0,0.0,0.0,0.0,0.0,0.0,0.0,0.0,0.0,0.0,0.0,0.0,0.0,0.0,0.0,1.0,0.0,0.0,0.0,0.0,0.0,0.0,0.0,0.0,0.0,0.0,0.0],"prettyValues":["0%","0%","0%","0%","0%","0%","0%","0%","0%","0%","0%","0%","0%","0%","0%","0%","0%","0%","0%","0%","0%","0%","0%","0%","0%","0%","0%","0%","0%","0%","0%","0%","0%","0%","0%","0%","100%","0%","0%","0%","0%","0%","0%","0%","0%","0%","0%","0%"],"values_N":[0,0,0,0,0,0,0,0,0,0,0,0,0,0,0,0,0,0,0,0,0,0,0,0,0,0,0,0,0,0,0,0,0,0,0,0,1,0,0,0,0,0,0,0,0,0,0,0],"buckets":[-1,-1,-1,-1,-1,-1,-1,-1,-1,-1,-1,-1,-1,-1,-1,-1,-1,-1,-1,-1,-1,-1,-1,-1,-1,-1,-1,-1,-1,-1,-1,-1,-1,-1,-1,-1,9,-1,-1,-1,-1,-1,-1,-1,-1,-1,-1,-1],"speciesCode":"tafpri1","name":"Tawny-flanked Prinia"},{"taxon":{"displayName":"Singing Cisticola","commonName":"Singing Cisticola","sciName":"Cisticola cantans","speciesCode":"sincis1","category":"species","reportAsSpeciesCode":"sincis1","reportAsCategory":"species","showSpeciesPageLink":true},"values":[0.0,0.0,0.0,0.0,0.0,0.0,0.0,0.0,0.0,0.0,0.0,0.0,0.0,0.0,0.0,0.0,0.0,0.0,0.0,0.0,0.0,0.0,0.0,0.0,0.0,0.0,0.0,0.0,0.0,0.0,0.0,0.0,0.0,0.0,0.0,0.0,1.0,0.0,0.0,0.0,0.0,0.0,0.0,0.0,0.0,0.0,0.0,0.0],"prettyValues":["0%","0%","0%","0%","0%","0%","0%","0%","0%","0%","0%","0%","0%","0%","0%","0%","0%","0%","0%","0%","0%","0%","0%","0%","0%","0%","0%","0%","0%","0%","0%","0%","0%","0%","0%","0%","100%","0%","0%","0%","0%","0%","0%","0%","0%","0%","0%","0%"],"values_N":[0,0,0,0,0,0,0,0,0,0,0,0,0,0,0,0,0,0,0,0,0,0,0,0,0,0,0,0,0,0,0,0,0,0,0,0,1,0,0,0,0,0,0,0,0,0,0,0],"buckets":[-1,-1,-1,-1,-1,-1,-1,-1,-1,-1,-1,-1,-1,-1,-1,-1,-1,-1,-1,-1,-1,-1,-1,-1,-1,-1,-1,-1,-1,-1,-1,-1,-1,-1,-1,-1,9,-1,-1,-1,-1,-1,-1,-1,-1,-1,-1,-1],"speciesCode":"sincis1","name":"Singing Cisticola"},{"taxon":{"displayName":"Chubb's Cisticola","commonName":"Chubb's Cisticola","sciName":"Cisticola chubbi","speciesCode":"chucis1","category":"species","reportAsSpeciesCode":"chucis1","reportAsCategory":"species","showSpeciesPageLink":true},"values":[0.0,0.0,0.0,0.0,0.0,0.0,0.0,0.0,0.0,0.0,0.0,0.0,0.0,0.0,0.0,0.0,0.0,0.0,0.0,0.0,0.0,0.0,0.0,0.0,0.0,0.0,0.0,0.0,0.0,0.0,0.0,0.0,0.0,0.0,0.0,0.0,1.0,0.0,0.0,0.0,0.0,0.0,0.0,0.0,0.0,0.0,0.0,0.0],"prettyValues":["0%","0%","0%","0%","0%","0%","0%","0%","0%","0%","0%","0%","0%","0%","0%","0%","0%","0%","0%","0%","0%","0%","0%","0%","0%","0%","0%","0%","0%","0%","0%","0%","0%","0%","0%","0%","100%","0%","0%","0%","0%","0%","0%","0%","0%","0%","0%","0%"],"values_N":[0,0,0,0,0,0,0,0,0,0,0,0,0,0,0,0,0,0,0,0,0,0,0,0,0,0,0,0,0,0,0,0,0,0,0,0,1,0,0,0,0,0,0,0,0,0,0,0],"buckets":[-1,-1,-1,-1,-1,-1,-1,-1,-1,-1,-1,-1,-1,-1,-1,-1,-1,-1,-1,-1,-1,-1,-1,-1,-1,-1,-1,-1,-1,-1,-1,-1,-1,-1,-1,-1,9,-1,-1,-1,-1,-1,-1,-1,-1,-1,-1,-1],"speciesCode":"chucis1","name":"Chubb's Cisticola"},{"taxon":{"displayName":"Mountain Yellow-Warbler","commonName":"Mountain Yellow-Warbler","sciName":"Iduna similis","speciesCode":"moywar1","category":"species","reportAsSpeciesCode":"moywar1","reportAsCategory":"species","showSpeciesPageLink":true},"values":[0.0,0.0,0.0,0.0,0.0,0.0,0.0,0.0,0.0,0.0,0.0,0.0,0.0,0.0,0.0,0.0,0.0,0.0,0.0,0.0,0.0,0.0,0.0,0.0,0.0,0.0,0.0,0.0,0.0,0.0,0.0,0.0,0.0,0.0,0.0,0.0,1.0,0.0,0.0,0.0,0.0,0.0,0.0,0.0,0.0,0.0,0.0,0.0],"prettyValues":["0%","0%","0%","0%","0%","0%","0%","0%","0%","0%","0%","0%","0%","0%","0%","0%","0%","0%","0%","0%","0%","0%","0%","0%","0%","0%","0%","0%","0%","0%","0%","0%","0%","0%","0%","0%","100%","0%","0%","0%","0%","0%","0%","0%","0%","0%","0%","0%"],"values_N":[0,0,0,0,0,0,0,0,0,0,0,0,0,0,0,0,0,0,0,0,0,0,0,0,0,0,0,0,0,0,0,0,0,0,0,0,1,0,0,0,0,0,0,0,0,0,0,0],"buckets":[-1,-1,-1,-1,-1,-1,-1,-1,-1,-1,-1,-1,-1,-1,-1,-1,-1,-1,-1,-1,-1,-1,-1,-1,-1,-1,-1,-1,-1,-1,-1,-1,-1,-1,-1,-1,9,-1,-1,-1,-1,-1,-1,-1,-1,-1,-1,-1],"speciesCode":"moywar1","name":"Mountain Yellow-Warbler"},{"taxon":{"displayName":"Cinnamon Bracken-Warbler","commonName":"Cinnamon Bracken-Warbler","sciName":"Bradypterus cinnamomeus","speciesCode":"cibwar1","category":"species","reportAsSpeciesCode":"cibwar1","reportAsCategory":"species","showSpeciesPageLink":true},"values":[0.0,0.0,0.0,0.0,0.0,0.0,0.0,0.0,0.0,0.0,0.0,0.0,0.0,0.0,0.0,0.0,0.0,0.0,0.0,0.0,0.0,0.0,0.0,0.0,0.0,0.0,0.0,0.0,0.0,0.0,0.0,0.0,0.0,0.0,0.0,0.0,1.0,0.0,0.0,0.0,0.0,0.0,0.0,0.0,0.0,0.0,0.0,0.0],"prettyValues":["0%","0%","0%","0%","0%","0%","0%","0%","0%","0%","0%","0%","0%","0%","0%","0%","0%","0%","0%","0%","0%","0%","0%","0%","0%","0%","0%","0%","0%","0%","0%","0%","0%","0%","0%","0%","100%","0%","0%","0%","0%","0%","0%","0%","0%","0%","0%","0%"],"values_N":[0,0,0,0,0,0,0,0,0,0,0,0,0,0,0,0,0,0,0,0,0,0,0,0,0,0,0,0,0,0,0,0,0,0,0,0,1,0,0,0,0,0,0,0,0,0,0,0],"buckets":[-1,-1,-1,-1,-1,-1,-1,-1,-1,-1,-1,-1,-1,-1,-1,-1,-1,-1,-1,-1,-1,-1,-1,-1,-1,-1,-1,-1,-1,-1,-1,-1,-1,-1,-1,-1,9,-1,-1,-1,-1,-1,-1,-1,-1,-1,-1,-1],"speciesCode":"cibwar1","name":"Cinnamon Bracken-Warbler"},{"taxon":{"displayName":"Rock Martin","commonName":"Rock Martin","sciName":"Ptyonoprogne fuligula","speciesCode":"rocmar2","category":"species","reportAsSpeciesCode":"rocmar2","reportAsCategory":"species","showSpeciesPageLink":true},"values":[0.0,0.0,0.0,0.0,0.0,0.0,0.0,0.0,0.0,0.0,0.0,0.0,0.0,0.0,0.0,0.0,0.0,0.0,0.0,0.0,0.0,0.0,0.0,0.0,0.0,0.0,0.0,0.0,0.0,0.0,0.0,0.0,0.0,0.0,0.0,0.0,1.0,0.0,0.0,0.0,0.0,0.0,0.0,0.0,0.0,0.0,0.0,0.0],"prettyValues":["0%","0%","0%","0%","0%","0%","0%","0%","0%","0%","0%","0%","0%","0%","0%","0%","0%","0%","0%","0%","0%","0%","0%","0%","0%","0%","0%","0%","0%","0%","0%","0%","0%","0%","0%","0%","100%","0%","0%","0%","0%","0%","0%","0%","0%","0%","0%","0%"],"values_N":[0,0,0,0,0,0,0,0,0,0,0,0,0,0,0,0,0,0,0,0,0,0,0,0,0,0,0,0,0,0,0,0,0,0,0,0,1,0,0,0,0,0,0,0,0,0,0,0],"buckets":[-1,-1,-1,-1,-1,-1,-1,-1,-1,-1,-1,-1,-1,-1,-1,-1,-1,-1,-1,-1,-1,-1,-1,-1,-1,-1,-1,-1,-1,-1,-1,-1,-1,-1,-1,-1,9,-1,-1,-1,-1,-1,-1,-1,-1,-1,-1,-1],"speciesCode":"rocmar2","name":"Rock Martin"},{"taxon":{"displayName":"Barn Swallow","commonName":"Barn Swallow","sciName":"Hirundo rustica","speciesCode":"barswa","category":"species","reportAsSpeciesCode":"barswa","reportAsCategory":"species","showSpeciesPageLink":true},"values":[0.0,0.0,0.0,0.0,0.0,0.0,0.0,0.0,0.0,0.0,0.0,0.0,0.0,0.0,0.0,0.0,0.0,0.0,0.0,0.0,0.0,0.0,0.0,0.0,0.0,0.0,0.0,0.0,0.0,0.0,0.0,0.0,0.0,0.0,0.0,0.0,1.0,0.0,0.0,0.0,0.0,0.0,0.0,0.0,0.0,0.0,0.0,0.0],"prettyValues":["0%","0%","0%","0%","0%","0%","0%","0%","0%","0%","0%","0%","0%","0%","0%","0%","0%","0%","0%","0%","0%","0%","0%","0%","0%","0%","0%","0%","0%","0%","0%","0%","0%","0%","0%","0%","100%","0%","0%","0%","0%","0%","0%","0%","0%","0%","0%","0%"],"values_N":[0,0,0,0,0,0,0,0,0,0,0,0,0,0,0,0,0,0,0,0,0,0,0,0,0,0,0,0,0,0,0,0,0,0,0,0,1,0,0,0,0,0,0,0,0,0,0,0],"buckets":[-1,-1,-1,-1,-1,-1,-1,-1,-1,-1,-1,-1,-1,-1,-1,-1,-1,-1,-1,-1,-1,-1,-1,-1,-1,-1,-1,-1,-1,-1,-1,-1,-1,-1,-1,-1,9,-1,-1,-1,-1,-1,-1,-1,-1,-1,-1,-1],"speciesCode":"barswa","name":"Barn Swallow"},{"taxon":{"displayName":"Mosque Swallow","commonName":"Mosque Swallow","sciName":"Cecropis senegalensis","speciesCode":"mosswa2","category":"species","reportAsSpeciesCode":"mosswa2","reportAsCategory":"species","showSpeciesPageLink":true},"values":[0.0,0.0,0.0,0.0,0.0,0.0,0.0,0.0,0.0,0.0,0.0,0.0,0.0,0.0,0.0,0.0,0.0,0.0,0.0,0.0,0.0,0.0,0.0,0.0,0.0,0.0,0.0,0.0,0.0,0.0,0.0,0.0,0.0,0.0,0.0,0.0,1.0,0.0,0.0,0.0,0.0,0.0,0.0,0.0,0.0,0.0,0.0,0.0],"prettyValues":["0%","0%","0%","0%","0%","0%","0%","0%","0%","0%","0%","0%","0%","0%","0%","0%","0%","0%","0%","0%","0%","0%","0%","0%","0%","0%","0%","0%","0%","0%","0%","0%","0%","0%","0%","0%","100%","0%","0%","0%","0%","0%","0%","0%","0%","0%","0%","0%"],"values_N":[0,0,0,0,0,0,0,0,0,0,0,0,0,0,0,0,0,0,0,0,0,0,0,0,0,0,0,0,0,0,0,0,0,0,0,0,1,0,0,0,0,0,0,0,0,0,0,0],"buckets":[-1,-1,-1,-1,-1,-1,-1,-1,-1,-1,-1,-1,-1,-1,-1,-1,-1,-1,-1,-1,-1,-1,-1,-1,-1,-1,-1,-1,-1,-1,-1,-1,-1,-1,-1,-1,9,-1,-1,-1,-1,-1,-1,-1,-1,-1,-1,-1],"speciesCode":"mosswa2","name":"Mosque Swallow"},{"taxon":{"displayName":"Common House-Martin","commonName":"Common House-Martin","sciName":"Delichon urbicum","speciesCode":"cohmar1","category":"species","reportAsSpeciesCode":"cohmar1","reportAsCategory":"species","showSpeciesPageLink":true},"values":[0.0,0.0,0.0,0.0,0.0,0.0,0.0,0.0,0.0,0.0,0.0,0.0,0.0,0.0,0.0,0.0,0.0,0.0,0.0,0.0,0.0,0.0,0.0,0.0,0.0,0.0,0.0,0.0,0.0,0.0,0.0,0.0,0.0,0.0,0.0,0.0,1.0,0.0,0.0,0.0,0.0,0.0,0.0,0.0,0.0,0.0,0.0,0.0],"prettyValues":["0%","0%","0%","0%","0%","0%","0%","0%","0%","0%","0%","0%","0%","0%","0%","0%","0%","0%","0%","0%","0%","0%","0%","0%","0%","0%","0%","0%","0%","0%","0%","0%","0%","0%","0%","0%","100%","0%","0%","0%","0%","0%","0%","0%","0%","0%","0%","0%"],"values_N":[0,0,0,0,0,0,0,0,0,0,0,0,0,0,0,0,0,0,0,0,0,0,0,0,0,0,0,0,0,0,0,0,0,0,0,0,1,0,0,0,0,0,0,0,0,0,0,0],"buckets":[-1,-1,-1,-1,-1,-1,-1,-1,-1,-1,-1,-1,-1,-1,-1,-1,-1,-1,-1,-1,-1,-1,-1,-1,-1,-1,-1,-1,-1,-1,-1,-1,-1,-1,-1,-1,9,-1,-1,-1,-1,-1,-1,-1,-1,-1,-1,-1],"speciesCode":"cohmar1","name":"Common House-Martin"},{"taxon":{"displayName":"Black Sawwing","commonName":"Black Sawwing","sciName":"Psalidoprocne pristoptera","speciesCode":"blksaw1","category":"species","reportAsSpeciesCode":"blksaw1","reportAsCategory":"species","showSpeciesPageLink":true},"values":[0.0,0.0,0.0,0.0,0.0,0.0,0.0,0.0,0.0,0.0,0.0,0.0,0.0,0.0,0.0,0.0,0.0,0.0,0.0,0.0,0.0,0.0,0.0,0.0,0.0,0.0,0.0,0.0,0.0,0.0,0.0,0.0,0.0,0.0,0.0,0.0,1.0,0.0,0.0,0.0,0.0,0.0,0.0,0.0,0.0,0.0,0.0,0.0],"prettyValues":["0%","0%","0%","0%","0%","0%","0%","0%","0%","0%","0%","0%","0%","0%","0%","0%","0%","0%","0%","0%","0%","0%","0%","0%","0%","0%","0%","0%","0%","0%","0%","0%","0%","0%","0%","0%","100%","0%","0%","0%","0%","0%","0%","0%","0%","0%","0%","0%"],"values_N":[0,0,0,0,0,0,0,0,0,0,0,0,0,0,0,0,0,0,0,0,0,0,0,0,0,0,0,0,0,0,0,0,0,0,0,0,1,0,0,0,0,0,0,0,0,0,0,0],"buckets":[-1,-1,-1,-1,-1,-1,-1,-1,-1,-1,-1,-1,-1,-1,-1,-1,-1,-1,-1,-1,-1,-1,-1,-1,-1,-1,-1,-1,-1,-1,-1,-1,-1,-1,-1,-1,9,-1,-1,-1,-1,-1,-1,-1,-1,-1,-1,-1],"speciesCode":"blksaw1","name":"Black Sawwing"},{"taxon":{"displayName":"Gray-rumped Swallow","commonName":"Gray-rumped Swallow","sciName":"Pseudhirundo griseopyga","speciesCode":"gyrswa1","category":"species","reportAsSpeciesCode":"gyrswa1","reportAsCategory":"species","showSpeciesPageLink":true},"values":[0.0,0.0,0.0,0.0,0.0,0.0,0.0,0.0,0.0,0.0,0.0,0.0,0.0,0.0,0.0,0.0,0.0,0.0,0.0,0.0,0.0,0.0,0.0,0.0,0.0,0.0,0.0,0.0,0.0,0.0,0.0,0.0,0.0,0.0,0.0,0.0,1.0,0.0,0.0,0.0,0.0,0.0,0.0,0.0,0.0,0.0,0.0,0.0],"prettyValues":["0%","0%","0%","0%","0%","0%","0%","0%","0%","0%","0%","0%","0%","0%","0%","0%","0%","0%","0%","0%","0%","0%","0%","0%","0%","0%","0%","0%","0%","0%","0%","0%","0%","0%","0%","0%","100%","0%","0%","0%","0%","0%","0%","0%","0%","0%","0%","0%"],"values_N":[0,0,0,0,0,0,0,0,0,0,0,0,0,0,0,0,0,0,0,0,0,0,0,0,0,0,0,0,0,0,0,0,0,0,0,0,1,0,0,0,0,0,0,0,0,0,0,0],"buckets":[-1,-1,-1,-1,-1,-1,-1,-1,-1,-1,-1,-1,-1,-1,-1,-1,-1,-1,-1,-1,-1,-1,-1,-1,-1,-1,-1,-1,-1,-1,-1,-1,-1,-1,-1,-1,9,-1,-1,-1,-1,-1,-1,-1,-1,-1,-1,-1],"speciesCode":"gyrswa1","name":"Gray-rumped Swallow"},{"taxon":{"displayName":"Eastern Mountain Greenbul","commonName":"Eastern Mountain Greenbul","sciName":"Arizelocichla nigriceps","speciesCode":"easmog1","category":"species","reportAsSpeciesCode":"easmog1","reportAsCategory":"species","showSpeciesPageLink":true},"values":[0.0,0.0,0.0,0.0,0.0,0.0,0.0,0.0,0.0,0.0,0.0,0.0,0.0,0.0,0.0,0.0,0.0,0.0,0.0,0.0,0.0,0.0,0.0,0.0,0.0,0.0,0.0,0.0,0.0,0.0,0.0,0.0,0.0,0.0,0.0,0.0,1.0,0.0,0.0,0.0,0.0,0.0,0.0,0.0,0.0,0.0,0.0,0.0],"prettyValues":["0%","0%","0%","0%","0%","0%","0%","0%","0%","0%","0%","0%","0%","0%","0%","0%","0%","0%","0%","0%","0%","0%","0%","0%","0%","0%","0%","0%","0%","0%","0%","0%","0%","0%","0%","0%","100%","0%","0%","0%","0%","0%","0%","0%","0%","0%","0%","0%"],"values_N":[0,0,0,0,0,0,0,0,0,0,0,0,0,0,0,0,0,0,0,0,0,0,0,0,0,0,0,0,0,0,0,0,0,0,0,0,1,0,0,0,0,0,0,0,0,0,0,0],"buckets":[-1,-1,-1,-1,-1,-1,-1,-1,-1,-1,-1,-1,-1,-1,-1,-1,-1,-1,-1,-1,-1,-1,-1,-1,-1,-1,-1,-1,-1,-1,-1,-1,-1,-1,-1,-1,9,-1,-1,-1,-1,-1,-1,-1,-1,-1,-1,-1],"speciesCode":"easmog1","name":"Eastern Mountain Greenbul"},{"taxon":{"displayName":"Yellow-whiskered Greenbul","commonName":"Yellow-whiskered Greenbul","sciName":"Eurillas latirostris","speciesCode":"yewgre1","category":"species","reportAsSpeciesCode":"yewgre1","reportAsCategory":"species","showSpeciesPageLink":true},"values":[0.0,0.0,0.0,0.0,0.0,0.0,0.0,0.0,0.0,0.0,0.0,0.0,0.0,0.0,0.0,0.0,0.0,0.0,0.0,0.0,0.0,0.0,0.0,0.0,0.0,0.0,0.0,0.0,0.0,0.0,0.0,0.0,0.0,0.0,0.0,0.0,1.0,0.0,0.0,0.0,0.0,0.0,0.0,0.0,0.0,0.0,0.0,0.0],"prettyValues":["0%","0%","0%","0%","0%","0%","0%","0%","0%","0%","0%","0%","0%","0%","0%","0%","0%","0%","0%","0%","0%","0%","0%","0%","0%","0%","0%","0%","0%","0%","0%","0%","0%","0%","0%","0%","100%","0%","0%","0%","0%","0%","0%","0%","0%","0%","0%","0%"],"values_N":[0,0,0,0,0,0,0,0,0,0,0,0,0,0,0,0,0,0,0,0,0,0,0,0,0,0,0,0,0,0,0,0,0,0,0,0,1,0,0,0,0,0,0,0,0,0,0,0],"buckets":[-1,-1,-1,-1,-1,-1,-1,-1,-1,-1,-1,-1,-1,-1,-1,-1,-1,-1,-1,-1,-1,-1,-1,-1,-1,-1,-1,-1,-1,-1,-1,-1,-1,-1,-1,-1,9,-1,-1,-1,-1,-1,-1,-1,-1,-1,-1,-1],"speciesCode":"yewgre1","name":"Yellow-whiskered Greenbul"},{"taxon":{"displayName":"Common Bulbul","commonName":"Common Bulbul","sciName":"Pycnonotus barbatus","speciesCode":"combul2","category":"species","reportAsSpeciesCode":"combul2","reportAsCategory":"species","showSpeciesPageLink":true},"values":[0.0,0.0,0.0,0.0,0.0,0.0,0.0,0.0,0.0,0.0,0.0,0.0,0.0,0.0,0.0,0.0,0.0,0.0,0.0,0.0,0.0,0.0,0.0,0.0,0.0,0.0,0.0,0.0,0.0,0.0,0.0,0.0,0.0,0.0,0.0,0.0,1.0,0.0,0.0,0.0,0.0,0.0,0.0,0.0,0.0,0.0,0.0,0.0],"prettyValues":["0%","0%","0%","0%","0%","0%","0%","0%","0%","0%","0%","0%","0%","0%","0%","0%","0%","0%","0%","0%","0%","0%","0%","0%","0%","0%","0%","0%","0%","0%","0%","0%","0%","0%","0%","0%","100%","0%","0%","0%","0%","0%","0%","0%","0%","0%","0%","0%"],"values_N":[0,0,0,0,0,0,0,0,0,0,0,0,0,0,0,0,0,0,0,0,0,0,0,0,0,0,0,0,0,0,0,0,0,0,0,0,1,0,0,0,0,0,0,0,0,0,0,0],"buckets":[-1,-1,-1,-1,-1,-1,-1,-1,-1,-1,-1,-1,-1,-1,-1,-1,-1,-1,-1,-1,-1,-1,-1,-1,-1,-1,-1,-1,-1,-1,-1,-1,-1,-1,-1,-1,9,-1,-1,-1,-1,-1,-1,-1,-1,-1,-1,-1],"speciesCode":"combul2","name":"Common Bulbul"},{"taxon":{"displayName":"African Hill Babbler","commonName":"African Hill Babbler","sciName":"Sylvia abyssinica","speciesCode":"afhbab1","category":"species","reportAsSpeciesCode":"afhbab1","reportAsCategory":"species","showSpeciesPageLink":true},"values":[0.0,0.0,0.0,0.0,0.0,0.0,0.0,0.0,0.0,0.0,0.0,0.0,0.0,0.0,0.0,0.0,0.0,0.0,0.0,0.0,0.0,0.0,0.0,0.0,0.0,0.0,0.0,0.0,0.0,0.0,0.0,0.0,0.0,0.0,0.0,0.0,1.0,0.0,0.0,0.0,0.0,0.0,0.0,0.0,0.0,0.0,0.0,0.0],"prettyValues":["0%","0%","0%","0%","0%","0%","0%","0%","0%","0%","0%","0%","0%","0%","0%","0%","0%","0%","0%","0%","0%","0%","0%","0%","0%","0%","0%","0%","0%","0%","0%","0%","0%","0%","0%","0%","100%","0%","0%","0%","0%","0%","0%","0%","0%","0%","0%","0%"],"values_N":[0,0,0,0,0,0,0,0,0,0,0,0,0,0,0,0,0,0,0,0,0,0,0,0,0,0,0,0,0,0,0,0,0,0,0,0,1,0,0,0,0,0,0,0,0,0,0,0],"buckets":[-1,-1,-1,-1,-1,-1,-1,-1,-1,-1,-1,-1,-1,-1,-1,-1,-1,-1,-1,-1,-1,-1,-1,-1,-1,-1,-1,-1,-1,-1,-1,-1,-1,-1,-1,-1,9,-1,-1,-1,-1,-1,-1,-1,-1,-1,-1,-1],"speciesCode":"afhbab1","name":"African Hill Babbler"},{"taxon":{"displayName":"African Yellow White-eye","commonName":"African Yellow White-eye","sciName":"Zosterops senegalensis","speciesCode":"ayweye1","category":"species","reportAsSpeciesCode":"ayweye1","reportAsCategory":"species","showSpeciesPageLink":true},"values":[0.0,0.0,0.0,0.0,0.0,0.0,0.0,0.0,0.0,0.0,0.0,0.0,0.0,0.0,0.0,0.0,0.0,0.0,0.0,0.0,0.0,0.0,0.0,0.0,0.0,0.0,0.0,0.0,0.0,0.0,0.0,0.0,0.0,0.0,0.0,0.0,1.0,0.0,0.0,0.0,0.0,0.0,0.0,0.0,0.0,0.0,0.0,0.0],"prettyValues":["0%","0%","0%","0%","0%","0%","0%","0%","0%","0%","0%","0%","0%","0%","0%","0%","0%","0%","0%","0%","0%","0%","0%","0%","0%","0%","0%","0%","0%","0%","0%","0%","0%","0%","0%","0%","100%","0%","0%","0%","0%","0%","0%","0%","0%","0%","0%","0%"],"values_N":[0,0,0,0,0,0,0,0,0,0,0,0,0,0,0,0,0,0,0,0,0,0,0,0,0,0,0,0,0,0,0,0,0,0,0,0,1,0,0,0,0,0,0,0,0,0,0,0],"buckets":[-1,-1,-1,-1,-1,-1,-1,-1,-1,-1,-1,-1,-1,-1,-1,-1,-1,-1,-1,-1,-1,-1,-1,-1,-1,-1,-1,-1,-1,-1,-1,-1,-1,-1,-1,-1,9,-1,-1,-1,-1,-1,-1,-1,-1,-1,-1,-1],"speciesCode":"ayweye1","name":"African Yellow White-eye"},{"taxon":{"displayName":"African Spotted Creeper","commonName":"African Spotted Creeper","sciName":"Salpornis salvadori","speciesCode":"spocre2","category":"species","reportAsSpeciesCode":"spocre2","reportAsCategory":"species","showSpeciesPageLink":true},"values":[0.0,0.0,0.0,0.0,0.0,0.0,0.0,0.0,0.0,0.0,0.0,0.0,0.0,0.0,0.0,0.0,0.0,0.0,0.0,0.0,0.0,0.0,0.0,0.0,0.0,0.0,0.0,0.0,0.0,0.0,0.0,0.0,0.0,0.0,0.0,0.0,1.0,0.0,0.0,0.0,0.0,0.0,0.0,0.0,0.0,0.0,0.0,0.0],"prettyValues":["0%","0%","0%","0%","0%","0%","0%","0%","0%","0%","0%","0%","0%","0%","0%","0%","0%","0%","0%","0%","0%","0%","0%","0%","0%","0%","0%","0%","0%","0%","0%","0%","0%","0%","0%","0%","100%","0%","0%","0%","0%","0%","0%","0%","0%","0%","0%","0%"],"values_N":[0,0,0,0,0,0,0,0,0,0,0,0,0,0,0,0,0,0,0,0,0,0,0,0,0,0,0,0,0,0,0,0,0,0,0,0,1,0,0,0,0,0,0,0,0,0,0,0],"buckets":[-1,-1,-1,-1,-1,-1,-1,-1,-1,-1,-1,-1,-1,-1,-1,-1,-1,-1,-1,-1,-1,-1,-1,-1,-1,-1,-1,-1,-1,-1,-1,-1,-1,-1,-1,-1,9,-1,-1,-1,-1,-1,-1,-1,-1,-1,-1,-1],"speciesCode":"spocre2","name":"African Spotted Creeper"},{"taxon":{"displayName":"Violet-backed Starling","commonName":"Violet-backed Starling","sciName":"Cinnyricinclus leucogaster","speciesCode":"vibsta2","category":"species","reportAsSpeciesCode":"vibsta2","reportAsCategory":"species","showSpeciesPageLink":true},"values":[0.0,0.0,0.0,0.0,0.0,0.0,0.0,0.0,0.0,0.0,0.0,0.0,0.0,0.0,0.0,0.0,0.0,0.0,0.0,0.0,0.0,0.0,0.0,0.0,0.0,0.0,0.0,0.0,0.0,0.0,0.0,0.0,0.0,0.0,0.0,0.0,1.0,0.0,0.0,0.0,0.0,0.0,0.0,0.0,0.0,0.0,0.0,0.0],"prettyValues":["0%","0%","0%","0%","0%","0%","0%","0%","0%","0%","0%","0%","0%","0%","0%","0%","0%","0%","0%","0%","0%","0%","0%","0%","0%","0%","0%","0%","0%","0%","0%","0%","0%","0%","0%","0%","100%","0%","0%","0%","0%","0%","0%","0%","0%","0%","0%","0%"],"values_N":[0,0,0,0,0,0,0,0,0,0,0,0,0,0,0,0,0,0,0,0,0,0,0,0,0,0,0,0,0,0,0,0,0,0,0,0,1,0,0,0,0,0,0,0,0,0,0,0],"buckets":[-1,-1,-1,-1,-1,-1,-1,-1,-1,-1,-1,-1,-1,-1,-1,-1,-1,-1,-1,-1,-1,-1,-1,-1,-1,-1,-1,-1,-1,-1,-1,-1,-1,-1,-1,-1,9,-1,-1,-1,-1,-1,-1,-1,-1,-1,-1,-1],"speciesCode":"vibsta2","name":"Violet-backed Starling"},{"taxon":{"displayName":"Abyssinian Thrush","commonName":"Abyssinian Thrush","sciName":"Turdus abyssinicus","speciesCode":"abythr1","category":"species","reportAsSpeciesCode":"abythr1","reportAsCategory":"species","showSpeciesPageLink":true},"values":[0.0,0.0,0.0,0.0,0.0,0.0,0.0,0.0,0.0,0.0,0.0,0.0,0.0,0.0,0.0,0.0,0.0,0.0,0.0,0.0,0.0,0.0,0.0,0.0,0.0,0.0,0.0,0.0,0.0,0.0,0.0,0.0,0.0,0.0,0.0,0.0,1.0,0.0,0.0,0.0,0.0,0.0,0.0,0.0,0.0,0.0,0.0,0.0],"prettyValues":["0%","0%","0%","0%","0%","0%","0%","0%","0%","0%","0%","0%","0%","0%","0%","0%","0%","0%","0%","0%","0%","0%","0%","0%","0%","0%","0%","0%","0%","0%","0%","0%","0%","0%","0%","0%","100%","0%","0%","0%","0%","0%","0%","0%","0%","0%","0%","0%"],"values_N":[0,0,0,0,0,0,0,0,0,0,0,0,0,0,0,0,0,0,0,0,0,0,0,0,0,0,0,0,0,0,0,0,0,0,0,0,1,0,0,0,0,0,0,0,0,0,0,0],"buckets":[-1,-1,-1,-1,-1,-1,-1,-1,-1,-1,-1,-1,-1,-1,-1,-1,-1,-1,-1,-1,-1,-1,-1,-1,-1,-1,-1,-1,-1,-1,-1,-1,-1,-1,-1,-1,9,-1,-1,-1,-1,-1,-1,-1,-1,-1,-1,-1],"speciesCode":"abythr1","name":"Abyssinian Thrush"},{"taxon":{"displayName":"African Dusky Flycatcher","commonName":"African Dusky Flycatcher","sciName":"Muscicapa adusta","speciesCode":"afdfly1","category":"species","reportAsSpeciesCode":"afdfly1","reportAsCategory":"species","showSpeciesPageLink":true},"values":[0.0,0.0,0.0,0.0,0.0,0.0,0.0,0.0,0.0,0.0,0.0,0.0,0.0,0.0,0.0,0.0,0.0,0.0,0.0,0.0,0.0,0.0,0.0,0.0,0.0,0.0,0.0,0.0,0.0,0.0,0.0,0.0,0.0,0.0,0.0,0.0,1.0,0.0,0.0,0.0,0.0,0.0,0.0,0.0,0.0,0.0,0.0,0.0],"prettyValues":["0%","0%","0%","0%","0%","0%","0%","0%","0%","0%","0%","0%","0%","0%","0%","0%","0%","0%","0%","0%","0%","0%","0%","0%","0%","0%","0%","0%","0%","0%","0%","0%","0%","0%","0%","0%","100%","0%","0%","0%","0%","0%","0%","0%","0%","0%","0%","0%"],"values_N":[0,0,0,0,0,0,0,0,0,0,0,0,0,0,0,0,0,0,0,0,0,0,0,0,0,0,0,0,0,0,0,0,0,0,0,0,1,0,0,0,0,0,0,0,0,0,0,0],"buckets":[-1,-1,-1,-1,-1,-1,-1,-1,-1,-1,-1,-1,-1,-1,-1,-1,-1,-1,-1,-1,-1,-1,-1,-1,-1,-1,-1,-1,-1,-1,-1,-1,-1,-1,-1,-1,9,-1,-1,-1,-1,-1,-1,-1,-1,-1,-1,-1],"speciesCode":"afdfly1","name":"African Dusky Flycatcher"},{"taxon":{"displayName":"Pale Flycatcher","commonName":"Pale Flycatcher","sciName":"Agricola pallidus","speciesCode":"palfly2","category":"species","reportAsSpeciesCode":"palfly2","reportAsCategory":"species","showSpeciesPageLink":true},"values":[0.0,0.0,0.0,0.0,0.0,0.0,0.0,0.0,0.0,0.0,0.0,0.0,0.0,0.0,0.0,0.0,0.0,0.0,0.0,0.0,0.0,0.0,0.0,0.0,0.0,0.0,0.0,0.0,0.0,0.0,0.0,0.0,0.0,0.0,0.0,0.0,1.0,0.0,0.0,0.0,0.0,0.0,0.0,0.0,0.0,0.0,0.0,0.0],"prettyValues":["0%","0%","0%","0%","0%","0%","0%","0%","0%","0%","0%","0%","0%","0%","0%","0%","0%","0%","0%","0%","0%","0%","0%","0%","0%","0%","0%","0%","0%","0%","0%","0%","0%","0%","0%","0%","100%","0%","0%","0%","0%","0%","0%","0%","0%","0%","0%","0%"],"values_N":[0,0,0,0,0,0,0,0,0,0,0,0,0,0,0,0,0,0,0,0,0,0,0,0,0,0,0,0,0,0,0,0,0,0,0,0,1,0,0,0,0,0,0,0,0,0,0,0],"buckets":[-1,-1,-1,-1,-1,-1,-1,-1,-1,-1,-1,-1,-1,-1,-1,-1,-1,-1,-1,-1,-1,-1,-1,-1,-1,-1,-1,-1,-1,-1,-1,-1,-1,-1,-1,-1,9,-1,-1,-1,-1,-1,-1,-1,-1,-1,-1,-1],"speciesCode":"palfly2","name":"Pale Flycatcher"},{"taxon":{"displayName":"White-eyed Slaty-Flycatcher","commonName":"White-eyed Slaty-Flycatcher","sciName":"Melaenornis fischeri","speciesCode":"wheslf1","category":"species","reportAsSpeciesCode":"wheslf1","reportAsCategory":"species","showSpeciesPageLink":true},"values":[0.0,0.0,0.0,0.0,0.0,0.0,0.0,0.0,0.0,0.0,0.0,0.0,0.0,0.0,0.0,0.0,0.0,0.0,0.0,0.0,0.0,0.0,0.0,0.0,0.0,0.0,0.0,0.0,0.0,0.0,0.0,0.0,0.0,0.0,0.0,0.0,1.0,0.0,0.0,0.0,0.0,0.0,0.0,0.0,0.0,0.0,0.0,0.0],"prettyValues":["0%","0%","0%","0%","0%","0%","0%","0%","0%","0%","0%","0%","0%","0%","0%","0%","0%","0%","0%","0%","0%","0%","0%","0%","0%","0%","0%","0%","0%","0%","0%","0%","0%","0%","0%","0%","100%","0%","0%","0%","0%","0%","0%","0%","0%","0%","0%","0%"],"values_N":[0,0,0,0,0,0,0,0,0,0,0,0,0,0,0,0,0,0,0,0,0,0,0,0,0,0,0,0,0,0,0,0,0,0,0,0,1,0,0,0,0,0,0,0,0,0,0,0],"buckets":[-1,-1,-1,-1,-1,-1,-1,-1,-1,-1,-1,-1,-1,-1,-1,-1,-1,-1,-1,-1,-1,-1,-1,-1,-1,-1,-1,-1,-1,-1,-1,-1,-1,-1,-1,-1,9,-1,-1,-1,-1,-1,-1,-1,-1,-1,-1,-1],"speciesCode":"wheslf1","name":"White-eyed Slaty-Flycatcher"},{"taxon":{"displayName":"Cape Robin-Chat","commonName":"Cape Robin-Chat","sciName":"Cossypha caffra","speciesCode":"carcha1","category":"species","reportAsSpeciesCode":"carcha1","reportAsCategory":"species","showSpeciesPageLink":true},"values":[0.0,0.0,0.0,0.0,0.0,0.0,0.0,0.0,0.0,0.0,0.0,0.0,0.0,0.0,0.0,0.0,0.0,0.0,0.0,0.0,0.0,0.0,0.0,0.0,0.0,0.0,0.0,0.0,0.0,0.0,0.0,0.0,0.0,0.0,0.0,0.0,1.0,0.0,0.0,0.0,0.0,0.0,0.0,0.0,0.0,0.0,0.0,0.0],"prettyValues":["0%","0%","0%","0%","0%","0%","0%","0%","0%","0%","0%","0%","0%","0%","0%","0%","0%","0%","0%","0%","0%","0%","0%","0%","0%","0%","0%","0%","0%","0%","0%","0%","0%","0%","0%","0%","100%","0%","0%","0%","0%","0%","0%","0%","0%","0%","0%","0%"],"values_N":[0,0,0,0,0,0,0,0,0,0,0,0,0,0,0,0,0,0,0,0,0,0,0,0,0,0,0,0,0,0,0,0,0,0,0,0,1,0,0,0,0,0,0,0,0,0,0,0],"buckets":[-1,-1,-1,-1,-1,-1,-1,-1,-1,-1,-1,-1,-1,-1,-1,-1,-1,-1,-1,-1,-1,-1,-1,-1,-1,-1,-1,-1,-1,-1,-1,-1,-1,-1,-1,-1,9,-1,-1,-1,-1,-1,-1,-1,-1,-1,-1,-1],"speciesCode":"carcha1","name":"Cape Robin-Chat"},{"taxon":{"displayName":"White-starred Robin","commonName":"White-starred Robin","sciName":"Pogonocichla stellata","speciesCode":"whsrob1","category":"species","reportAsSpeciesCode":"whsrob1","reportAsCategory":"species","showSpeciesPageLink":true},"values":[0.0,0.0,0.0,0.0,0.0,0.0,0.0,0.0,0.0,0.0,0.0,0.0,0.0,0.0,0.0,0.0,0.0,0.0,0.0,0.0,0.0,0.0,0.0,0.0,0.0,0.0,0.0,0.0,0.0,0.0,0.0,0.0,0.0,0.0,0.0,0.0,1.0,0.0,0.0,0.0,0.0,0.0,0.0,0.0,0.0,0.0,0.0,0.0],"prettyValues":["0%","0%","0%","0%","0%","0%","0%","0%","0%","0%","0%","0%","0%","0%","0%","0%","0%","0%","0%","0%","0%","0%","0%","0%","0%","0%","0%","0%","0%","0%","0%","0%","0%","0%","0%","0%","100%","0%","0%","0%","0%","0%","0%","0%","0%","0%","0%","0%"],"values_N":[0,0,0,0,0,0,0,0,0,0,0,0,0,0,0,0,0,0,0,0,0,0,0,0,0,0,0,0,0,0,0,0,0,0,0,0,1,0,0,0,0,0,0,0,0,0,0,0],"buckets":[-1,-1,-1,-1,-1,-1,-1,-1,-1,-1,-1,-1,-1,-1,-1,-1,-1,-1,-1,-1,-1,-1,-1,-1,-1,-1,-1,-1,-1,-1,-1,-1,-1,-1,-1,-1,9,-1,-1,-1,-1,-1,-1,-1,-1,-1,-1,-1],"speciesCode":"whsrob1","name":"White-starred Robin"},{"taxon":{"displayName":"Little Rock-Thrush","commonName":"Little Rock-Thrush","sciName":"Monticola rufocinereus","speciesCode":"lirthr1","category":"species","reportAsSpeciesCode":"lirthr1","reportAsCategory":"species","showSpeciesPageLink":true},"values":[0.0,0.0,0.0,0.0,0.0,0.0,0.0,0.0,0.0,0.0,0.0,0.0,0.0,0.0,0.0,0.0,0.0,0.0,0.0,0.0,0.0,0.0,0.0,0.0,0.0,0.0,0.0,0.0,0.0,0.0,0.0,0.0,0.0,0.0,0.0,0.0,1.0,0.0,0.0,0.0,0.0,0.0,0.0,0.0,0.0,0.0,0.0,0.0],"prettyValues":["0%","0%","0%","0%","0%","0%","0%","0%","0%","0%","0%","0%","0%","0%","0%","0%","0%","0%","0%","0%","0%","0%","0%","0%","0%","0%","0%","0%","0%","0%","0%","0%","0%","0%","0%","0%","100%","0%","0%","0%","0%","0%","0%","0%","0%","0%","0%","0%"],"values_N":[0,0,0,0,0,0,0,0,0,0,0,0,0,0,0,0,0,0,0,0,0,0,0,0,0,0,0,0,0,0,0,0,0,0,0,0,1,0,0,0,0,0,0,0,0,0,0,0],"buckets":[-1,-1,-1,-1,-1,-1,-1,-1,-1,-1,-1,-1,-1,-1,-1,-1,-1,-1,-1,-1,-1,-1,-1,-1,-1,-1,-1,-1,-1,-1,-1,-1,-1,-1,-1,-1,9,-1,-1,-1,-1,-1,-1,-1,-1,-1,-1,-1],"speciesCode":"lirthr1","name":"Little Rock-Thrush"},{"taxon":{"displayName":"African Stonechat","commonName":"African Stonechat","sciName":"Saxicola torquatus","speciesCode":"afrsto1","category":"species","reportAsSpeciesCode":"afrsto1","reportAsCategory":"species","showSpeciesPageLink":true},"values":[0.0,0.0,0.0,0.0,0.0,0.0,0.0,0.0,0.0,0.0,0.0,0.0,0.0,0.0,0.0,0.0,0.0,0.0,0.0,0.0,0.0,0.0,0.0,0.0,0.0,0.0,0.0,0.0,0.0,0.0,0.0,0.0,0.0,0.0,0.0,0.0,1.0,0.0,0.0,0.0,0.0,0.0,0.0,0.0,0.0,0.0,0.0,0.0],"prettyValues":["0%","0%","0%","0%","0%","0%","0%","0%","0%","0%","0%","0%","0%","0%","0%","0%","0%","0%","0%","0%","0%","0%","0%","0%","0%","0%","0%","0%","0%","0%","0%","0%","0%","0%","0%","0%","100%","0%","0%","0%","0%","0%","0%","0%","0%","0%","0%","0%"],"values_N":[0,0,0,0,0,0,0,0,0,0,0,0,0,0,0,0,0,0,0,0,0,0,0,0,0,0,0,0,0,0,0,0,0,0,0,0,1,0,0,0,0,0,0,0,0,0,0,0],"buckets":[-1,-1,-1,-1,-1,-1,-1,-1,-1,-1,-1,-1,-1,-1,-1,-1,-1,-1,-1,-1,-1,-1,-1,-1,-1,-1,-1,-1,-1,-1,-1,-1,-1,-1,-1,-1,9,-1,-1,-1,-1,-1,-1,-1,-1,-1,-1,-1],"speciesCode":"afrsto1","name":"African Stonechat"},{"taxon":{"displayName":"Northern Anteater-Chat","commonName":"Northern Anteater-Chat","sciName":"Myrmecocichla aethiops","speciesCode":"noacha1","category":"species","reportAsSpeciesCode":"noacha1","reportAsCategory":"species","showSpeciesPageLink":true},"values":[0.0,0.0,0.0,0.0,0.0,0.0,0.0,0.0,0.0,0.0,0.0,0.0,0.0,0.0,0.0,0.0,0.0,0.0,0.0,0.0,0.0,0.0,0.0,0.0,0.0,0.0,0.0,0.0,0.0,0.0,0.0,0.0,0.0,0.0,0.0,0.0,1.0,0.0,0.0,0.0,0.0,0.0,0.0,0.0,0.0,0.0,0.0,0.0],"prettyValues":["0%","0%","0%","0%","0%","0%","0%","0%","0%","0%","0%","0%","0%","0%","0%","0%","0%","0%","0%","0%","0%","0%","0%","0%","0%","0%","0%","0%","0%","0%","0%","0%","0%","0%","0%","0%","100%","0%","0%","0%","0%","0%","0%","0%","0%","0%","0%","0%"],"values_N":[0,0,0,0,0,0,0,0,0,0,0,0,0,0,0,0,0,0,0,0,0,0,0,0,0,0,0,0,0,0,0,0,0,0,0,0,1,0,0,0,0,0,0,0,0,0,0,0],"buckets":[-1,-1,-1,-1,-1,-1,-1,-1,-1,-1,-1,-1,-1,-1,-1,-1,-1,-1,-1,-1,-1,-1,-1,-1,-1,-1,-1,-1,-1,-1,-1,-1,-1,-1,-1,-1,9,-1,-1,-1,-1,-1,-1,-1,-1,-1,-1,-1],"speciesCode":"noacha1","name":"Northern Anteater-Chat"},{"taxon":{"displayName":"Northern Wheatear","commonName":"Northern Wheatear","sciName":"Oenanthe oenanthe","speciesCode":"norwhe","category":"species","reportAsSpeciesCode":"norwhe","reportAsCategory":"species","showSpeciesPageLink":true},"values":[0.0,0.0,0.0,0.0,0.0,0.0,0.0,0.0,0.0,0.0,0.0,0.0,0.0,0.0,0.0,0.0,0.0,0.0,0.0,0.0,0.0,0.0,0.0,0.0,0.0,0.0,0.0,0.0,0.0,0.0,0.0,0.0,0.0,0.0,0.0,0.0,1.0,0.0,0.0,0.0,0.0,0.0,0.0,0.0,0.0,0.0,0.0,0.0],"prettyValues":["0%","0%","0%","0%","0%","0%","0%","0%","0%","0%","0%","0%","0%","0%","0%","0%","0%","0%","0%","0%","0%","0%","0%","0%","0%","0%","0%","0%","0%","0%","0%","0%","0%","0%","0%","0%","100%","0%","0%","0%","0%","0%","0%","0%","0%","0%","0%","0%"],"values_N":[0,0,0,0,0,0,0,0,0,0,0,0,0,0,0,0,0,0,0,0,0,0,0,0,0,0,0,0,0,0,0,0,0,0,0,0,1,0,0,0,0,0,0,0,0,0,0,0],"buckets":[-1,-1,-1,-1,-1,-1,-1,-1,-1,-1,-1,-1,-1,-1,-1,-1,-1,-1,-1,-1,-1,-1,-1,-1,-1,-1,-1,-1,-1,-1,-1,-1,-1,-1,-1,-1,9,-1,-1,-1,-1,-1,-1,-1,-1,-1,-1,-1],"speciesCode":"norwhe","name":"Northern Wheatear"},{"taxon":{"displayName":"Green-headed Sunbird","commonName":"Green-headed Sunbird","sciName":"Cyanomitra verticalis","speciesCode":"gnhsun1","category":"species","reportAsSpeciesCode":"gnhsun1","reportAsCategory":"species","showSpeciesPageLink":true},"values":[0.0,0.0,0.0,0.0,0.0,0.0,0.0,0.0,0.0,0.0,0.0,0.0,0.0,0.0,0.0,0.0,0.0,0.0,0.0,0.0,0.0,0.0,0.0,0.0,0.0,0.0,0.0,0.0,0.0,0.0,0.0,0.0,0.0,0.0,0.0,0.0,1.0,0.0,0.0,0.0,0.0,0.0,0.0,0.0,0.0,0.0,0.0,0.0],"prettyValues":["0%","0%","0%","0%","0%","0%","0%","0%","0%","0%","0%","0%","0%","0%","0%","0%","0%","0%","0%","0%","0%","0%","0%","0%","0%","0%","0%","0%","0%","0%","0%","0%","0%","0%","0%","0%","100%","0%","0%","0%","0%","0%","0%","0%","0%","0%","0%","0%"],"values_N":[0,0,0,0,0,0,0,0,0,0,0,0,0,0,0,0,0,0,0,0,0,0,0,0,0,0,0,0,0,0,0,0,0,0,0,0,1,0,0,0,0,0,0,0,0,0,0,0],"buckets":[-1,-1,-1,-1,-1,-1,-1,-1,-1,-1,-1,-1,-1,-1,-1,-1,-1,-1,-1,-1,-1,-1,-1,-1,-1,-1,-1,-1,-1,-1,-1,-1,-1,-1,-1,-1,9,-1,-1,-1,-1,-1,-1,-1,-1,-1,-1,-1],"speciesCode":"gnhsun1","name":"Green-headed Sunbird"},{"taxon":{"displayName":"Tacazze Sunbird","commonName":"Tacazze Sunbird","sciName":"Nectarinia tacazze","speciesCode":"tacsun1","category":"species","reportAsSpeciesCode":"tacsun1","reportAsCategory":"species","showSpeciesPageLink":true},"values":[0.0,0.0,0.0,0.0,0.0,0.0,0.0,0.0,0.0,0.0,0.0,0.0,0.0,0.0,0.0,0.0,0.0,0.0,0.0,0.0,0.0,0.0,0.0,0.0,0.0,0.0,0.0,0.0,0.0,0.0,0.0,0.0,0.0,0.0,0.0,0.0,1.0,0.0,0.0,0.0,0.0,0.0,0.0,0.0,0.0,0.0,0.0,0.0],"prettyValues":["0%","0%","0%","0%","0%","0%","0%","0%","0%","0%","0%","0%","0%","0%","0%","0%","0%","0%","0%","0%","0%","0%","0%","0%","0%","0%","0%","0%","0%","0%","0%","0%","0%","0%","0%","0%","100%","0%","0%","0%","0%","0%","0%","0%","0%","0%","0%","0%"],"values_N":[0,0,0,0,0,0,0,0,0,0,0,0,0,0,0,0,0,0,0,0,0,0,0,0,0,0,0,0,0,0,0,0,0,0,0,0,1,0,0,0,0,0,0,0,0,0,0,0],"buckets":[-1,-1,-1,-1,-1,-1,-1,-1,-1,-1,-1,-1,-1,-1,-1,-1,-1,-1,-1,-1,-1,-1,-1,-1,-1,-1,-1,-1,-1,-1,-1,-1,-1,-1,-1,-1,9,-1,-1,-1,-1,-1,-1,-1,-1,-1,-1,-1],"speciesCode":"tacsun1","name":"Tacazze Sunbird"},{"taxon":{"displayName":"Golden-winged Sunbird","commonName":"Golden-winged Sunbird","sciName":"Drepanorhynchus reichenowi","speciesCode":"gowsun2","category":"species","reportAsSpeciesCode":"gowsun2","reportAsCategory":"species","showSpeciesPageLink":true},"values":[0.0,0.0,0.0,0.0,0.0,0.0,0.0,0.0,0.0,0.0,0.0,0.0,0.0,0.0,0.0,0.0,0.0,0.0,0.0,0.0,0.0,0.0,0.0,0.0,0.0,0.0,0.0,0.0,0.0,0.0,0.0,0.0,0.0,0.0,0.0,0.0,1.0,0.0,0.0,0.0,0.0,0.0,0.0,0.0,0.0,0.0,0.0,0.0],"prettyValues":["0%","0%","0%","0%","0%","0%","0%","0%","0%","0%","0%","0%","0%","0%","0%","0%","0%","0%","0%","0%","0%","0%","0%","0%","0%","0%","0%","0%","0%","0%","0%","0%","0%","0%","0%","0%","100%","0%","0%","0%","0%","0%","0%","0%","0%","0%","0%","0%"],"values_N":[0,0,0,0,0,0,0,0,0,0,0,0,0,0,0,0,0,0,0,0,0,0,0,0,0,0,0,0,0,0,0,0,0,0,0,0,1,0,0,0,0,0,0,0,0,0,0,0],"buckets":[-1,-1,-1,-1,-1,-1,-1,-1,-1,-1,-1,-1,-1,-1,-1,-1,-1,-1,-1,-1,-1,-1,-1,-1,-1,-1,-1,-1,-1,-1,-1,-1,-1,-1,-1,-1,9,-1,-1,-1,-1,-1,-1,-1,-1,-1,-1,-1],"speciesCode":"gowsun2","name":"Golden-winged Sunbird"},{"taxon":{"displayName":"Northern Double-collared Sunbird","commonName":"Northern Double-collared Sunbird","sciName":"Cinnyris reichenowi","speciesCode":"ndcsun2","category":"species","reportAsSpeciesCode":"ndcsun2","reportAsCategory":"species","showSpeciesPageLink":true},"values":[0.0,0.0,0.0,0.0,0.0,0.0,0.0,0.0,0.0,0.0,0.0,0.0,0.0,0.0,0.0,0.0,0.0,0.0,0.0,0.0,0.0,0.0,0.0,0.0,0.0,0.0,0.0,0.0,0.0,0.0,0.0,0.0,0.0,0.0,0.0,0.0,1.0,0.0,0.0,0.0,0.0,0.0,0.0,0.0,0.0,0.0,0.0,0.0],"prettyValues":["0%","0%","0%","0%","0%","0%","0%","0%","0%","0%","0%","0%","0%","0%","0%","0%","0%","0%","0%","0%","0%","0%","0%","0%","0%","0%","0%","0%","0%","0%","0%","0%","0%","0%","0%","0%","100%","0%","0%","0%","0%","0%","0%","0%","0%","0%","0%","0%"],"values_N":[0,0,0,0,0,0,0,0,0,0,0,0,0,0,0,0,0,0,0,0,0,0,0,0,0,0,0,0,0,0,0,0,0,0,0,0,1,0,0,0,0,0,0,0,0,0,0,0],"buckets":[-1,-1,-1,-1,-1,-1,-1,-1,-1,-1,-1,-1,-1,-1,-1,-1,-1,-1,-1,-1,-1,-1,-1,-1,-1,-1,-1,-1,-1,-1,-1,-1,-1,-1,-1,-1,9,-1,-1,-1,-1,-1,-1,-1,-1,-1,-1,-1],"speciesCode":"ndcsun2","name":"Northern Double-collared Sunbird"},{"taxon":{"displayName":"Variable Sunbird","commonName":"Variable Sunbird","sciName":"Cinnyris venustus","speciesCode":"varsun2","category":"species","reportAsSpeciesCode":"varsun2","reportAsCategory":"species","showSpeciesPageLink":true},"values":[0.0,0.0,0.0,0.0,0.0,0.0,0.0,0.0,0.0,0.0,0.0,0.0,0.0,0.0,0.0,0.0,0.0,0.0,0.0,0.0,0.0,0.0,0.0,0.0,0.0,0.0,0.0,0.0,0.0,0.0,0.0,0.0,0.0,0.0,0.0,0.0,1.0,0.0,0.0,0.0,0.0,0.0,0.0,0.0,0.0,0.0,0.0,0.0],"prettyValues":["0%","0%","0%","0%","0%","0%","0%","0%","0%","0%","0%","0%","0%","0%","0%","0%","0%","0%","0%","0%","0%","0%","0%","0%","0%","0%","0%","0%","0%","0%","0%","0%","0%","0%","0%","0%","100%","0%","0%","0%","0%","0%","0%","0%","0%","0%","0%","0%"],"values_N":[0,0,0,0,0,0,0,0,0,0,0,0,0,0,0,0,0,0,0,0,0,0,0,0,0,0,0,0,0,0,0,0,0,0,0,0,1,0,0,0,0,0,0,0,0,0,0,0],"buckets":[-1,-1,-1,-1,-1,-1,-1,-1,-1,-1,-1,-1,-1,-1,-1,-1,-1,-1,-1,-1,-1,-1,-1,-1,-1,-1,-1,-1,-1,-1,-1,-1,-1,-1,-1,-1,9,-1,-1,-1,-1,-1,-1,-1,-1,-1,-1,-1],"speciesCode":"varsun2","name":"Variable Sunbird"},{"taxon":{"displayName":"Baglafecht Weaver","commonName":"Baglafecht Weaver","sciName":"Ploceus baglafecht","speciesCode":"bagwea1","category":"species","reportAsSpeciesCode":"bagwea1","reportAsCategory":"species","showSpeciesPageLink":true},"values":[0.0,0.0,0.0,0.0,0.0,0.0,0.0,0.0,0.0,0.0,0.0,0.0,0.0,0.0,0.0,0.0,0.0,0.0,0.0,0.0,0.0,0.0,0.0,0.0,0.0,0.0,0.0,0.0,0.0,0.0,0.0,0.0,0.0,0.0,0.0,0.0,1.0,0.0,0.0,0.0,0.0,0.0,0.0,0.0,0.0,0.0,0.0,0.0],"prettyValues":["0%","0%","0%","0%","0%","0%","0%","0%","0%","0%","0%","0%","0%","0%","0%","0%","0%","0%","0%","0%","0%","0%","0%","0%","0%","0%","0%","0%","0%","0%","0%","0%","0%","0%","0%","0%","100%","0%","0%","0%","0%","0%","0%","0%","0%","0%","0%","0%"],"values_N":[0,0,0,0,0,0,0,0,0,0,0,0,0,0,0,0,0,0,0,0,0,0,0,0,0,0,0,0,0,0,0,0,0,0,0,0,1,0,0,0,0,0,0,0,0,0,0,0],"buckets":[-1,-1,-1,-1,-1,-1,-1,-1,-1,-1,-1,-1,-1,-1,-1,-1,-1,-1,-1,-1,-1,-1,-1,-1,-1,-1,-1,-1,-1,-1,-1,-1,-1,-1,-1,-1,9,-1,-1,-1,-1,-1,-1,-1,-1,-1,-1,-1],"speciesCode":"bagwea1","name":"Baglafecht Weaver"},{"taxon":{"displayName":"Black-billed Weaver","commonName":"Black-billed Weaver","sciName":"Ploceus melanogaster","speciesCode":"blbwea1","category":"species","reportAsSpeciesCode":"blbwea1","reportAsCategory":"species","showSpeciesPageLink":true},"values":[0.0,0.0,0.0,0.0,0.0,0.0,0.0,0.0,0.0,0.0,0.0,0.0,0.0,0.0,0.0,0.0,0.0,0.0,0.0,0.0,0.0,0.0,0.0,0.0,0.0,0.0,0.0,0.0,0.0,0.0,0.0,0.0,0.0,0.0,0.0,0.0,1.0,0.0,0.0,0.0,0.0,0.0,0.0,0.0,0.0,0.0,0.0,0.0],"prettyValues":["0%","0%","0%","0%","0%","0%","0%","0%","0%","0%","0%","0%","0%","0%","0%","0%","0%","0%","0%","0%","0%","0%","0%","0%","0%","0%","0%","0%","0%","0%","0%","0%","0%","0%","0%","0%","100%","0%","0%","0%","0%","0%","0%","0%","0%","0%","0%","0%"],"values_N":[0,0,0,0,0,0,0,0,0,0,0,0,0,0,0,0,0,0,0,0,0,0,0,0,0,0,0,0,0,0,0,0,0,0,0,0,1,0,0,0,0,0,0,0,0,0,0,0],"buckets":[-1,-1,-1,-1,-1,-1,-1,-1,-1,-1,-1,-1,-1,-1,-1,-1,-1,-1,-1,-1,-1,-1,-1,-1,-1,-1,-1,-1,-1,-1,-1,-1,-1,-1,-1,-1,9,-1,-1,-1,-1,-1,-1,-1,-1,-1,-1,-1],"speciesCode":"blbwea1","name":"Black-billed Weaver"},{"taxon":{"displayName":"Yellow-bellied Waxbill","commonName":"Yellow-bellied Waxbill","sciName":"Coccopygia quartinia","speciesCode":"yebwax2","category":"species","reportAsSpeciesCode":"yebwax2","reportAsCategory":"species","showSpeciesPageLink":true},"values":[0.0,0.0,0.0,0.0,0.0,0.0,0.0,0.0,0.0,0.0,0.0,0.0,0.0,0.0,0.0,0.0,0.0,0.0,0.0,0.0,0.0,0.0,0.0,0.0,0.0,0.0,0.0,0.0,0.0,0.0,0.0,0.0,0.0,0.0,0.0,0.0,1.0,0.0,0.0,0.0,0.0,0.0,0.0,0.0,0.0,0.0,0.0,0.0],"prettyValues":["0%","0%","0%","0%","0%","0%","0%","0%","0%","0%","0%","0%","0%","0%","0%","0%","0%","0%","0%","0%","0%","0%","0%","0%","0%","0%","0%","0%","0%","0%","0%","0%","0%","0%","0%","0%","100%","0%","0%","0%","0%","0%","0%","0%","0%","0%","0%","0%"],"values_N":[0,0,0,0,0,0,0,0,0,0,0,0,0,0,0,0,0,0,0,0,0,0,0,0,0,0,0,0,0,0,0,0,0,0,0,0,1,0,0,0,0,0,0,0,0,0,0,0],"buckets":[-1,-1,-1,-1,-1,-1,-1,-1,-1,-1,-1,-1,-1,-1,-1,-1,-1,-1,-1,-1,-1,-1,-1,-1,-1,-1,-1,-1,-1,-1,-1,-1,-1,-1,-1,-1,9,-1,-1,-1,-1,-1,-1,-1,-1,-1,-1,-1],"speciesCode":"yebwax2","name":"Yellow-bellied Waxbill"},{"taxon":{"displayName":"Black-crowned Waxbill","commonName":"Black-crowned Waxbill","sciName":"Estrilda nonnula","speciesCode":"blcwax2","category":"species","reportAsSpeciesCode":"blcwax2","reportAsCategory":"species","showSpeciesPageLink":true},"values":[0.0,0.0,0.0,0.0,0.0,0.0,0.0,0.0,0.0,0.0,0.0,0.0,0.0,0.0,0.0,0.0,0.0,0.0,0.0,0.0,0.0,0.0,0.0,0.0,0.0,0.0,0.0,0.0,0.0,0.0,0.0,0.0,0.0,0.0,0.0,0.0,1.0,0.0,0.0,0.0,0.0,0.0,0.0,0.0,0.0,0.0,0.0,0.0],"prettyValues":["0%","0%","0%","0%","0%","0%","0%","0%","0%","0%","0%","0%","0%","0%","0%","0%","0%","0%","0%","0%","0%","0%","0%","0%","0%","0%","0%","0%","0%","0%","0%","0%","0%","0%","0%","0%","100%","0%","0%","0%","0%","0%","0%","0%","0%","0%","0%","0%"],"values_N":[0,0,0,0,0,0,0,0,0,0,0,0,0,0,0,0,0,0,0,0,0,0,0,0,0,0,0,0,0,0,0,0,0,0,0,0,1,0,0,0,0,0,0,0,0,0,0,0],"buckets":[-1,-1,-1,-1,-1,-1,-1,-1,-1,-1,-1,-1,-1,-1,-1,-1,-1,-1,-1,-1,-1,-1,-1,-1,-1,-1,-1,-1,-1,-1,-1,-1,-1,-1,-1,-1,9,-1,-1,-1,-1,-1,-1,-1,-1,-1,-1,-1],"speciesCode":"blcwax2","name":"Black-crowned Waxbill"},{"taxon":{"displayName":"Red-cheeked Cordonbleu","commonName":"Red-cheeked Cordonbleu","sciName":"Uraeginthus bengalus","speciesCode":"reccor","category":"species","reportAsSpeciesCode":"reccor","reportAsCategory":"species","showSpeciesPageLink":true},"values":[0.0,0.0,0.0,0.0,0.0,0.0,0.0,0.0,0.0,0.0,0.0,0.0,0.0,0.0,0.0,0.0,0.0,0.0,0.0,0.0,0.0,0.0,0.0,0.0,0.0,0.0,0.0,0.0,0.0,0.0,0.0,0.0,0.0,0.0,0.0,0.0,1.0,0.0,0.0,0.0,0.0,0.0,0.0,0.0,0.0,0.0,0.0,0.0],"prettyValues":["0%","0%","0%","0%","0%","0%","0%","0%","0%","0%","0%","0%","0%","0%","0%","0%","0%","0%","0%","0%","0%","0%","0%","0%","0%","0%","0%","0%","0%","0%","0%","0%","0%","0%","0%","0%","100%","0%","0%","0%","0%","0%","0%","0%","0%","0%","0%","0%"],"values_N":[0,0,0,0,0,0,0,0,0,0,0,0,0,0,0,0,0,0,0,0,0,0,0,0,0,0,0,0,0,0,0,0,0,0,0,0,1,0,0,0,0,0,0,0,0,0,0,0],"buckets":[-1,-1,-1,-1,-1,-1,-1,-1,-1,-1,-1,-1,-1,-1,-1,-1,-1,-1,-1,-1,-1,-1,-1,-1,-1,-1,-1,-1,-1,-1,-1,-1,-1,-1,-1,-1,9,-1,-1,-1,-1,-1,-1,-1,-1,-1,-1,-1],"speciesCode":"reccor","name":"Red-cheeked Cordonbleu"},{"taxon":{"displayName":"African Firefinch","commonName":"African Firefinch","sciName":"Lagonosticta rubricata","speciesCode":"afffin","category":"species","reportAsSpeciesCode":"afffin","reportAsCategory":"species","showSpeciesPageLink":true},"values":[0.0,0.0,0.0,0.0,0.0,0.0,0.0,0.0,0.0,0.0,0.0,0.0,0.0,0.0,0.0,0.0,0.0,0.0,0.0,0.0,0.0,0.0,0.0,0.0,0.0,0.0,0.0,0.0,0.0,0.0,0.0,0.0,0.0,0.0,0.0,0.0,1.0,0.0,0.0,0.0,0.0,0.0,0.0,0.0,0.0,0.0,0.0,0.0],"prettyValues":["0%","0%","0%","0%","0%","0%","0%","0%","0%","0%","0%","0%","0%","0%","0%","0%","0%","0%","0%","0%","0%","0%","0%","0%","0%","0%","0%","0%","0%","0%","0%","0%","0%","0%","0%","0%","100%","0%","0%","0%","0%","0%","0%","0%","0%","0%","0%","0%"],"values_N":[0,0,0,0,0,0,0,0,0,0,0,0,0,0,0,0,0,0,0,0,0,0,0,0,0,0,0,0,0,0,0,0,0,0,0,0,1,0,0,0,0,0,0,0,0,0,0,0],"buckets":[-1,-1,-1,-1,-1,-1,-1,-1,-1,-1,-1,-1,-1,-1,-1,-1,-1,-1,-1,-1,-1,-1,-1,-1,-1,-1,-1,-1,-1,-1,-1,-1,-1,-1,-1,-1,9,-1,-1,-1,-1,-1,-1,-1,-1,-1,-1,-1],"speciesCode":"afffin","name":"African Firefinch"},{"taxon":{"displayName":"Pin-tailed Whydah","commonName":"Pin-tailed Whydah","sciName":"Vidua macroura","speciesCode":"pitwhy","category":"species","reportAsSpeciesCode":"pitwhy","reportAsCategory":"species","showSpeciesPageLink":true},"values":[0.0,0.0,0.0,0.0,0.0,0.0,0.0,0.0,0.0,0.0,0.0,0.0,0.0,0.0,0.0,0.0,0.0,0.0,0.0,0.0,0.0,0.0,0.0,0.0,0.0,0.0,0.0,0.0,0.0,0.0,0.0,0.0,0.0,0.0,0.0,0.0,1.0,0.0,0.0,0.0,0.0,0.0,0.0,0.0,0.0,0.0,0.0,0.0],"prettyValues":["0%","0%","0%","0%","0%","0%","0%","0%","0%","0%","0%","0%","0%","0%","0%","0%","0%","0%","0%","0%","0%","0%","0%","0%","0%","0%","0%","0%","0%","0%","0%","0%","0%","0%","0%","0%","100%","0%","0%","0%","0%","0%","0%","0%","0%","0%","0%","0%"],"values_N":[0,0,0,0,0,0,0,0,0,0,0,0,0,0,0,0,0,0,0,0,0,0,0,0,0,0,0,0,0,0,0,0,0,0,0,0,1,0,0,0,0,0,0,0,0,0,0,0],"buckets":[-1,-1,-1,-1,-1,-1,-1,-1,-1,-1,-1,-1,-1,-1,-1,-1,-1,-1,-1,-1,-1,-1,-1,-1,-1,-1,-1,-1,-1,-1,-1,-1,-1,-1,-1,-1,9,-1,-1,-1,-1,-1,-1,-1,-1,-1,-1,-1],"speciesCode":"pitwhy","name":"Pin-tailed Whydah"},{"taxon":{"displayName":"Kenya Rufous Sparrow","commonName":"Kenya Rufous Sparrow","sciName":"Passer rufocinctus","speciesCode":"kerspa2","category":"species","reportAsSpeciesCode":"kerspa2","reportAsCategory":"species","showSpeciesPageLink":true},"values":[0.0,0.0,0.0,0.0,0.0,0.0,0.0,0.0,0.0,0.0,0.0,0.0,0.0,0.0,0.0,0.0,0.0,0.0,0.0,0.0,0.0,0.0,0.0,0.0,0.0,0.0,0.0,0.0,0.0,0.0,0.0,0.0,0.0,0.0,0.0,0.0,1.0,0.0,0.0,0.0,0.0,0.0,0.0,0.0,0.0,0.0,0.0,0.0],"prettyValues":["0%","0%","0%","0%","0%","0%","0%","0%","0%","0%","0%","0%","0%","0%","0%","0%","0%","0%","0%","0%","0%","0%","0%","0%","0%","0%","0%","0%","0%","0%","0%","0%","0%","0%","0%","0%","100%","0%","0%","0%","0%","0%","0%","0%","0%","0%","0%","0%"],"values_N":[0,0,0,0,0,0,0,0,0,0,0,0,0,0,0,0,0,0,0,0,0,0,0,0,0,0,0,0,0,0,0,0,0,0,0,0,1,0,0,0,0,0,0,0,0,0,0,0],"buckets":[-1,-1,-1,-1,-1,-1,-1,-1,-1,-1,-1,-1,-1,-1,-1,-1,-1,-1,-1,-1,-1,-1,-1,-1,-1,-1,-1,-1,-1,-1,-1,-1,-1,-1,-1,-1,9,-1,-1,-1,-1,-1,-1,-1,-1,-1,-1,-1],"speciesCode":"kerspa2","name":"Kenya Rufous Sparrow"},{"taxon":{"displayName":"Northern Gray-headed Sparrow","commonName":"Northern Gray-headed Sparrow","sciName":"Passer griseus","speciesCode":"gyhspa1","category":"species","reportAsSpeciesCode":"gyhspa1","reportAsCategory":"species","showSpeciesPageLink":true},"values":[0.0,0.0,0.0,0.0,0.0,0.0,0.0,0.0,0.0,0.0,0.0,0.0,0.0,0.0,0.0,0.0,0.0,0.0,0.0,0.0,0.0,0.0,0.0,0.0,0.0,0.0,0.0,0.0,0.0,0.0,0.0,0.0,0.0,0.0,0.0,0.0,1.0,0.0,0.0,0.0,0.0,0.0,0.0,0.0,0.0,0.0,0.0,0.0],"prettyValues":["0%","0%","0%","0%","0%","0%","0%","0%","0%","0%","0%","0%","0%","0%","0%","0%","0%","0%","0%","0%","0%","0%","0%","0%","0%","0%","0%","0%","0%","0%","0%","0%","0%","0%","0%","0%","100%","0%","0%","0%","0%","0%","0%","0%","0%","0%","0%","0%"],"values_N":[0,0,0,0,0,0,0,0,0,0,0,0,0,0,0,0,0,0,0,0,0,0,0,0,0,0,0,0,0,0,0,0,0,0,0,0,1,0,0,0,0,0,0,0,0,0,0,0],"buckets":[-1,-1,-1,-1,-1,-1,-1,-1,-1,-1,-1,-1,-1,-1,-1,-1,-1,-1,-1,-1,-1,-1,-1,-1,-1,-1,-1,-1,-1,-1,-1,-1,-1,-1,-1,-1,9,-1,-1,-1,-1,-1,-1,-1,-1,-1,-1,-1],"speciesCode":"gyhspa1","name":"Northern Gray-headed Sparrow"},{"taxon":{"displayName":"African Pied Wagtail","commonName":"African Pied Wagtail","sciName":"Motacilla aguimp","speciesCode":"afpwag1","category":"species","reportAsSpeciesCode":"afpwag1","reportAsCategory":"species","showSpeciesPageLink":true},"values":[0.0,0.0,0.0,0.0,0.0,0.0,0.0,0.0,0.0,0.0,0.0,0.0,0.0,0.0,0.0,0.0,0.0,0.0,0.0,0.0,0.0,0.0,0.0,0.0,0.0,0.0,0.0,0.0,0.0,0.0,0.0,0.0,0.0,0.0,0.0,0.0,1.0,0.0,0.0,0.0,0.0,0.0,0.0,0.0,0.0,0.0,0.0,0.0],"prettyValues":["0%","0%","0%","0%","0%","0%","0%","0%","0%","0%","0%","0%","0%","0%","0%","0%","0%","0%","0%","0%","0%","0%","0%","0%","0%","0%","0%","0%","0%","0%","0%","0%","0%","0%","0%","0%","100%","0%","0%","0%","0%","0%","0%","0%","0%","0%","0%","0%"],"values_N":[0,0,0,0,0,0,0,0,0,0,0,0,0,0,0,0,0,0,0,0,0,0,0,0,0,0,0,0,0,0,0,0,0,0,0,0,1,0,0,0,0,0,0,0,0,0,0,0],"buckets":[-1,-1,-1,-1,-1,-1,-1,-1,-1,-1,-1,-1,-1,-1,-1,-1,-1,-1,-1,-1,-1,-1,-1,-1,-1,-1,-1,-1,-1,-1,-1,-1,-1,-1,-1,-1,9,-1,-1,-1,-1,-1,-1,-1,-1,-1,-1,-1],"speciesCode":"afpwag1","name":"African Pied Wagtail"},{"taxon":{"displayName":"African Pipit","commonName":"African Pipit","sciName":"Anthus cinnamomeus","speciesCode":"afrpip1","category":"species","reportAsSpeciesCode":"afrpip1","reportAsCategory":"species","showSpeciesPageLink":true},"values":[0.0,0.0,0.0,0.0,0.0,0.0,0.0,0.0,0.0,0.0,0.0,0.0,0.0,0.0,0.0,0.0,0.0,0.0,0.0,0.0,0.0,0.0,0.0,0.0,0.0,0.0,0.0,0.0,0.0,0.0,0.0,0.0,0.0,0.0,0.0,0.0,1.0,0.0,0.0,0.0,0.0,0.0,0.0,0.0,0.0,0.0,0.0,0.0],"prettyValues":["0%","0%","0%","0%","0%","0%","0%","0%","0%","0%","0%","0%","0%","0%","0%","0%","0%","0%","0%","0%","0%","0%","0%","0%","0%","0%","0%","0%","0%","0%","0%","0%","0%","0%","0%","0%","100%","0%","0%","0%","0%","0%","0%","0%","0%","0%","0%","0%"],"values_N":[0,0,0,0,0,0,0,0,0,0,0,0,0,0,0,0,0,0,0,0,0,0,0,0,0,0,0,0,0,0,0,0,0,0,0,0,1,0,0,0,0,0,0,0,0,0,0,0],"buckets":[-1,-1,-1,-1,-1,-1,-1,-1,-1,-1,-1,-1,-1,-1,-1,-1,-1,-1,-1,-1,-1,-1,-1,-1,-1,-1,-1,-1,-1,-1,-1,-1,-1,-1,-1,-1,9,-1,-1,-1,-1,-1,-1,-1,-1,-1,-1,-1],"speciesCode":"afrpip1","name":"African Pipit"},{"taxon":{"displayName":"Streaky Seedeater","commonName":"Streaky Seedeater","sciName":"Crithagra striolata","speciesCode":"strsee1","category":"species","reportAsSpeciesCode":"strsee1","reportAsCategory":"species","showSpeciesPageLink":true},"values":[0.0,0.0,0.0,0.0,0.0,0.0,0.0,0.0,0.0,0.0,0.0,0.0,0.0,0.0,0.0,0.0,0.0,0.0,0.0,0.0,0.0,0.0,0.0,0.0,0.0,0.0,0.0,0.0,0.0,0.0,0.0,0.0,0.0,0.0,0.0,0.0,1.0,0.0,0.0,0.0,0.0,0.0,0.0,0.0,0.0,0.0,0.0,0.0],"prettyValues":["0%","0%","0%","0%","0%","0%","0%","0%","0%","0%","0%","0%","0%","0%","0%","0%","0%","0%","0%","0%","0%","0%","0%","0%","0%","0%","0%","0%","0%","0%","0%","0%","0%","0%","0%","0%","100%","0%","0%","0%","0%","0%","0%","0%","0%","0%","0%","0%"],"values_N":[0,0,0,0,0,0,0,0,0,0,0,0,0,0,0,0,0,0,0,0,0,0,0,0,0,0,0,0,0,0,0,0,0,0,0,0,1,0,0,0,0,0,0,0,0,0,0,0],"buckets":[-1,-1,-1,-1,-1,-1,-1,-1,-1,-1,-1,-1,-1,-1,-1,-1,-1,-1,-1,-1,-1,-1,-1,-1,-1,-1,-1,-1,-1,-1,-1,-1,-1,-1,-1,-1,9,-1,-1,-1,-1,-1,-1,-1,-1,-1,-1,-1],"speciesCode":"strsee1","name":"Streaky Seedeater"},{"taxon":{"displayName":"Thick-billed Seedeater","commonName":"Thick-billed Seedeater","sciName":"Crithagra burtoni","speciesCode":"thbsee1","category":"species","reportAsSpeciesCode":"thbsee1","reportAsCategory":"species","showSpeciesPageLink":true},"values":[0.0,0.0,0.0,0.0,0.0,0.0,0.0,0.0,0.0,0.0,0.0,0.0,0.0,0.0,0.0,0.0,0.0,0.0,0.0,0.0,0.0,0.0,0.0,0.0,0.0,0.0,0.0,0.0,0.0,0.0,0.0,0.0,0.0,0.0,0.0,0.0,1.0,0.0,0.0,0.0,0.0,0.0,0.0,0.0,0.0,0.0,0.0,0.0],"prettyValues":["0%","0%","0%","0%","0%","0%","0%","0%","0%","0%","0%","0%","0%","0%","0%","0%","0%","0%","0%","0%","0%","0%","0%","0%","0%","0%","0%","0%","0%","0%","0%","0%","0%","0%","0%","0%","100%","0%","0%","0%","0%","0%","0%","0%","0%","0%","0%","0%"],"values_N":[0,0,0,0,0,0,0,0,0,0,0,0,0,0,0,0,0,0,0,0,0,0,0,0,0,0,0,0,0,0,0,0,0,0,0,0,1,0,0,0,0,0,0,0,0,0,0,0],"buckets":[-1,-1,-1,-1,-1,-1,-1,-1,-1,-1,-1,-1,-1,-1,-1,-1,-1,-1,-1,-1,-1,-1,-1,-1,-1,-1,-1,-1,-1,-1,-1,-1,-1,-1,-1,-1,9,-1,-1,-1,-1,-1,-1,-1,-1,-1,-1,-1],"speciesCode":"thbsee1","name":"Thick-billed Seedeater"}],"numSpecies":82,"numTaxa":82}